Workbook

Sheet Assumptions
A1: Mobile Money & Airtime Kiosk — Daily Transactions Model (5 Years)
A2: All monetary values in Ugandan Shillings (UGX). Blue cells are editable inputs; black cells are calculated.
A4: 1. SIMULATION PERIOD
A5: Start date | B5: 46023
A6: End date | B6: 47848
A7: Number of days simulated | B7: =B6-B5+1 -> 1826
A9: 2. INITIAL (STARTUP) CAPITAL
A10: Float capital (mobile money agent line) | B10: 3000000
A11: Initial airtime / data bundle stock | B11: 500000
A12: Kiosk setup (structure, signage, stool, umbrella) | B12: 800000
A13: Rent deposit (advance) | B13: 300000
A14: Equipment (phone, register book, solar charger, POS) | B14: 400000
A15: TOTAL INITIAL INVESTMENT (Starting Capital) | B15: =SUM(B10:B14) -> 5000000
A17: 3. MOBILE MONEY REVENUE DRIVERS
A18: Starting mobile money transactions / month (baseline) | B18: 500 | C18: Forecast given in the scenario
A19: Equivalent starting MM transactions / day | B19: =B18/30.44 -> 16.425756 | C19: Baseline month figure spread over an average 30.44-day month
A20: Monthly transaction growth rate — Year 1 | B20: 0.02
A21: Monthly transaction growth rate — Year 2 onward | B21: 0.005
A22: Equivalent daily growth rate — Year 1 | B22: =(1+B20)^(1/30.44)-1 -> 0.00065075788 | C22: (1+monthly rate)^(1/30.44) - 1
A23: Equivalent daily growth rate — Year 2 onward | B23: =(1+B21)^(1/30.44)-1 -> 0.0001638617
A24: Average commission earned per transaction (UGX) | B24: 600
A26: 4. AIRTIME / DATA BUNDLE REVENUE DRIVERS
A27: Starting airtime/data transactions / month (baseline) | B27: 400
A28: Equivalent starting airtime transactions / day | B28: =B27/30.44 -> 13.140604
A29: Monthly airtime transaction growth rate | B29: 0.01
A30: Equivalent daily airtime growth rate | B30: =(1+B29)^(1/30.44)-1 -> 0.00032693684
A31: Average markup profit per airtime/data sale (UGX) | B31: 300
A33: 5. DAY-OF-WEEK EFFECT
A34: Weekend transaction multiplier (Sat & Sun) | B34: 0.6 | C34: Kiosk clientele is students/staff, so weekend footfall is lighter
A35: Weekday transaction multiplier (Mon-Fri) | B35: 1
A37: 6. MONTHLY OPERATING COSTS (booked on the 1st of each calendar month)
A38: Kiosk rent | B38: 150000
A39: Transport for float top-up | B39: 40000
A40: Agent line / mobile money service charges | B40: 30000
A41: Utilities (phone charging, lighting) | B41: 20000
A42: Attendant wage (starts calendar Month 13) | B42: 150000
A43: Miscellaneous / contingency | B43: 20000
A45: 7. OTHER
A46: Monthly cost inflation (applied from calendar Month 13) | B46: 0.003

Sheet Daily Ledger
A1: Day # | B1: Date | C1: Sim Year | D1: Calendar Month # | E1: Day of Week | F1: Weekday Multiplier | G1: Cost Inflation Factor | H1: MM Transactions (trend) | I1: MM Transactions (actual) | J1: Commission Revenue | K1: Airtime Transactions (trend) | L1: Airtime Transactions (actual) | M1: Airtime Revenue | N1: Total Daily Revenue | O1: Rent | P1: Transport | Q1: Agent Charges | R1: Utilities | S1: Wage | T1: Misc | U1: Total Daily Costs | V1: Net Daily Profit | W1: Cumulative Net Cash Position | X1: Breakeven Reached?
A2: 1 | B2: =Assumptions!B5 -> 46023 | C2: =MIN(ROUNDUP(A2/365,0),5) -> 1 | D2: =DATEDIF(Assumptions!B5,B2,"m")+1 -> 1 | E2: =TEXT(B2,"ddd") -> Thu | F2: =IF(WEEKDAY(B2,2)>=6,Assumptions!B34,Assumptions!B35) -> 1 | G2: =IF(D2>=13,(1+Assumptions!B46)^(D2-12),1) -> 1 | H2: =Assumptions!B19 -> 16.425756 | I2: =ROUND(H2*F2,0) -> 16 | J2: =I2*Assumptions!B24 -> 9600 | K2: =Assumptions!B28 -> 13.140604 | L2: =ROUND(K2*F2,0) -> 13 | M2: =L2*Assumptions!B31 -> 3900 | N2: =J2+M2 -> 13500 | O2: =IF(DAY(B2)=1,Assumptions!B38*G2,0) -> 150000 | P2: =IF(DAY(B2)=1,Assumptions!B39*G2,0) -> 40000 | Q2: =IF(DAY(B2)=1,Assumptions!B40*G2,0) -> 30000 | R2: =IF(DAY(B2)=1,Assumptions!B41*G2,0) -> 20000 | S2: =IF(AND(DAY(B2)=1,D2>=13),Assumptions!B42*G2,0) -> 0 | T2: =IF(DAY(B2)=1,Assumptions!B43*G2,0) -> 20000 | U2: =SUM(O2:T2) -> 260000 | V2: =N2-U2 -> -246500 | W2: =-Assumptions!B15+V2 -> -5246500 | X2: =IF(W2>=0,"YES","No") -> No
A3: 2 | B3: =B2+1 -> 46024 | C3: =MIN(ROUNDUP(A3/365,0),5) -> 1 | D3: =DATEDIF(Assumptions!B5,B3,"m")+1 -> 1 | E3: =TEXT(B3,"ddd") -> Fri | F3: =IF(WEEKDAY(B3,2)>=6,Assumptions!B34,Assumptions!B35) -> 1 | G3: =IF(D3>=13,(1+Assumptions!B46)^(D3-12),1) -> 1 | H3: =H2*(1+IF(C3=1,Assumptions!B22,Assumptions!B23)) -> 16.436445 | I3: =ROUND(H3*F3,0) -> 16 | J3: =I3*Assumptions!B24 -> 9600 | K3: =K2*(1+Assumptions!B30) -> 13.144901 | L3: =ROUND(K3*F3,0) -> 13 | M3: =L3*Assumptions!B31 -> 3900 | N3: =J3+M3 -> 13500 | O3: =IF(DAY(B3)=1,Assumptions!B38*G3,0) -> 0 | P3: =IF(DAY(B3)=1,Assumptions!B39*G3,0) -> 0 | Q3: =IF(DAY(B3)=1,Assumptions!B40*G3,0) -> 0 | R3: =IF(DAY(B3)=1,Assumptions!B41*G3,0) -> 0 | S3: =IF(AND(DAY(B3)=1,D3>=13),Assumptions!B42*G3,0) -> 0 | T3: =IF(DAY(B3)=1,Assumptions!B43*G3,0) -> 0 | U3: =SUM(O3:T3) -> 0 | V3: =N3-U3 -> 13500 | W3: =W2+V3 -> -5233000 | X3: =IF(W3>=0,"YES","No") -> No
A4: 3 | B4: =B3+1 -> 46025 | C4: =MIN(ROUNDUP(A4/365,0),5) -> 1 | D4: =DATEDIF(Assumptions!B5,B4,"m")+1 -> 1 | E4: =TEXT(B4,"ddd") -> Sat | F4: =IF(WEEKDAY(B4,2)>=6,Assumptions!B34,Assumptions!B35) -> 0.6 | G4: =IF(D4>=13,(1+Assumptions!B46)^(D4-12),1) -> 1 | H4: =H3*(1+IF(C4=1,Assumptions!B22,Assumptions!B23)) -> 16.447141 | I4: =ROUND(H4*F4,0) -> 10 | J4: =I4*Assumptions!B24 -> 6000 | K4: =K3*(1+Assumptions!B30) -> 13.149198 | L4: =ROUND(K4*F4,0) -> 8 | M4: =L4*Assumptions!B31 -> 2400 | N4: =J4+M4 -> 8400 | O4: =IF(DAY(B4)=1,Assumptions!B38*G4,0) -> 0 | P4: =IF(DAY(B4)=1,Assumptions!B39*G4,0) -> 0 | Q4: =IF(DAY(B4)=1,Assumptions!B40*G4,0) -> 0 | R4: =IF(DAY(B4)=1,Assumptions!B41*G4,0) -> 0 | S4: =IF(AND(DAY(B4)=1,D4>=13),Assumptions!B42*G4,0) -> 0 | T4: =IF(DAY(B4)=1,Assumptions!B43*G4,0) -> 0 | U4: =SUM(O4:T4) -> 0 | V4: =N4-U4 -> 8400 | W4: =W3+V4 -> -5224600 | X4: =IF(W4>=0,"YES","No") -> No
A5: 4 | B5: =B4+1 -> 46026 | C5: =MIN(ROUNDUP(A5/365,0),5) -> 1 | D5: =DATEDIF(Assumptions!B5,B5,"m")+1 -> 1 | E5: =TEXT(B5,"ddd") -> Sun | F5: =IF(WEEKDAY(B5,2)>=6,Assumptions!B34,Assumptions!B35) -> 0.6 | G5: =IF(D5>=13,(1+Assumptions!B46)^(D5-12),1) -> 1 | H5: =H4*(1+IF(C5=1,Assumptions!B22,Assumptions!B23)) -> 16.457844 | I5: =ROUND(H5*F5,0) -> 10 | J5: =I5*Assumptions!B24 -> 6000 | K5: =K4*(1+Assumptions!B30) -> 13.153497 | L5: =ROUND(K5*F5,0) -> 8 | M5: =L5*Assumptions!B31 -> 2400 | N5: =J5+M5 -> 8400 | O5: =IF(DAY(B5)=1,Assumptions!B38*G5,0) -> 0 | P5: =IF(DAY(B5)=1,Assumptions!B39*G5,0) -> 0 | Q5: =IF(DAY(B5)=1,Assumptions!B40*G5,0) -> 0 | R5: =IF(DAY(B5)=1,Assumptions!B41*G5,0) -> 0 | S5: =IF(AND(DAY(B5)=1,D5>=13),Assumptions!B42*G5,0) -> 0 | T5: =IF(DAY(B5)=1,Assumptions!B43*G5,0) -> 0 | U5: =SUM(O5:T5) -> 0 | V5: =N5-U5 -> 8400 | W5: =W4+V5 -> -5216200 | X5: =IF(W5>=0,"YES","No") -> No
A6: 5 | B6: =B5+1 -> 46027 | C6: =MIN(ROUNDUP(A6/365,0),5) -> 1 | D6: =DATEDIF(Assumptions!B5,B6,"m")+1 -> 1 | E6: =TEXT(B6,"ddd") -> Mon | F6: =IF(WEEKDAY(B6,2)>=6,Assumptions!B34,Assumptions!B35) -> 1 | G6: =IF(D6>=13,(1+Assumptions!B46)^(D6-12),1) -> 1 | H6: =H5*(1+IF(C6=1,Assumptions!B22,Assumptions!B23)) -> 16.468554 | I6: =ROUND(H6*F6,0) -> 16 | J6: =I6*Assumptions!B24 -> 9600 | K6: =K5*(1+Assumptions!B30) -> 13.157797 | L6: =ROUND(K6*F6,0) -> 13 | M6: =L6*Assumptions!B31 -> 3900 | N6: =J6+M6 -> 13500 | O6: =IF(DAY(B6)=1,Assumptions!B38*G6,0) -> 0 | P6: =IF(DAY(B6)=1,Assumptions!B39*G6,0) -> 0 | Q6: =IF(DAY(B6)=1,Assumptions!B40*G6,0) -> 0 | R6: =IF(DAY(B6)=1,Assumptions!B41*G6,0) -> 0 | S6: =IF(AND(DAY(B6)=1,D6>=13),Assumptions!B42*G6,0) -> 0 | T6: =IF(DAY(B6)=1,Assumptions!B43*G6,0) -> 0 | U6: =SUM(O6:T6) -> 0 | V6: =N6-U6 -> 13500 | W6: =W5+V6 -> -5202700 | X6: =IF(W6>=0,"YES","No") -> No
A7: 6 | B7: =B6+1 -> 46028 | C7: =MIN(ROUNDUP(A7/365,0),5) -> 1 | D7: =DATEDIF(Assumptions!B5,B7,"m")+1 -> 1 | E7: =TEXT(B7,"ddd") -> Tue | F7: =IF(WEEKDAY(B7,2)>=6,Assumptions!B34,Assumptions!B35) -> 1 | G7: =IF(D7>=13,(1+Assumptions!B46)^(D7-12),1) -> 1 | H7: =H6*(1+IF(C7=1,Assumptions!B22,Assumptions!B23)) -> 16.479271 | I7: =ROUND(H7*F7,0) -> 16 | J7: =I7*Assumptions!B24 -> 9600 | K7: =K6*(1+Assumptions!B30) -> 13.162099 | L7: =ROUND(K7*F7,0) -> 13 | M7: =L7*Assumptions!B31 -> 3900 | N7: =J7+M7 -> 13500 | O7: =IF(DAY(B7)=1,Assumptions!B38*G7,0) -> 0 | P7: =IF(DAY(B7)=1,Assumptions!B39*G7,0) -> 0 | Q7: =IF(DAY(B7)=1,Assumptions!B40*G7,0) -> 0 | R7: =IF(DAY(B7)=1,Assumptions!B41*G7,0) -> 0 | S7: =IF(AND(DAY(B7)=1,D7>=13),Assumptions!B42*G7,0) -> 0 | T7: =IF(DAY(B7)=1,Assumptions!B43*G7,0) -> 0 | U7: =SUM(O7:T7) -> 0 | V7: =N7-U7 -> 13500 | W7: =W6+V7 -> -5189200 | X7: =IF(W7>=0,"YES","No") -> No
A8: 7 | B8: =B7+1 -> 46029 | C8: =MIN(ROUNDUP(A8/365,0),5) -> 1 | D8: =DATEDIF(Assumptions!B5,B8,"m")+1 -> 1 | E8: =TEXT(B8,"ddd") -> Wed | F8: =IF(WEEKDAY(B8,2)>=6,Assumptions!B34,Assumptions!B35) -> 1 | G8: =IF(D8>=13,(1+Assumptions!B46)^(D8-12),1) -> 1 | H8: =H7*(1+IF(C8=1,Assumptions!B22,Assumptions!B23)) -> 16.489995 | I8: =ROUND(H8*F8,0) -> 16 | J8: =I8*Assumptions!B24 -> 9600 | K8: =K7*(1+Assumptions!B30) -> 13.166402 | L8: =ROUND(K8*F8,0) -> 13 | M8: =L8*Assumptions!B31 -> 3900 | N8: =J8+M8 -> 13500 | O8: =IF(DAY(B8)=1,Assumptions!B38*G8,0) -> 0 | P8: =IF(DAY(B8)=1,Assumptions!B39*G8,0) -> 0 | Q8: =IF(DAY(B8)=1,Assumptions!B40*G8,0) -> 0 | R8: =IF(DAY(B8)=1,Assumptions!B41*G8,0) -> 0 | S8: =IF(AND(DAY(B8)=1,D8>=13),Assumptions!B42*G8,0) -> 0 | T8: =IF(DAY(B8)=1,Assumptions!B43*G8,0) -> 0 | U8: =SUM(O8:T8) -> 0 | V8: =N8-U8 -> 13500 | W8: =W7+V8 -> -5175700 | X8: =IF(W8>=0,"YES","No") -> No
A9: 8 | B9: =B8+1 -> 46030 | C9: =MIN(ROUNDUP(A9/365,0),5) -> 1 | D9: =DATEDIF(Assumptions!B5,B9,"m")+1 -> 1 | E9: =TEXT(B9,"ddd") -> Thu | F9: =IF(WEEKDAY(B9,2)>=6,Assumptions!B34,Assumptions!B35) -> 1 | G9: =IF(D9>=13,(1+Assumptions!B46)^(D9-12),1) -> 1 | H9: =H8*(1+IF(C9=1,Assumptions!B22,Assumptions!B23)) -> 16.500726 | I9: =ROUND(H9*F9,0) -> 17 | J9: =I9*Assumptions!B24 -> 10200 | K9: =K8*(1+Assumptions!B30) -> 13.170707 | L9: =ROUND(K9*F9,0) -> 13 | M9: =L9*Assumptions!B31 -> 3900 | N9: =J9+M9 -> 14100 | O9: =IF(DAY(B9)=1,Assumptions!B38*G9,0) -> 0 | P9: =IF(DAY(B9)=1,Assumptions!B39*G9,0) -> 0 | Q9: =IF(DAY(B9)=1,Assumptions!B40*G9,0) -> 0 | R9: =IF(DAY(B9)=1,Assumptions!B41*G9,0) -> 0 | S9: =IF(AND(DAY(B9)=1,D9>=13),Assumptions!B42*G9,0) -> 0 | T9: =IF(DAY(B9)=1,Assumptions!B43*G9,0) -> 0 | U9: =SUM(O9:T9) -> 0 | V9: =N9-U9 -> 14100 | W9: =W8+V9 -> -5161600 | X9: =IF(W9>=0,"YES","No") -> No
A10: 9 | B10: =B9+1 -> 46031 | C10: =MIN(ROUNDUP(A10/365,0),5) -> 1 | D10: =DATEDIF(Assumptions!B5,B10,"m")+1 -> 1 | E10: =TEXT(B10,"ddd") -> Fri | F10: =IF(WEEKDAY(B10,2)>=6,Assumptions!B34,Assumptions!B35) -> 1 | G10: =IF(D10>=13,(1+Assumptions!B46)^(D10-12),1) -> 1 | H10: =H9*(1+IF(C10=1,Assumptions!B22,Assumptions!B23)) -> 16.511464 | I10: =ROUND(H10*F10,0) -> 17 | J10: =I10*Assumptions!B24 -> 10200 | K10: =K9*(1+Assumptions!B30) -> 13.175013 | L10: =ROUND(K10*F10,0) -> 13 | M10: =L10*Assumptions!B31 -> 3900 | N10: =J10+M10 -> 14100 | O10: =IF(DAY(B10)=1,Assumptions!B38*G10,0) -> 0 | P10: =IF(DAY(B10)=1,Assumptions!B39*G10,0) -> 0 | Q10: =IF(DAY(B10)=1,Assumptions!B40*G10,0) -> 0 | R10: =IF(DAY(B10)=1,Assumptions!B41*G10,0) -> 0 | S10: =IF(AND(DAY(B10)=1,D10>=13),Assumptions!B42*G10,0) -> 0 | T10: =IF(DAY(B10)=1,Assumptions!B43*G10,0) -> 0 | U10: =SUM(O10:T10) -> 0 | V10: =N10-U10 -> 14100 | W10: =W9+V10 -> -5147500 | X10: =IF(W10>=0,"YES","No") -> No
A11: 10 | B11: =B10+1 -> 46032 | C11: =MIN(ROUNDUP(A11/365,0),5) -> 1 | D11: =DATEDIF(Assumptions!B5,B11,"m")+1 -> 1 | E11: =TEXT(B11,"ddd") -> Sat | F11: =IF(WEEKDAY(B11,2)>=6,Assumptions!B34,Assumptions!B35) -> 0.6 | G11: =IF(D11>=13,(1+Assumptions!B46)^(D11-12),1) -> 1 | H11: =H10*(1+IF(C11=1,Assumptions!B22,Assumptions!B23)) -> 16.522209 | I11: =ROUND(H11*F11,0) -> 10 | J11: =I11*Assumptions!B24 -> 6000 | K11: =K10*(1+Assumptions!B30) -> 13.17932 | L11: =ROUND(K11*F11,0) -> 8 | M11: =L11*Assumptions!B31 -> 2400 | N11: =J11+M11 -> 8400 | O11: =IF(DAY(B11)=1,Assumptions!B38*G11,0) -> 0 | P11: =IF(DAY(B11)=1,Assumptions!B39*G11,0) -> 0 | Q11: =IF(DAY(B11)=1,Assumptions!B40*G11,0) -> 0 | R11: =IF(DAY(B11)=1,Assumptions!B41*G11,0) -> 0 | S11: =IF(AND(DAY(B11)=1,D11>=13),Assumptions!B42*G11,0) -> 0 | T11: =IF(DAY(B11)=1,Assumptions!B43*G11,0) -> 0 | U11: =SUM(O11:T11) -> 0 | V11: =N11-U11 -> 8400 | W11: =W10+V11 -> -5139100 | X11: =IF(W11>=0,"YES","No") -> No
A12: 11 | B12: =B11+1 -> 46033 | C12: =MIN(ROUNDUP(A12/365,0),5) -> 1 | D12: =DATEDIF(Assumptions!B5,B12,"m")+1 -> 1 | E12: =TEXT(B12,"ddd") -> Sun | F12: =IF(WEEKDAY(B12,2)>=6,Assumptions!B34,Assumptions!B35) -> 0.6 | G12: =IF(D12>=13,(1+Assumptions!B46)^(D12-12),1) -> 1 | H12: =H11*(1+IF(C12=1,Assumptions!B22,Assumptions!B23)) -> 16.532961 | I12: =ROUND(H12*F12,0) -> 10 | J12: =I12*Assumptions!B24 -> 6000 | K12: =K11*(1+Assumptions!B30) -> 13.183629 | L12: =ROUND(K12*F12,0) -> 8 | M12: =L12*Assumptions!B31 -> 2400 | N12: =J12+M12 -> 8400 | O12: =IF(DAY(B12)=1,Assumptions!B38*G12,0) -> 0 | P12: =IF(DAY(B12)=1,Assumptions!B39*G12,0) -> 0 | Q12: =IF(DAY(B12)=1,Assumptions!B40*G12,0) -> 0 | R12: =IF(DAY(B12)=1,Assumptions!B41*G12,0) -> 0 | S12: =IF(AND(DAY(B12)=1,D12>=13),Assumptions!B42*G12,0) -> 0 | T12: =IF(DAY(B12)=1,Assumptions!B43*G12,0) -> 0 | U12: =SUM(O12:T12) -> 0 | V12: =N12-U12 -> 8400 | W12: =W11+V12 -> -5130700 | X12: =IF(W12>=0,"YES","No") -> No
A13: 12 | B13: =B12+1 -> 46034 | C13: =MIN(ROUNDUP(A13/365,0),5) -> 1 | D13: =DATEDIF(Assumptions!B5,B13,"m")+1 -> 1 | E13: =TEXT(B13,"ddd") -> Mon | F13: =IF(WEEKDAY(B13,2)>=6,Assumptions!B34,Assumptions!B35) -> 1 | G13: =IF(D13>=13,(1+Assumptions!B46)^(D13-12),1) -> 1 | H13: =H12*(1+IF(C13=1,Assumptions!B22,Assumptions!B23)) -> 16.54372 | I13: =ROUND(H13*F13,0) -> 17 | J13: =I13*Assumptions!B24 -> 10200 | K13: =K12*(1+Assumptions!B30) -> 13.187939 | L13: =ROUND(K13*F13,0) -> 13 | M13: =L13*Assumptions!B31 -> 3900 | N13: =J13+M13 -> 14100 | O13: =IF(DAY(B13)=1,Assumptions!B38*G13,0) -> 0 | P13: =IF(DAY(B13)=1,Assumptions!B39*G13,0) -> 0 | Q13: =IF(DAY(B13)=1,Assumptions!B40*G13,0) -> 0 | R13: =IF(DAY(B13)=1,Assumptions!B41*G13,0) -> 0 | S13: =IF(AND(DAY(B13)=1,D13>=13),Assumptions!B42*G13,0) -> 0 | T13: =IF(DAY(B13)=1,Assumptions!B43*G13,0) -> 0 | U13: =SUM(O13:T13) -> 0 | V13: =N13-U13 -> 14100 | W13: =W12+V13 -> -5116600 | X13: =IF(W13>=0,"YES","No") -> No
A14: 13 | B14: =B13+1 -> 46035 | C14: =MIN(ROUNDUP(A14/365,0),5) -> 1 | D14: =DATEDIF(Assumptions!B5,B14,"m")+1 -> 1 | E14: =TEXT(B14,"ddd") -> Tue | F14: =IF(WEEKDAY(B14,2)>=6,Assumptions!B34,Assumptions!B35) -> 1 | G14: =IF(D14>=13,(1+Assumptions!B46)^(D14-12),1) -> 1 | H14: =H13*(1+IF(C14=1,Assumptions!B22,Assumptions!B23)) -> 16.554486 | I14: =ROUND(H14*F14,0) -> 17 | J14: =I14*Assumptions!B24 -> 10200 | K14: =K13*(1+Assumptions!B30) -> 13.192251 | L14: =ROUND(K14*F14,0) -> 13 | M14: =L14*Assumptions!B31 -> 3900 | N14: =J14+M14 -> 14100 | O14: =IF(DAY(B14)=1,Assumptions!B38*G14,0) -> 0 | P14: =IF(DAY(B14)=1,Assumptions!B39*G14,0) -> 0 | Q14: =IF(DAY(B14)=1,Assumptions!B40*G14,0) -> 0 | R14: =IF(DAY(B14)=1,Assumptions!B41*G14,0) -> 0 | S14: =IF(AND(DAY(B14)=1,D14>=13),Assumptions!B42*G14,0) -> 0 | T14: =IF(DAY(B14)=1,Assumptions!B43*G14,0) -> 0 | U14: =SUM(O14:T14) -> 0 | V14: =N14-U14 -> 14100 | W14: =W13+V14 -> -5102500 | X14: =IF(W14>=0,"YES","No") -> No
A15: 14 | B15: =B14+1 -> 46036 | C15: =MIN(ROUNDUP(A15/365,0),5) -> 1 | D15: =DATEDIF(Assumptions!B5,B15,"m")+1 -> 1 | E15: =TEXT(B15,"ddd") -> Wed | F15: =IF(WEEKDAY(B15,2)>=6,Assumptions!B34,Assumptions!B35) -> 1 | G15: =IF(D15>=13,(1+Assumptions!B46)^(D15-12),1) -> 1 | H15: =H14*(1+IF(C15=1,Assumptions!B22,Assumptions!B23)) -> 16.565259 | I15: =ROUND(H15*F15,0) -> 17 | J15: =I15*Assumptions!B24 -> 10200 | K15: =K14*(1+Assumptions!B30) -> 13.196564 | L15: =ROUND(K15*F15,0) -> 13 | M15: =L15*Assumptions!B31 -> 3900 | N15: =J15+M15 -> 14100 | O15: =IF(DAY(B15)=1,Assumptions!B38*G15,0) -> 0 | P15: =IF(DAY(B15)=1,Assumptions!B39*G15,0) -> 0 | Q15: =IF(DAY(B15)=1,Assumptions!B40*G15,0) -> 0 | R15: =IF(DAY(B15)=1,Assumptions!B41*G15,0) -> 0 | S15: =IF(AND(DAY(B15)=1,D15>=13),Assumptions!B42*G15,0) -> 0 | T15: =IF(DAY(B15)=1,Assumptions!B43*G15,0) -> 0 | U15: =SUM(O15:T15) -> 0 | V15: =N15-U15 -> 14100 | W15: =W14+V15 -> -5088400 | X15: =IF(W15>=0,"YES","No") -> No
A16: 15 | B16: =B15+1 -> 46037 | C16: =MIN(ROUNDUP(A16/365,0),5) -> 1 | D16: =DATEDIF(Assumptions!B5,B16,"m")+1 -> 1 | E16: =TEXT(B16,"ddd") -> Thu | F16: =IF(WEEKDAY(B16,2)>=6,Assumptions!B34,Assumptions!B35) -> 1 | G16: =IF(D16>=13,(1+Assumptions!B46)^(D16-12),1) -> 1 | H16: =H15*(1+IF(C16=1,Assumptions!B22,Assumptions!B23)) -> 16.576039 | I16: =ROUND(H16*F16,0) -> 17 | J16: =I16*Assumptions!B24 -> 10200 | K16: =K15*(1+Assumptions!B30) -> 13.200879 | L16: =ROUND(K16*F16,0) -> 13 | M16: =L16*Assumptions!B31 -> 3900 | N16: =J16+M16 -> 14100 | O16: =IF(DAY(B16)=1,Assumptions!B38*G16,0) -> 0 | P16: =IF(DAY(B16)=1,Assumptions!B39*G16,0) -> 0 | Q16: =IF(DAY(B16)=1,Assumptions!B40*G16,0) -> 0 | R16: =IF(DAY(B16)=1,Assumptions!B41*G16,0) -> 0 | S16: =IF(AND(DAY(B16)=1,D16>=13),Assumptions!B42*G16,0) -> 0 | T16: =IF(DAY(B16)=1,Assumptions!B43*G16,0) -> 0 | U16: =SUM(O16:T16) -> 0 | V16: =N16-U16 -> 14100 | W16: =W15+V16 -> -5074300 | X16: =IF(W16>=0,"YES","No") -> No
A17: 16 | B17: =B16+1 -> 46038 | C17: =MIN(ROUNDUP(A17/365,0),5) -> 1 | D17: =DATEDIF(Assumptions!B5,B17,"m")+1 -> 1 | E17: =TEXT(B17,"ddd") -> Fri | F17: =IF(WEEKDAY(B17,2)>=6,Assumptions!B34,Assumptions!B35) -> 1 | G17: =IF(D17>=13,(1+Assumptions!B46)^(D17-12),1) -> 1 | H17: =H16*(1+IF(C17=1,Assumptions!B22,Assumptions!B23)) -> 16.586826 | I17: =ROUND(H17*F17,0) -> 17 | J17: =I17*Assumptions!B24 -> 10200 | K17: =K16*(1+Assumptions!B30) -> 13.205194 | L17: =ROUND(K17*F17,0) -> 13 | M17: =L17*Assumptions!B31 -> 3900 | N17: =J17+M17 -> 14100 | O17: =IF(DAY(B17)=1,Assumptions!B38*G17,0) -> 0 | P17: =IF(DAY(B17)=1,Assumptions!B39*G17,0) -> 0 | Q17: =IF(DAY(B17)=1,Assumptions!B40*G17,0) -> 0 | R17: =IF(DAY(B17)=1,Assumptions!B41*G17,0) -> 0 | S17: =IF(AND(DAY(B17)=1,D17>=13),Assumptions!B42*G17,0) -> 0 | T17: =IF(DAY(B17)=1,Assumptions!B43*G17,0) -> 0 | U17: =SUM(O17:T17) -> 0 | V17: =N17-U17 -> 14100 | W17: =W16+V17 -> -5060200 | X17: =IF(W17>=0,"YES","No") -> No
A18: 17 | B18: =B17+1 -> 46039 | C18: =MIN(ROUNDUP(A18/365,0),5) -> 1 | D18: =DATEDIF(Assumptions!B5,B18,"m")+1 -> 1 | E18: =TEXT(B18,"ddd") -> Sat | F18: =IF(WEEKDAY(B18,2)>=6,Assumptions!B34,Assumptions!B35) -> 0.6 | G18: =IF(D18>=13,(1+Assumptions!B46)^(D18-12),1) -> 1 | H18: =H17*(1+IF(C18=1,Assumptions!B22,Assumptions!B23)) -> 16.59762 | I18: =ROUND(H18*F18,0) -> 10 | J18: =I18*Assumptions!B24 -> 6000 | K18: =K17*(1+Assumptions!B30) -> 13.209512 | L18: =ROUND(K18*F18,0) -> 8 | M18: =L18*Assumptions!B31 -> 2400 | N18: =J18+M18 -> 8400 | O18: =IF(DAY(B18)=1,Assumptions!B38*G18,0) -> 0 | P18: =IF(DAY(B18)=1,Assumptions!B39*G18,0) -> 0 | Q18: =IF(DAY(B18)=1,Assumptions!B40*G18,0) -> 0 | R18: =IF(DAY(B18)=1,Assumptions!B41*G18,0) -> 0 | S18: =IF(AND(DAY(B18)=1,D18>=13),Assumptions!B42*G18,0) -> 0 | T18: =IF(DAY(B18)=1,Assumptions!B43*G18,0) -> 0 | U18: =SUM(O18:T18) -> 0 | V18: =N18-U18 -> 8400 | W18: =W17+V18 -> -5051800 | X18: =IF(W18>=0,"YES","No") -> No
A19: 18 | B19: =B18+1 -> 46040 | C19: =MIN(ROUNDUP(A19/365,0),5) -> 1 | D19: =DATEDIF(Assumptions!B5,B19,"m")+1 -> 1 | E19: =TEXT(B19,"ddd") -> Sun | F19: =IF(WEEKDAY(B19,2)>=6,Assumptions!B34,Assumptions!B35) -> 0.6 | G19: =IF(D19>=13,(1+Assumptions!B46)^(D19-12),1) -> 1 | H19: =H18*(1+IF(C19=1,Assumptions!B22,Assumptions!B23)) -> 16.608421 | I19: =ROUND(H19*F19,0) -> 10 | J19: =I19*Assumptions!B24 -> 6000 | K19: =K18*(1+Assumptions!B30) -> 13.21383 | L19: =ROUND(K19*F19,0) -> 8 | M19: =L19*Assumptions!B31 -> 2400 | N19: =J19+M19 -> 8400 | O19: =IF(DAY(B19)=1,Assumptions!B38*G19,0) -> 0 | P19: =IF(DAY(B19)=1,Assumptions!B39*G19,0) -> 0 | Q19: =IF(DAY(B19)=1,Assumptions!B40*G19,0) -> 0 | R19: =IF(DAY(B19)=1,Assumptions!B41*G19,0) -> 0 | S19: =IF(AND(DAY(B19)=1,D19>=13),Assumptions!B42*G19,0) -> 0 | T19: =IF(DAY(B19)=1,Assumptions!B43*G19,0) -> 0 | U19: =SUM(O19:T19) -> 0 | V19: =N19-U19 -> 8400 | W19: =W18+V19 -> -5043400 | X19: =IF(W19>=0,"YES","No") -> No
A20: 19 | B20: =B19+1 -> 46041 | C20: =MIN(ROUNDUP(A20/365,0),5) -> 1 | D20: =DATEDIF(Assumptions!B5,B20,"m")+1 -> 1 | E20: =TEXT(B20,"ddd") -> Mon | F20: =IF(WEEKDAY(B20,2)>=6,Assumptions!B34,Assumptions!B35) -> 1 | G20: =IF(D20>=13,(1+Assumptions!B46)^(D20-12),1) -> 1 | H20: =H19*(1+IF(C20=1,Assumptions!B22,Assumptions!B23)) -> 16.619229 | I20: =ROUND(H20*F20,0) -> 17 | J20: =I20*Assumptions!B24 -> 10200 | K20: =K19*(1+Assumptions!B30) -> 13.21815 | L20: =ROUND(K20*F20,0) -> 13 | M20: =L20*Assumptions!B31 -> 3900 | N20: =J20+M20 -> 14100 | O20: =IF(DAY(B20)=1,Assumptions!B38*G20,0) -> 0 | P20: =IF(DAY(B20)=1,Assumptions!B39*G20,0) -> 0 | Q20: =IF(DAY(B20)=1,Assumptions!B40*G20,0) -> 0 | R20: =IF(DAY(B20)=1,Assumptions!B41*G20,0) -> 0 | S20: =IF(AND(DAY(B20)=1,D20>=13),Assumptions!B42*G20,0) -> 0 | T20: =IF(DAY(B20)=1,Assumptions!B43*G20,0) -> 0 | U20: =SUM(O20:T20) -> 0 | V20: =N20-U20 -> 14100 | W20: =W19+V20 -> -5029300 | X20: =IF(W20>=0,"YES","No") -> No
A21: 20 | B21: =B20+1 -> 46042 | C21: =MIN(ROUNDUP(A21/365,0),5) -> 1 | D21: =DATEDIF(Assumptions!B5,B21,"m")+1 -> 1 | E21: =TEXT(B21,"ddd") -> Tue | F21: =IF(WEEKDAY(B21,2)>=6,Assumptions!B34,Assumptions!B35) -> 1 | G21: =IF(D21>=13,(1+Assumptions!B46)^(D21-12),1) -> 1 | H21: =H20*(1+IF(C21=1,Assumptions!B22,Assumptions!B23)) -> 16.630044 | I21: =ROUND(H21*F21,0) -> 17 | J21: =I21*Assumptions!B24 -> 10200 | K21: =K20*(1+Assumptions!B30) -> 13.222472 | L21: =ROUND(K21*F21,0) -> 13 | M21: =L21*Assumptions!B31 -> 3900 | N21: =J21+M21 -> 14100 | O21: =IF(DAY(B21)=1,Assumptions!B38*G21,0) -> 0 | P21: =IF(DAY(B21)=1,Assumptions!B39*G21,0) -> 0 | Q21: =IF(DAY(B21)=1,Assumptions!B40*G21,0) -> 0 | R21: =IF(DAY(B21)=1,Assumptions!B41*G21,0) -> 0 | S21: =IF(AND(DAY(B21)=1,D21>=13),Assumptions!B42*G21,0) -> 0 | T21: =IF(DAY(B21)=1,Assumptions!B43*G21,0) -> 0 | U21: =SUM(O21:T21) -> 0 | V21: =N21-U21 -> 14100 | W21: =W20+V21 -> -5015200 | X21: =IF(W21>=0,"YES","No") -> No
A22: 21 | B22: =B21+1 -> 46043 | C22: =MIN(ROUNDUP(A22/365,0),5) -> 1 | D22: =DATEDIF(Assumptions!B5,B22,"m")+1 -> 1 | E22: =TEXT(B22,"ddd") -> Wed | F22: =IF(WEEKDAY(B22,2)>=6,Assumptions!B34,Assumptions!B35) -> 1 | G22: =IF(D22>=13,(1+Assumptions!B46)^(D22-12),1) -> 1 | H22: =H21*(1+IF(C22=1,Assumptions!B22,Assumptions!B23)) -> 16.640866 | I22: =ROUND(H22*F22,0) -> 17 | J22: =I22*Assumptions!B24 -> 10200 | K22: =K21*(1+Assumptions!B30) -> 13.226795 | L22: =ROUND(K22*F22,0) -> 13 | M22: =L22*Assumptions!B31 -> 3900 | N22: =J22+M22 -> 14100 | O22: =IF(DAY(B22)=1,Assumptions!B38*G22,0) -> 0 | P22: =IF(DAY(B22)=1,Assumptions!B39*G22,0) -> 0 | Q22: =IF(DAY(B22)=1,Assumptions!B40*G22,0) -> 0 | R22: =IF(DAY(B22)=1,Assumptions!B41*G22,0) -> 0 | S22: =IF(AND(DAY(B22)=1,D22>=13),Assumptions!B42*G22,0) -> 0 | T22: =IF(DAY(B22)=1,Assumptions!B43*G22,0) -> 0 | U22: =SUM(O22:T22) -> 0 | V22: =N22-U22 -> 14100 | W22: =W21+V22 -> -5001100 | X22: =IF(W22>=0,"YES","No") -> No
A23: 22 | B23: =B22+1 -> 46044 | C23: =MIN(ROUNDUP(A23/365,0),5) -> 1 | D23: =DATEDIF(Assumptions!B5,B23,"m")+1 -> 1 | E23: =TEXT(B23,"ddd") -> Thu | F23: =IF(WEEKDAY(B23,2)>=6,Assumptions!B34,Assumptions!B35) -> 1 | G23: =IF(D23>=13,(1+Assumptions!B46)^(D23-12),1) -> 1 | H23: =H22*(1+IF(C23=1,Assumptions!B22,Assumptions!B23)) -> 16.651695 | I23: =ROUND(H23*F23,0) -> 17 | J23: =I23*Assumptions!B24 -> 10200 | K23: =K22*(1+Assumptions!B30) -> 13.231119 | L23: =ROUND(K23*F23,0) -> 13 | M23: =L23*Assumptions!B31 -> 3900 | N23: =J23+M23 -> 14100 | O23: =IF(DAY(B23)=1,Assumptions!B38*G23,0) -> 0 | P23: =IF(DAY(B23)=1,Assumptions!B39*G23,0) -> 0 | Q23: =IF(DAY(B23)=1,Assumptions!B40*G23,0) -> 0 | R23: =IF(DAY(B23)=1,Assumptions!B41*G23,0) -> 0 | S23: =IF(AND(DAY(B23)=1,D23>=13),Assumptions!B42*G23,0) -> 0 | T23: =IF(DAY(B23)=1,Assumptions!B43*G23,0) -> 0 | U23: =SUM(O23:T23) -> 0 | V23: =N23-U23 -> 14100 | W23: =W22+V23 -> -4987000 | X23: =IF(W23>=0,"YES","No") -> No
A24: 23 | B24: =B23+1 -> 46045 | C24: =MIN(ROUNDUP(A24/365,0),5) -> 1 | D24: =DATEDIF(Assumptions!B5,B24,"m")+1 -> 1 | E24: =TEXT(B24,"ddd") -> Fri | F24: =IF(WEEKDAY(B24,2)>=6,Assumptions!B34,Assumptions!B35) -> 1 | G24: =IF(D24>=13,(1+Assumptions!B46)^(D24-12),1) -> 1 | H24: =H23*(1+IF(C24=1,Assumptions!B22,Assumptions!B23)) -> 16.662532 | I24: =ROUND(H24*F24,0) -> 17 | J24: =I24*Assumptions!B24 -> 10200 | K24: =K23*(1+Assumptions!B30) -> 13.235445 | L24: =ROUND(K24*F24,0) -> 13 | M24: =L24*Assumptions!B31 -> 3900 | N24: =J24+M24 -> 14100 | O24: =IF(DAY(B24)=1,Assumptions!B38*G24,0) -> 0 | P24: =IF(DAY(B24)=1,Assumptions!B39*G24,0) -> 0 | Q24: =IF(DAY(B24)=1,Assumptions!B40*G24,0) -> 0 | R24: =IF(DAY(B24)=1,Assumptions!B41*G24,0) -> 0 | S24: =IF(AND(DAY(B24)=1,D24>=13),Assumptions!B42*G24,0) -> 0 | T24: =IF(DAY(B24)=1,Assumptions!B43*G24,0) -> 0 | U24: =SUM(O24:T24) -> 0 | V24: =N24-U24 -> 14100 | W24: =W23+V24 -> -4972900 | X24: =IF(W24>=0,"YES","No") -> No
A25: 24 | B25: =B24+1 -> 46046 | C25: =MIN(ROUNDUP(A25/365,0),5) -> 1 | D25: =DATEDIF(Assumptions!B5,B25,"m")+1 -> 1 | E25: =TEXT(B25,"ddd") -> Sat | F25: =IF(WEEKDAY(B25,2)>=6,Assumptions!B34,Assumptions!B35) -> 0.6 | G25: =IF(D25>=13,(1+Assumptions!B46)^(D25-12),1) -> 1 | H25: =H24*(1+IF(C25=1,Assumptions!B22,Assumptions!B23)) -> 16.673375 | I25: =ROUND(H25*F25,0) -> 10 | J25: =I25*Assumptions!B24 -> 6000 | K25: =K24*(1+Assumptions!B30) -> 13.239772 | L25: =ROUND(K25*F25,0) -> 8 | M25: =L25*Assumptions!B31 -> 2400 | N25: =J25+M25 -> 8400 | O25: =IF(DAY(B25)=1,Assumptions!B38*G25,0) -> 0 | P25: =IF(DAY(B25)=1,Assumptions!B39*G25,0) -> 0 | Q25: =IF(DAY(B25)=1,Assumptions!B40*G25,0) -> 0 | R25: =IF(DAY(B25)=1,Assumptions!B41*G25,0) -> 0 | S25: =IF(AND(DAY(B25)=1,D25>=13),Assumptions!B42*G25,0) -> 0 | T25: =IF(DAY(B25)=1,Assumptions!B43*G25,0) -> 0 | U25: =SUM(O25:T25) -> 0 | V25: =N25-U25 -> 8400 | W25: =W24+V25 -> -4964500 | X25: =IF(W25>=0,"YES","No") -> No
A26: 25 | B26: =B25+1 -> 46047 | C26: =MIN(ROUNDUP(A26/365,0),5) -> 1 | D26: =DATEDIF(Assumptions!B5,B26,"m")+1 -> 1 | E26: =TEXT(B26,"ddd") -> Sun | F26: =IF(WEEKDAY(B26,2)>=6,Assumptions!B34,Assumptions!B35) -> 0.6 | G26: =IF(D26>=13,(1+Assumptions!B46)^(D26-12),1) -> 1 | H26: =H25*(1+IF(C26=1,Assumptions!B22,Assumptions!B23)) -> 16.684225 | I26: =ROUND(H26*F26,0) -> 10 | J26: =I26*Assumptions!B24 -> 6000 | K26: =K25*(1+Assumptions!B30) -> 13.244101 | L26: =ROUND(K26*F26,0) -> 8 | M26: =L26*Assumptions!B31 -> 2400 | N26: =J26+M26 -> 8400 | O26: =IF(DAY(B26)=1,Assumptions!B38*G26,0) -> 0 | P26: =IF(DAY(B26)=1,Assumptions!B39*G26,0) -> 0 | Q26: =IF(DAY(B26)=1,Assumptions!B40*G26,0) -> 0 | R26: =IF(DAY(B26)=1,Assumptions!B41*G26,0) -> 0 | S26: =IF(AND(DAY(B26)=1,D26>=13),Assumptions!B42*G26,0) -> 0 | T26: =IF(DAY(B26)=1,Assumptions!B43*G26,0) -> 0 | U26: =SUM(O26:T26) -> 0 | V26: =N26-U26 -> 8400 | W26: =W25+V26 -> -4956100 | X26: =IF(W26>=0,"YES","No") -> No
A27: 26 | B27: =B26+1 -> 46048 | C27: =MIN(ROUNDUP(A27/365,0),5) -> 1 | D27: =DATEDIF(Assumptions!B5,B27,"m")+1 -> 1 | E27: =TEXT(B27,"ddd") -> Mon | F27: =IF(WEEKDAY(B27,2)>=6,Assumptions!B34,Assumptions!B35) -> 1 | G27: =IF(D27>=13,(1+Assumptions!B46)^(D27-12),1) -> 1 | H27: =H26*(1+IF(C27=1,Assumptions!B22,Assumptions!B23)) -> 16.695083 | I27: =ROUND(H27*F27,0) -> 17 | J27: =I27*Assumptions!B24 -> 10200 | K27: =K26*(1+Assumptions!B30) -> 13.248431 | L27: =ROUND(K27*F27,0) -> 13 | M27: =L27*Assumptions!B31 -> 3900 | N27: =J27+M27 -> 14100 | O27: =IF(DAY(B27)=1,Assumptions!B38*G27,0) -> 0 | P27: =IF(DAY(B27)=1,Assumptions!B39*G27,0) -> 0 | Q27: =IF(DAY(B27)=1,Assumptions!B40*G27,0) -> 0 | R27: =IF(DAY(B27)=1,Assumptions!B41*G27,0) -> 0 | S27: =IF(AND(DAY(B27)=1,D27>=13),Assumptions!B42*G27,0) -> 0 | T27: =IF(DAY(B27)=1,Assumptions!B43*G27,0) -> 0 | U27: =SUM(O27:T27) -> 0 | V27: =N27-U27 -> 14100 | W27: =W26+V27 -> -4942000 | X27: =IF(W27>=0,"YES","No") -> No
A28: 27 | B28: =B27+1 -> 46049 | C28: =MIN(ROUNDUP(A28/365,0),5) -> 1 | D28: =DATEDIF(Assumptions!B5,B28,"m")+1 -> 1 | E28: =TEXT(B28,"ddd") -> Tue | F28: =IF(WEEKDAY(B28,2)>=6,Assumptions!B34,Assumptions!B35) -> 1 | G28: =IF(D28>=13,(1+Assumptions!B46)^(D28-12),1) -> 1 | H28: =H27*(1+IF(C28=1,Assumptions!B22,Assumptions!B23)) -> 16.705947 | I28: =ROUND(H28*F28,0) -> 17 | J28: =I28*Assumptions!B24 -> 10200 | K28: =K27*(1+Assumptions!B30) -> 13.252762 | L28: =ROUND(K28*F28,0) -> 13 | M28: =L28*Assumptions!B31 -> 3900 | N28: =J28+M28 -> 14100 | O28: =IF(DAY(B28)=1,Assumptions!B38*G28,0) -> 0 | P28: =IF(DAY(B28)=1,Assumptions!B39*G28,0) -> 0 | Q28: =IF(DAY(B28)=1,Assumptions!B40*G28,0) -> 0 | R28: =IF(DAY(B28)=1,Assumptions!B41*G28,0) -> 0 | S28: =IF(AND(DAY(B28)=1,D28>=13),Assumptions!B42*G28,0) -> 0 | T28: =IF(DAY(B28)=1,Assumptions!B43*G28,0) -> 0 | U28: =SUM(O28:T28) -> 0 | V28: =N28-U28 -> 14100 | W28: =W27+V28 -> -4927900 | X28: =IF(W28>=0,"YES","No") -> No
A29: 28 | B29: =B28+1 -> 46050 | C29: =MIN(ROUNDUP(A29/365,0),5) -> 1 | D29: =DATEDIF(Assumptions!B5,B29,"m")+1 -> 1 | E29: =TEXT(B29,"ddd") -> Wed | F29: =IF(WEEKDAY(B29,2)>=6,Assumptions!B34,Assumptions!B35) -> 1 | G29: =IF(D29>=13,(1+Assumptions!B46)^(D29-12),1) -> 1 | H29: =H28*(1+IF(C29=1,Assumptions!B22,Assumptions!B23)) -> 16.716819 | I29: =ROUND(H29*F29,0) -> 17 | J29: =I29*Assumptions!B24 -> 10200 | K29: =K28*(1+Assumptions!B30) -> 13.257095 | L29: =ROUND(K29*F29,0) -> 13 | M29: =L29*Assumptions!B31 -> 3900 | N29: =J29+M29 -> 14100 | O29: =IF(DAY(B29)=1,Assumptions!B38*G29,0) -> 0 | P29: =IF(DAY(B29)=1,Assumptions!B39*G29,0) -> 0 | Q29: =IF(DAY(B29)=1,Assumptions!B40*G29,0) -> 0 | R29: =IF(DAY(B29)=1,Assumptions!B41*G29,0) -> 0 | S29: =IF(AND(DAY(B29)=1,D29>=13),Assumptions!B42*G29,0) -> 0 | T29: =IF(DAY(B29)=1,Assumptions!B43*G29,0) -> 0 | U29: =SUM(O29:T29) -> 0 | V29: =N29-U29 -> 14100 | W29: =W28+V29 -> -4913800 | X29: =IF(W29>=0,"YES","No") -> No
A30: 29 | B30: =B29+1 -> 46051 | C30: =MIN(ROUNDUP(A30/365,0),5) -> 1 | D30: =DATEDIF(Assumptions!B5,B30,"m")+1 -> 1 | E30: =TEXT(B30,"ddd") -> Thu | F30: =IF(WEEKDAY(B30,2)>=6,Assumptions!B34,Assumptions!B35) -> 1 | G30: =IF(D30>=13,(1+Assumptions!B46)^(D30-12),1) -> 1 | H30: =H29*(1+IF(C30=1,Assumptions!B22,Assumptions!B23)) -> 16.727697 | I30: =ROUND(H30*F30,0) -> 17 | J30: =I30*Assumptions!B24 -> 10200 | K30: =K29*(1+Assumptions!B30) -> 13.261429 | L30: =ROUND(K30*F30,0) -> 13 | M30: =L30*Assumptions!B31 -> 3900 | N30: =J30+M30 -> 14100 | O30: =IF(DAY(B30)=1,Assumptions!B38*G30,0) -> 0 | P30: =IF(DAY(B30)=1,Assumptions!B39*G30,0) -> 0 | Q30: =IF(DAY(B30)=1,Assumptions!B40*G30,0) -> 0 | R30: =IF(DAY(B30)=1,Assumptions!B41*G30,0) -> 0 | S30: =IF(AND(DAY(B30)=1,D30>=13),Assumptions!B42*G30,0) -> 0 | T30: =IF(DAY(B30)=1,Assumptions!B43*G30,0) -> 0 | U30: =SUM(O30:T30) -> 0 | V30: =N30-U30 -> 14100 | W30: =W29+V30 -> -4899700 | X30: =IF(W30>=0,"YES","No") -> No
A31: 30 | B31: =B30+1 -> 46052 | C31: =MIN(ROUNDUP(A31/365,0),5) -> 1 | D31: =DATEDIF(Assumptions!B5,B31,"m")+1 -> 1 | E31: =TEXT(B31,"ddd") -> Fri | F31: =IF(WEEKDAY(B31,2)>=6,Assumptions!B34,Assumptions!B35) -> 1 | G31: =IF(D31>=13,(1+Assumptions!B46)^(D31-12),1) -> 1 | H31: =H30*(1+IF(C31=1,Assumptions!B22,Assumptions!B23)) -> 16.738583 | I31: =ROUND(H31*F31,0) -> 17 | J31: =I31*Assumptions!B24 -> 10200 | K31: =K30*(1+Assumptions!B30) -> 13.265765 | L31: =ROUND(K31*F31,0) -> 13 | M31: =L31*Assumptions!B31 -> 3900 | N31: =J31+M31 -> 14100 | O31: =IF(DAY(B31)=1,Assumptions!B38*G31,0) -> 0 | P31: =IF(DAY(B31)=1,Assumptions!B39*G31,0) -> 0 | Q31: =IF(DAY(B31)=1,Assumptions!B40*G31,0) -> 0 | R31: =IF(DAY(B31)=1,Assumptions!B41*G31,0) -> 0 | S31: =IF(AND(DAY(B31)=1,D31>=13),Assumptions!B42*G31,0) -> 0 | T31: =IF(DAY(B31)=1,Assumptions!B43*G31,0) -> 0 | U31: =SUM(O31:T31) -> 0 | V31: =N31-U31 -> 14100 | W31: =W30+V31 -> -4885600 | X31: =IF(W31>=0,"YES","No") -> No
A32: 31 | B32: =B31+1 -> 46053 | C32: =MIN(ROUNDUP(A32/365,0),5) -> 1 | D32: =DATEDIF(Assumptions!B5,B32,"m")+1 -> 1 | E32: =TEXT(B32,"ddd") -> Sat | F32: =IF(WEEKDAY(B32,2)>=6,Assumptions!B34,Assumptions!B35) -> 0.6 | G32: =IF(D32>=13,(1+Assumptions!B46)^(D32-12),1) -> 1 | H32: =H31*(1+IF(C32=1,Assumptions!B22,Assumptions!B23)) -> 16.749476 | I32: =ROUND(H32*F32,0) -> 10 | J32: =I32*Assumptions!B24 -> 6000 | K32: =K31*(1+Assumptions!B30) -> 13.270102 | L32: =ROUND(K32*F32,0) -> 8 | M32: =L32*Assumptions!B31 -> 2400 | N32: =J32+M32 -> 8400 | O32: =IF(DAY(B32)=1,Assumptions!B38*G32,0) -> 0 | P32: =IF(DAY(B32)=1,Assumptions!B39*G32,0) -> 0 | Q32: =IF(DAY(B32)=1,Assumptions!B40*G32,0) -> 0 | R32: =IF(DAY(B32)=1,Assumptions!B41*G32,0) -> 0 | S32: =IF(AND(DAY(B32)=1,D32>=13),Assumptions!B42*G32,0) -> 0 | T32: =IF(DAY(B32)=1,Assumptions!B43*G32,0) -> 0 | U32: =SUM(O32:T32) -> 0 | V32: =N32-U32 -> 8400 | W32: =W31+V32 -> -4877200 | X32: =IF(W32>=0,"YES","No") -> No
A33: 32 | B33: =B32+1 -> 46054 | C33: =MIN(ROUNDUP(A33/365,0),5) -> 1 | D33: =DATEDIF(Assumptions!B5,B33,"m")+1 -> 2 | E33: =TEXT(B33,"ddd") -> Sun | F33: =IF(WEEKDAY(B33,2)>=6,Assumptions!B34,Assumptions!B35) -> 0.6 | G33: =IF(D33>=13,(1+Assumptions!B46)^(D33-12),1) -> 1 | H33: =H32*(1+IF(C33=1,Assumptions!B22,Assumptions!B23)) -> 16.760375 | I33: =ROUND(H33*F33,0) -> 10 | J33: =I33*Assumptions!B24 -> 6000 | K33: =K32*(1+Assumptions!B30) -> 13.27444 | L33: =ROUND(K33*F33,0) -> 8 | M33: =L33*Assumptions!B31 -> 2400 | N33: =J33+M33 -> 8400 | O33: =IF(DAY(B33)=1,Assumptions!B38*G33,0) -> 150000 | P33: =IF(DAY(B33)=1,Assumptions!B39*G33,0) -> 40000 | Q33: =IF(DAY(B33)=1,Assumptions!B40*G33,0) -> 30000 | R33: =IF(DAY(B33)=1,Assumptions!B41*G33,0) -> 20000 | S33: =IF(AND(DAY(B33)=1,D33>=13),Assumptions!B42*G33,0) -> 0 | T33: =IF(DAY(B33)=1,Assumptions!B43*G33,0) -> 20000 | U33: =SUM(O33:T33) -> 260000 | V33: =N33-U33 -> -251600 | W33: =W32+V33 -> -5128800 | X33: =IF(W33>=0,"YES","No") -> No
A34: 33 | B34: =B33+1 -> 46055 | C34: =MIN(ROUNDUP(A34/365,0),5) -> 1 | D34: =DATEDIF(Assumptions!B5,B34,"m")+1 -> 2 | E34: =TEXT(B34,"ddd") -> Mon | F34: =IF(WEEKDAY(B34,2)>=6,Assumptions!B34,Assumptions!B35) -> 1 | G34: =IF(D34>=13,(1+Assumptions!B46)^(D34-12),1) -> 1 | H34: =H33*(1+IF(C34=1,Assumptions!B22,Assumptions!B23)) -> 16.771282 | I34: =ROUND(H34*F34,0) -> 17 | J34: =I34*Assumptions!B24 -> 10200 | K34: =K33*(1+Assumptions!B30) -> 13.27878 | L34: =ROUND(K34*F34,0) -> 13 | M34: =L34*Assumptions!B31 -> 3900 | N34: =J34+M34 -> 14100 | O34: =IF(DAY(B34)=1,Assumptions!B38*G34,0) -> 0 | P34: =IF(DAY(B34)=1,Assumptions!B39*G34,0) -> 0 | Q34: =IF(DAY(B34)=1,Assumptions!B40*G34,0) -> 0 | R34: =IF(DAY(B34)=1,Assumptions!B41*G34,0) -> 0 | S34: =IF(AND(DAY(B34)=1,D34>=13),Assumptions!B42*G34,0) -> 0 | T34: =IF(DAY(B34)=1,Assumptions!B43*G34,0) -> 0 | U34: =SUM(O34:T34) -> 0 | V34: =N34-U34 -> 14100 | W34: =W33+V34 -> -5114700 | X34: =IF(W34>=0,"YES","No") -> No
A35: 34 | B35: =B34+1 -> 46056 | C35: =MIN(ROUNDUP(A35/365,0),5) -> 1 | D35: =DATEDIF(Assumptions!B5,B35,"m")+1 -> 2 | E35: =TEXT(B35,"ddd") -> Tue | F35: =IF(WEEKDAY(B35,2)>=6,Assumptions!B34,Assumptions!B35) -> 1 | G35: =IF(D35>=13,(1+Assumptions!B46)^(D35-12),1) -> 1 | H35: =H34*(1+IF(C35=1,Assumptions!B22,Assumptions!B23)) -> 16.782196 | I35: =ROUND(H35*F35,0) -> 17 | J35: =I35*Assumptions!B24 -> 10200 | K35: =K34*(1+Assumptions!B30) -> 13.283121 | L35: =ROUND(K35*F35,0) -> 13 | M35: =L35*Assumptions!B31 -> 3900 | N35: =J35+M35 -> 14100 | O35: =IF(DAY(B35)=1,Assumptions!B38*G35,0) -> 0 | P35: =IF(DAY(B35)=1,Assumptions!B39*G35,0) -> 0 | Q35: =IF(DAY(B35)=1,Assumptions!B40*G35,0) -> 0 | R35: =IF(DAY(B35)=1,Assumptions!B41*G35,0) -> 0 | S35: =IF(AND(DAY(B35)=1,D35>=13),Assumptions!B42*G35,0) -> 0 | T35: =IF(DAY(B35)=1,Assumptions!B43*G35,0) -> 0 | U35: =SUM(O35:T35) -> 0 | V35: =N35-U35 -> 14100 | W35: =W34+V35 -> -5100600 | X35: =IF(W35>=0,"YES","No") -> No
A36: 35 | B36: =B35+1 -> 46057 | C36: =MIN(ROUNDUP(A36/365,0),5) -> 1 | D36: =DATEDIF(Assumptions!B5,B36,"m")+1 -> 2 | E36: =TEXT(B36,"ddd") -> Wed | F36: =IF(WEEKDAY(B36,2)>=6,Assumptions!B34,Assumptions!B35) -> 1 | G36: =IF(D36>=13,(1+Assumptions!B46)^(D36-12),1) -> 1 | H36: =H35*(1+IF(C36=1,Assumptions!B22,Assumptions!B23)) -> 16.793118 | I36: =ROUND(H36*F36,0) -> 17 | J36: =I36*Assumptions!B24 -> 10200 | K36: =K35*(1+Assumptions!B30) -> 13.287464 | L36: =ROUND(K36*F36,0) -> 13 | M36: =L36*Assumptions!B31 -> 3900 | N36: =J36+M36 -> 14100 | O36: =IF(DAY(B36)=1,Assumptions!B38*G36,0) -> 0 | P36: =IF(DAY(B36)=1,Assumptions!B39*G36,0) -> 0 | Q36: =IF(DAY(B36)=1,Assumptions!B40*G36,0) -> 0 | R36: =IF(DAY(B36)=1,Assumptions!B41*G36,0) -> 0 | S36: =IF(AND(DAY(B36)=1,D36>=13),Assumptions!B42*G36,0) -> 0 | T36: =IF(DAY(B36)=1,Assumptions!B43*G36,0) -> 0 | U36: =SUM(O36:T36) -> 0 | V36: =N36-U36 -> 14100 | W36: =W35+V36 -> -5086500 | X36: =IF(W36>=0,"YES","No") -> No
A37: 36 | B37: =B36+1 -> 46058 | C37: =MIN(ROUNDUP(A37/365,0),5) -> 1 | D37: =DATEDIF(Assumptions!B5,B37,"m")+1 -> 2 | E37: =TEXT(B37,"ddd") -> Thu | F37: =IF(WEEKDAY(B37,2)>=6,Assumptions!B34,Assumptions!B35) -> 1 | G37: =IF(D37>=13,(1+Assumptions!B46)^(D37-12),1) -> 1 | H37: =H36*(1+IF(C37=1,Assumptions!B22,Assumptions!B23)) -> 16.804046 | I37: =ROUND(H37*F37,0) -> 17 | J37: =I37*Assumptions!B24 -> 10200 | K37: =K36*(1+Assumptions!B30) -> 13.291808 | L37: =ROUND(K37*F37,0) -> 13 | M37: =L37*Assumptions!B31 -> 3900 | N37: =J37+M37 -> 14100 | O37: =IF(DAY(B37)=1,Assumptions!B38*G37,0) -> 0 | P37: =IF(DAY(B37)=1,Assumptions!B39*G37,0) -> 0 | Q37: =IF(DAY(B37)=1,Assumptions!B40*G37,0) -> 0 | R37: =IF(DAY(B37)=1,Assumptions!B41*G37,0) -> 0 | S37: =IF(AND(DAY(B37)=1,D37>=13),Assumptions!B42*G37,0) -> 0 | T37: =IF(DAY(B37)=1,Assumptions!B43*G37,0) -> 0 | U37: =SUM(O37:T37) -> 0 | V37: =N37-U37 -> 14100 | W37: =W36+V37 -> -5072400 | X37: =IF(W37>=0,"YES","No") -> No
A38: 37 | B38: =B37+1 -> 46059 | C38: =MIN(ROUNDUP(A38/365,0),5) -> 1 | D38: =DATEDIF(Assumptions!B5,B38,"m")+1 -> 2 | E38: =TEXT(B38,"ddd") -> Fri | F38: =IF(WEEKDAY(B38,2)>=6,Assumptions!B34,Assumptions!B35) -> 1 | G38: =IF(D38>=13,(1+Assumptions!B46)^(D38-12),1) -> 1 | H38: =H37*(1+IF(C38=1,Assumptions!B22,Assumptions!B23)) -> 16.814981 | I38: =ROUND(H38*F38,0) -> 17 | J38: =I38*Assumptions!B24 -> 10200 | K38: =K37*(1+Assumptions!B30) -> 13.296154 | L38: =ROUND(K38*F38,0) -> 13 | M38: =L38*Assumptions!B31 -> 3900 | N38: =J38+M38 -> 14100 | O38: =IF(DAY(B38)=1,Assumptions!B38*G38,0) -> 0 | P38: =IF(DAY(B38)=1,Assumptions!B39*G38,0) -> 0 | Q38: =IF(DAY(B38)=1,Assumptions!B40*G38,0) -> 0 | R38: =IF(DAY(B38)=1,Assumptions!B41*G38,0) -> 0 | S38: =IF(AND(DAY(B38)=1,D38>=13),Assumptions!B42*G38,0) -> 0 | T38: =IF(DAY(B38)=1,Assumptions!B43*G38,0) -> 0 | U38: =SUM(O38:T38) -> 0 | V38: =N38-U38 -> 14100 | W38: =W37+V38 -> -5058300 | X38: =IF(W38>=0,"YES","No") -> No
A39: 38 | B39: =B38+1 -> 46060 | C39: =MIN(ROUNDUP(A39/365,0),5) -> 1 | D39: =DATEDIF(Assumptions!B5,B39,"m")+1 -> 2 | E39: =TEXT(B39,"ddd") -> Sat | F39: =IF(WEEKDAY(B39,2)>=6,Assumptions!B34,Assumptions!B35) -> 0.6 | G39: =IF(D39>=13,(1+Assumptions!B46)^(D39-12),1) -> 1 | H39: =H38*(1+IF(C39=1,Assumptions!B22,Assumptions!B23)) -> 16.825924 | I39: =ROUND(H39*F39,0) -> 10 | J39: =I39*Assumptions!B24 -> 6000 | K39: =K38*(1+Assumptions!B30) -> 13.300501 | L39: =ROUND(K39*F39,0) -> 8 | M39: =L39*Assumptions!B31 -> 2400 | N39: =J39+M39 -> 8400 | O39: =IF(DAY(B39)=1,Assumptions!B38*G39,0) -> 0 | P39: =IF(DAY(B39)=1,Assumptions!B39*G39,0) -> 0 | Q39: =IF(DAY(B39)=1,Assumptions!B40*G39,0) -> 0 | R39: =IF(DAY(B39)=1,Assumptions!B41*G39,0) -> 0 | S39: =IF(AND(DAY(B39)=1,D39>=13),Assumptions!B42*G39,0) -> 0 | T39: =IF(DAY(B39)=1,Assumptions!B43*G39,0) -> 0 | U39: =SUM(O39:T39) -> 0 | V39: =N39-U39 -> 8400 | W39: =W38+V39 -> -5049900 | X39: =IF(W39>=0,"YES","No") -> No
A40: 39 | B40: =B39+1 -> 46061 | C40: =MIN(ROUNDUP(A40/365,0),5) -> 1 | D40: =DATEDIF(Assumptions!B5,B40,"m")+1 -> 2 | E40: =TEXT(B40,"ddd") -> Sun | F40: =IF(WEEKDAY(B40,2)>=6,Assumptions!B34,Assumptions!B35) -> 0.6 | G40: =IF(D40>=13,(1+Assumptions!B46)^(D40-12),1) -> 1 | H40: =H39*(1+IF(C40=1,Assumptions!B22,Assumptions!B23)) -> 16.836873 | I40: =ROUND(H40*F40,0) -> 10 | J40: =I40*Assumptions!B24 -> 6000 | K40: =K39*(1+Assumptions!B30) -> 13.304849 | L40: =ROUND(K40*F40,0) -> 8 | M40: =L40*Assumptions!B31 -> 2400 | N40: =J40+M40 -> 8400 | O40: =IF(DAY(B40)=1,Assumptions!B38*G40,0) -> 0 | P40: =IF(DAY(B40)=1,Assumptions!B39*G40,0) -> 0 | Q40: =IF(DAY(B40)=1,Assumptions!B40*G40,0) -> 0 | R40: =IF(DAY(B40)=1,Assumptions!B41*G40,0) -> 0 | S40: =IF(AND(DAY(B40)=1,D40>=13),Assumptions!B42*G40,0) -> 0 | T40: =IF(DAY(B40)=1,Assumptions!B43*G40,0) -> 0 | U40: =SUM(O40:T40) -> 0 | V40: =N40-U40 -> 8400 | W40: =W39+V40 -> -5041500 | X40: =IF(W40>=0,"YES","No") -> No
A41: 40 | B41: =B40+1 -> 46062 | C41: =MIN(ROUNDUP(A41/365,0),5) -> 1 | D41: =DATEDIF(Assumptions!B5,B41,"m")+1 -> 2 | E41: =TEXT(B41,"ddd") -> Mon | F41: =IF(WEEKDAY(B41,2)>=6,Assumptions!B34,Assumptions!B35) -> 1 | G41: =IF(D41>=13,(1+Assumptions!B46)^(D41-12),1) -> 1 | H41: =H40*(1+IF(C41=1,Assumptions!B22,Assumptions!B23)) -> 16.84783 | I41: =ROUND(H41*F41,0) -> 17 | J41: =I41*Assumptions!B24 -> 10200 | K41: =K40*(1+Assumptions!B30) -> 13.309199 | L41: =ROUND(K41*F41,0) -> 13 | M41: =L41*Assumptions!B31 -> 3900 | N41: =J41+M41 -> 14100 | O41: =IF(DAY(B41)=1,Assumptions!B38*G41,0) -> 0 | P41: =IF(DAY(B41)=1,Assumptions!B39*G41,0) -> 0 | Q41: =IF(DAY(B41)=1,Assumptions!B40*G41,0) -> 0 | R41: =IF(DAY(B41)=1,Assumptions!B41*G41,0) -> 0 | S41: =IF(AND(DAY(B41)=1,D41>=13),Assumptions!B42*G41,0) -> 0 | T41: =IF(DAY(B41)=1,Assumptions!B43*G41,0) -> 0 | U41: =SUM(O41:T41) -> 0 | V41: =N41-U41 -> 14100 | W41: =W40+V41 -> -5027400 | X41: =IF(W41>=0,"YES","No") -> No
A42: 41 | B42: =B41+1 -> 46063 | C42: =MIN(ROUNDUP(A42/365,0),5) -> 1 | D42: =DATEDIF(Assumptions!B5,B42,"m")+1 -> 2 | E42: =TEXT(B42,"ddd") -> Tue | F42: =IF(WEEKDAY(B42,2)>=6,Assumptions!B34,Assumptions!B35) -> 1 | G42: =IF(D42>=13,(1+Assumptions!B46)^(D42-12),1) -> 1 | H42: =H41*(1+IF(C42=1,Assumptions!B22,Assumptions!B23)) -> 16.858794 | I42: =ROUND(H42*F42,0) -> 17 | J42: =I42*Assumptions!B24 -> 10200 | K42: =K41*(1+Assumptions!B30) -> 13.31355 | L42: =ROUND(K42*F42,0) -> 13 | M42: =L42*Assumptions!B31 -> 3900 | N42: =J42+M42 -> 14100 | O42: =IF(DAY(B42)=1,Assumptions!B38*G42,0) -> 0 | P42: =IF(DAY(B42)=1,Assumptions!B39*G42,0) -> 0 | Q42: =IF(DAY(B42)=1,Assumptions!B40*G42,0) -> 0 | R42: =IF(DAY(B42)=1,Assumptions!B41*G42,0) -> 0 | S42: =IF(AND(DAY(B42)=1,D42>=13),Assumptions!B42*G42,0) -> 0 | T42: =IF(DAY(B42)=1,Assumptions!B43*G42,0) -> 0 | U42: =SUM(O42:T42) -> 0 | V42: =N42-U42 -> 14100 | W42: =W41+V42 -> -5013300 | X42: =IF(W42>=0,"YES","No") -> No
A43: 42 | B43: =B42+1 -> 46064 | C43: =MIN(ROUNDUP(A43/365,0),5) -> 1 | D43: =DATEDIF(Assumptions!B5,B43,"m")+1 -> 2 | E43: =TEXT(B43,"ddd") -> Wed | F43: =IF(WEEKDAY(B43,2)>=6,Assumptions!B34,Assumptions!B35) -> 1 | G43: =IF(D43>=13,(1+Assumptions!B46)^(D43-12),1) -> 1 | H43: =H42*(1+IF(C43=1,Assumptions!B22,Assumptions!B23)) -> 16.869765 | I43: =ROUND(H43*F43,0) -> 17 | J43: =I43*Assumptions!B24 -> 10200 | K43: =K42*(1+Assumptions!B30) -> 13.317903 | L43: =ROUND(K43*F43,0) -> 13 | M43: =L43*Assumptions!B31 -> 3900 | N43: =J43+M43 -> 14100 | O43: =IF(DAY(B43)=1,Assumptions!B38*G43,0) -> 0 | P43: =IF(DAY(B43)=1,Assumptions!B39*G43,0) -> 0 | Q43: =IF(DAY(B43)=1,Assumptions!B40*G43,0) -> 0 | R43: =IF(DAY(B43)=1,Assumptions!B41*G43,0) -> 0 | S43: =IF(AND(DAY(B43)=1,D43>=13),Assumptions!B42*G43,0) -> 0 | T43: =IF(DAY(B43)=1,Assumptions!B43*G43,0) -> 0 | U43: =SUM(O43:T43) -> 0 | V43: =N43-U43 -> 14100 | W43: =W42+V43 -> -4999200 | X43: =IF(W43>=0,"YES","No") -> No
A44: 43 | B44: =B43+1 -> 46065 | C44: =MIN(ROUNDUP(A44/365,0),5) -> 1 | D44: =DATEDIF(Assumptions!B5,B44,"m")+1 -> 2 | E44: =TEXT(B44,"ddd") -> Thu | F44: =IF(WEEKDAY(B44,2)>=6,Assumptions!B34,Assumptions!B35) -> 1 | G44: =IF(D44>=13,(1+Assumptions!B46)^(D44-12),1) -> 1 | H44: =H43*(1+IF(C44=1,Assumptions!B22,Assumptions!B23)) -> 16.880743 | I44: =ROUND(H44*F44,0) -> 17 | J44: =I44*Assumptions!B24 -> 10200 | K44: =K43*(1+Assumptions!B30) -> 13.322257 | L44: =ROUND(K44*F44,0) -> 13 | M44: =L44*Assumptions!B31 -> 3900 | N44: =J44+M44 -> 14100 | O44: =IF(DAY(B44)=1,Assumptions!B38*G44,0) -> 0 | P44: =IF(DAY(B44)=1,Assumptions!B39*G44,0) -> 0 | Q44: =IF(DAY(B44)=1,Assumptions!B40*G44,0) -> 0 | R44: =IF(DAY(B44)=1,Assumptions!B41*G44,0) -> 0 | S44: =IF(AND(DAY(B44)=1,D44>=13),Assumptions!B42*G44,0) -> 0 | T44: =IF(DAY(B44)=1,Assumptions!B43*G44,0) -> 0 | U44: =SUM(O44:T44) -> 0 | V44: =N44-U44 -> 14100 | W44: =W43+V44 -> -4985100 | X44: =IF(W44>=0,"YES","No") -> No
A45: 44 | B45: =B44+1 -> 46066 | C45: =MIN(ROUNDUP(A45/365,0),5) -> 1 | D45: =DATEDIF(Assumptions!B5,B45,"m")+1 -> 2 | E45: =TEXT(B45,"ddd") -> Fri | F45: =IF(WEEKDAY(B45,2)>=6,Assumptions!B34,Assumptions!B35) -> 1 | G45: =IF(D45>=13,(1+Assumptions!B46)^(D45-12),1) -> 1 | H45: =H44*(1+IF(C45=1,Assumptions!B22,Assumptions!B23)) -> 16.891728 | I45: =ROUND(H45*F45,0) -> 17 | J45: =I45*Assumptions!B24 -> 10200 | K45: =K44*(1+Assumptions!B30) -> 13.326613 | L45: =ROUND(K45*F45,0) -> 13 | M45: =L45*Assumptions!B31 -> 3900 | N45: =J45+M45 -> 14100 | O45: =IF(DAY(B45)=1,Assumptions!B38*G45,0) -> 0 | P45: =IF(DAY(B45)=1,Assumptions!B39*G45,0) -> 0 | Q45: =IF(DAY(B45)=1,Assumptions!B40*G45,0) -> 0 | R45: =IF(DAY(B45)=1,Assumptions!B41*G45,0) -> 0 | S45: =IF(AND(DAY(B45)=1,D45>=13),Assumptions!B42*G45,0) -> 0 | T45: =IF(DAY(B45)=1,Assumptions!B43*G45,0) -> 0 | U45: =SUM(O45:T45) -> 0 | V45: =N45-U45 -> 14100 | W45: =W44+V45 -> -4971000 | X45: =IF(W45>=0,"YES","No") -> No
A46: 45 | B46: =B45+1 -> 46067 | C46: =MIN(ROUNDUP(A46/365,0),5) -> 1 | D46: =DATEDIF(Assumptions!B5,B46,"m")+1 -> 2 | E46: =TEXT(B46,"ddd") -> Sat | F46: =IF(WEEKDAY(B46,2)>=6,Assumptions!B34,Assumptions!B35) -> 0.6 | G46: =IF(D46>=13,(1+Assumptions!B46)^(D46-12),1) -> 1 | H46: =H45*(1+IF(C46=1,Assumptions!B22,Assumptions!B23)) -> 16.902721 | I46: =ROUND(H46*F46,0) -> 10 | J46: =I46*Assumptions!B24 -> 6000 | K46: =K45*(1+Assumptions!B30) -> 13.33097 | L46: =ROUND(K46*F46,0) -> 8 | M46: =L46*Assumptions!B31 -> 2400 | N46: =J46+M46 -> 8400 | O46: =IF(DAY(B46)=1,Assumptions!B38*G46,0) -> 0 | P46: =IF(DAY(B46)=1,Assumptions!B39*G46,0) -> 0 | Q46: =IF(DAY(B46)=1,Assumptions!B40*G46,0) -> 0 | R46: =IF(DAY(B46)=1,Assumptions!B41*G46,0) -> 0 | S46: =IF(AND(DAY(B46)=1,D46>=13),Assumptions!B42*G46,0) -> 0 | T46: =IF(DAY(B46)=1,Assumptions!B43*G46,0) -> 0 | U46: =SUM(O46:T46) -> 0 | V46: =N46-U46 -> 8400 | W46: =W45+V46 -> -4962600 | X46: =IF(W46>=0,"YES","No") -> No
A47: 46 | B47: =B46+1 -> 46068 | C47: =MIN(ROUNDUP(A47/365,0),5) -> 1 | D47: =DATEDIF(Assumptions!B5,B47,"m")+1 -> 2 | E47: =TEXT(B47,"ddd") -> Sun | F47: =IF(WEEKDAY(B47,2)>=6,Assumptions!B34,Assumptions!B35) -> 0.6 | G47: =IF(D47>=13,(1+Assumptions!B46)^(D47-12),1) -> 1 | H47: =H46*(1+IF(C47=1,Assumptions!B22,Assumptions!B23)) -> 16.91372 | I47: =ROUND(H47*F47,0) -> 10 | J47: =I47*Assumptions!B24 -> 6000 | K47: =K46*(1+Assumptions!B30) -> 13.335328 | L47: =ROUND(K47*F47,0) -> 8 | M47: =L47*Assumptions!B31 -> 2400 | N47: =J47+M47 -> 8400 | O47: =IF(DAY(B47)=1,Assumptions!B38*G47,0) -> 0 | P47: =IF(DAY(B47)=1,Assumptions!B39*G47,0) -> 0 | Q47: =IF(DAY(B47)=1,Assumptions!B40*G47,0) -> 0 | R47: =IF(DAY(B47)=1,Assumptions!B41*G47,0) -> 0 | S47: =IF(AND(DAY(B47)=1,D47>=13),Assumptions!B42*G47,0) -> 0 | T47: =IF(DAY(B47)=1,Assumptions!B43*G47,0) -> 0 | U47: =SUM(O47:T47) -> 0 | V47: =N47-U47 -> 8400 | W47: =W46+V47 -> -4954200 | X47: =IF(W47>=0,"YES","No") -> No
A48: 47 | B48: =B47+1 -> 46069 | C48: =MIN(ROUNDUP(A48/365,0),5) -> 1 | D48: =DATEDIF(Assumptions!B5,B48,"m")+1 -> 2 | E48: =TEXT(B48,"ddd") -> Mon | F48: =IF(WEEKDAY(B48,2)>=6,Assumptions!B34,Assumptions!B35) -> 1 | G48: =IF(D48>=13,(1+Assumptions!B46)^(D48-12),1) -> 1 | H48: =H47*(1+IF(C48=1,Assumptions!B22,Assumptions!B23)) -> 16.924727 | I48: =ROUND(H48*F48,0) -> 17 | J48: =I48*Assumptions!B24 -> 10200 | K48: =K47*(1+Assumptions!B30) -> 13.339688 | L48: =ROUND(K48*F48,0) -> 13 | M48: =L48*Assumptions!B31 -> 3900 | N48: =J48+M48 -> 14100 | O48: =IF(DAY(B48)=1,Assumptions!B38*G48,0) -> 0 | P48: =IF(DAY(B48)=1,Assumptions!B39*G48,0) -> 0 | Q48: =IF(DAY(B48)=1,Assumptions!B40*G48,0) -> 0 | R48: =IF(DAY(B48)=1,Assumptions!B41*G48,0) -> 0 | S48: =IF(AND(DAY(B48)=1,D48>=13),Assumptions!B42*G48,0) -> 0 | T48: =IF(DAY(B48)=1,Assumptions!B43*G48,0) -> 0 | U48: =SUM(O48:T48) -> 0 | V48: =N48-U48 -> 14100 | W48: =W47+V48 -> -4940100 | X48: =IF(W48>=0,"YES","No") -> No
A49: 48 | B49: =B48+1 -> 46070 | C49: =MIN(ROUNDUP(A49/365,0),5) -> 1 | D49: =DATEDIF(Assumptions!B5,B49,"m")+1 -> 2 | E49: =TEXT(B49,"ddd") -> Tue | F49: =IF(WEEKDAY(B49,2)>=6,Assumptions!B34,Assumptions!B35) -> 1 | G49: =IF(D49>=13,(1+Assumptions!B46)^(D49-12),1) -> 1 | H49: =H48*(1+IF(C49=1,Assumptions!B22,Assumptions!B23)) -> 16.935741 | I49: =ROUND(H49*F49,0) -> 17 | J49: =I49*Assumptions!B24 -> 10200 | K49: =K48*(1+Assumptions!B30) -> 13.344049 | L49: =ROUND(K49*F49,0) -> 13 | M49: =L49*Assumptions!B31 -> 3900 | N49: =J49+M49 -> 14100 | O49: =IF(DAY(B49)=1,Assumptions!B38*G49,0) -> 0 | P49: =IF(DAY(B49)=1,Assumptions!B39*G49,0) -> 0 | Q49: =IF(DAY(B49)=1,Assumptions!B40*G49,0) -> 0 | R49: =IF(DAY(B49)=1,Assumptions!B41*G49,0) -> 0 | S49: =IF(AND(DAY(B49)=1,D49>=13),Assumptions!B42*G49,0) -> 0 | T49: =IF(DAY(B49)=1,Assumptions!B43*G49,0) -> 0 | U49: =SUM(O49:T49) -> 0 | V49: =N49-U49 -> 14100 | W49: =W48+V49 -> -4926000 | X49: =IF(W49>=0,"YES","No") -> No
A50: 49 | B50: =B49+1 -> 46071 | C50: =MIN(ROUNDUP(A50/365,0),5) -> 1 | D50: =DATEDIF(Assumptions!B5,B50,"m")+1 -> 2 | E50: =TEXT(B50,"ddd") -> Wed | F50: =IF(WEEKDAY(B50,2)>=6,Assumptions!B34,Assumptions!B35) -> 1 | G50: =IF(D50>=13,(1+Assumptions!B46)^(D50-12),1) -> 1 | H50: =H49*(1+IF(C50=1,Assumptions!B22,Assumptions!B23)) -> 16.946762 | I50: =ROUND(H50*F50,0) -> 17 | J50: =I50*Assumptions!B24 -> 10200 | K50: =K49*(1+Assumptions!B30) -> 13.348412 | L50: =ROUND(K50*F50,0) -> 13 | M50: =L50*Assumptions!B31 -> 3900 | N50: =J50+M50 -> 14100 | O50: =IF(DAY(B50)=1,Assumptions!B38*G50,0) -> 0 | P50: =IF(DAY(B50)=1,Assumptions!B39*G50,0) -> 0 | Q50: =IF(DAY(B50)=1,Assumptions!B40*G50,0) -> 0 | R50: =IF(DAY(B50)=1,Assumptions!B41*G50,0) -> 0 | S50: =IF(AND(DAY(B50)=1,D50>=13),Assumptions!B42*G50,0) -> 0 | T50: =IF(DAY(B50)=1,Assumptions!B43*G50,0) -> 0 | U50: =SUM(O50:T50) -> 0 | V50: =N50-U50 -> 14100 | W50: =W49+V50 -> -4911900 | X50: =IF(W50>=0,"YES","No") -> No
A51: 50 | B51: =B50+1 -> 46072 | C51: =MIN(ROUNDUP(A51/365,0),5) -> 1 | D51: =DATEDIF(Assumptions!B5,B51,"m")+1 -> 2 | E51: =TEXT(B51,"ddd") -> Thu | F51: =IF(WEEKDAY(B51,2)>=6,Assumptions!B34,Assumptions!B35) -> 1 | G51: =IF(D51>=13,(1+Assumptions!B46)^(D51-12),1) -> 1 | H51: =H50*(1+IF(C51=1,Assumptions!B22,Assumptions!B23)) -> 16.95779 | I51: =ROUND(H51*F51,0) -> 17 | J51: =I51*Assumptions!B24 -> 10200 | K51: =K50*(1+Assumptions!B30) -> 13.352776 | L51: =ROUND(K51*F51,0) -> 13 | M51: =L51*Assumptions!B31 -> 3900 | N51: =J51+M51 -> 14100 | O51: =IF(DAY(B51)=1,Assumptions!B38*G51,0) -> 0 | P51: =IF(DAY(B51)=1,Assumptions!B39*G51,0) -> 0 | Q51: =IF(DAY(B51)=1,Assumptions!B40*G51,0) -> 0 | R51: =IF(DAY(B51)=1,Assumptions!B41*G51,0) -> 0 | S51: =IF(AND(DAY(B51)=1,D51>=13),Assumptions!B42*G51,0) -> 0 | T51: =IF(DAY(B51)=1,Assumptions!B43*G51,0) -> 0 | U51: =SUM(O51:T51) -> 0 | V51: =N51-U51 -> 14100 | W51: =W50+V51 -> -4897800 | X51: =IF(W51>=0,"YES","No") -> No
A52: 51 | B52: =B51+1 -> 46073 | C52: =MIN(ROUNDUP(A52/365,0),5) -> 1 | D52: =DATEDIF(Assumptions!B5,B52,"m")+1 -> 2 | E52: =TEXT(B52,"ddd") -> Fri | F52: =IF(WEEKDAY(B52,2)>=6,Assumptions!B34,Assumptions!B35) -> 1 | G52: =IF(D52>=13,(1+Assumptions!B46)^(D52-12),1) -> 1 | H52: =H51*(1+IF(C52=1,Assumptions!B22,Assumptions!B23)) -> 16.968826 | I52: =ROUND(H52*F52,0) -> 17 | J52: =I52*Assumptions!B24 -> 10200 | K52: =K51*(1+Assumptions!B30) -> 13.357141 | L52: =ROUND(K52*F52,0) -> 13 | M52: =L52*Assumptions!B31 -> 3900 | N52: =J52+M52 -> 14100 | O52: =IF(DAY(B52)=1,Assumptions!B38*G52,0) -> 0 | P52: =IF(DAY(B52)=1,Assumptions!B39*G52,0) -> 0 | Q52: =IF(DAY(B52)=1,Assumptions!B40*G52,0) -> 0 | R52: =IF(DAY(B52)=1,Assumptions!B41*G52,0) -> 0 | S52: =IF(AND(DAY(B52)=1,D52>=13),Assumptions!B42*G52,0) -> 0 | T52: =IF(DAY(B52)=1,Assumptions!B43*G52,0) -> 0 | U52: =SUM(O52:T52) -> 0 | V52: =N52-U52 -> 14100 | W52: =W51+V52 -> -4883700 | X52: =IF(W52>=0,"YES","No") -> No
A53: 52 | B53: =B52+1 -> 46074 | C53: =MIN(ROUNDUP(A53/365,0),5) -> 1 | D53: =DATEDIF(Assumptions!B5,B53,"m")+1 -> 2 | E53: =TEXT(B53,"ddd") -> Sat | F53: =IF(WEEKDAY(B53,2)>=6,Assumptions!B34,Assumptions!B35) -> 0.6 | G53: =IF(D53>=13,(1+Assumptions!B46)^(D53-12),1) -> 1 | H53: =H52*(1+IF(C53=1,Assumptions!B22,Assumptions!B23)) -> 16.979868 | I53: =ROUND(H53*F53,0) -> 10 | J53: =I53*Assumptions!B24 -> 6000 | K53: =K52*(1+Assumptions!B30) -> 13.361508 | L53: =ROUND(K53*F53,0) -> 8 | M53: =L53*Assumptions!B31 -> 2400 | N53: =J53+M53 -> 8400 | O53: =IF(DAY(B53)=1,Assumptions!B38*G53,0) -> 0 | P53: =IF(DAY(B53)=1,Assumptions!B39*G53,0) -> 0 | Q53: =IF(DAY(B53)=1,Assumptions!B40*G53,0) -> 0 | R53: =IF(DAY(B53)=1,Assumptions!B41*G53,0) -> 0 | S53: =IF(AND(DAY(B53)=1,D53>=13),Assumptions!B42*G53,0) -> 0 | T53: =IF(DAY(B53)=1,Assumptions!B43*G53,0) -> 0 | U53: =SUM(O53:T53) -> 0 | V53: =N53-U53 -> 8400 | W53: =W52+V53 -> -4875300 | X53: =IF(W53>=0,"YES","No") -> No
A54: 53 | B54: =B53+1 -> 46075 | C54: =MIN(ROUNDUP(A54/365,0),5) -> 1 | D54: =DATEDIF(Assumptions!B5,B54,"m")+1 -> 2 | E54: =TEXT(B54,"ddd") -> Sun | F54: =IF(WEEKDAY(B54,2)>=6,Assumptions!B34,Assumptions!B35) -> 0.6 | G54: =IF(D54>=13,(1+Assumptions!B46)^(D54-12),1) -> 1 | H54: =H53*(1+IF(C54=1,Assumptions!B22,Assumptions!B23)) -> 16.990918 | I54: =ROUND(H54*F54,0) -> 10 | J54: =I54*Assumptions!B24 -> 6000 | K54: =K53*(1+Assumptions!B30) -> 13.365877 | L54: =ROUND(K54*F54,0) -> 8 | M54: =L54*Assumptions!B31 -> 2400 | N54: =J54+M54 -> 8400 | O54: =IF(DAY(B54)=1,Assumptions!B38*G54,0) -> 0 | P54: =IF(DAY(B54)=1,Assumptions!B39*G54,0) -> 0 | Q54: =IF(DAY(B54)=1,Assumptions!B40*G54,0) -> 0 | R54: =IF(DAY(B54)=1,Assumptions!B41*G54,0) -> 0 | S54: =IF(AND(DAY(B54)=1,D54>=13),Assumptions!B42*G54,0) -> 0 | T54: =IF(DAY(B54)=1,Assumptions!B43*G54,0) -> 0 | U54: =SUM(O54:T54) -> 0 | V54: =N54-U54 -> 8400 | W54: =W53+V54 -> -4866900 | X54: =IF(W54>=0,"YES","No") -> No
A55: 54 | B55: =B54+1 -> 46076 | C55: =MIN(ROUNDUP(A55/365,0),5) -> 1 | D55: =DATEDIF(Assumptions!B5,B55,"m")+1 -> 2 | E55: =TEXT(B55,"ddd") -> Mon | F55: =IF(WEEKDAY(B55,2)>=6,Assumptions!B34,Assumptions!B35) -> 1 | G55: =IF(D55>=13,(1+Assumptions!B46)^(D55-12),1) -> 1 | H55: =H54*(1+IF(C55=1,Assumptions!B22,Assumptions!B23)) -> 17.001975 | I55: =ROUND(H55*F55,0) -> 17 | J55: =I55*Assumptions!B24 -> 10200 | K55: =K54*(1+Assumptions!B30) -> 13.370247 | L55: =ROUND(K55*F55,0) -> 13 | M55: =L55*Assumptions!B31 -> 3900 | N55: =J55+M55 -> 14100 | O55: =IF(DAY(B55)=1,Assumptions!B38*G55,0) -> 0 | P55: =IF(DAY(B55)=1,Assumptions!B39*G55,0) -> 0 | Q55: =IF(DAY(B55)=1,Assumptions!B40*G55,0) -> 0 | R55: =IF(DAY(B55)=1,Assumptions!B41*G55,0) -> 0 | S55: =IF(AND(DAY(B55)=1,D55>=13),Assumptions!B42*G55,0) -> 0 | T55: =IF(DAY(B55)=1,Assumptions!B43*G55,0) -> 0 | U55: =SUM(O55:T55) -> 0 | V55: =N55-U55 -> 14100 | W55: =W54+V55 -> -4852800 | X55: =IF(W55>=0,"YES","No") -> No
A56: 55 | B56: =B55+1 -> 46077 | C56: =MIN(ROUNDUP(A56/365,0),5) -> 1 | D56: =DATEDIF(Assumptions!B5,B56,"m")+1 -> 2 | E56: =TEXT(B56,"ddd") -> Tue | F56: =IF(WEEKDAY(B56,2)>=6,Assumptions!B34,Assumptions!B35) -> 1 | G56: =IF(D56>=13,(1+Assumptions!B46)^(D56-12),1) -> 1 | H56: =H55*(1+IF(C56=1,Assumptions!B22,Assumptions!B23)) -> 17.013039 | I56: =ROUND(H56*F56,0) -> 17 | J56: =I56*Assumptions!B24 -> 10200 | K56: =K55*(1+Assumptions!B30) -> 13.374618 | L56: =ROUND(K56*F56,0) -> 13 | M56: =L56*Assumptions!B31 -> 3900 | N56: =J56+M56 -> 14100 | O56: =IF(DAY(B56)=1,Assumptions!B38*G56,0) -> 0 | P56: =IF(DAY(B56)=1,Assumptions!B39*G56,0) -> 0 | Q56: =IF(DAY(B56)=1,Assumptions!B40*G56,0) -> 0 | R56: =IF(DAY(B56)=1,Assumptions!B41*G56,0) -> 0 | S56: =IF(AND(DAY(B56)=1,D56>=13),Assumptions!B42*G56,0) -> 0 | T56: =IF(DAY(B56)=1,Assumptions!B43*G56,0) -> 0 | U56: =SUM(O56:T56) -> 0 | V56: =N56-U56 -> 14100 | W56: =W55+V56 -> -4838700 | X56: =IF(W56>=0,"YES","No") -> No
A57: 56 | B57: =B56+1 -> 46078 | C57: =MIN(ROUNDUP(A57/365,0),5) -> 1 | D57: =DATEDIF(Assumptions!B5,B57,"m")+1 -> 2 | E57: =TEXT(B57,"ddd") -> Wed | F57: =IF(WEEKDAY(B57,2)>=6,Assumptions!B34,Assumptions!B35) -> 1 | G57: =IF(D57>=13,(1+Assumptions!B46)^(D57-12),1) -> 1 | H57: =H56*(1+IF(C57=1,Assumptions!B22,Assumptions!B23)) -> 17.024111 | I57: =ROUND(H57*F57,0) -> 17 | J57: =I57*Assumptions!B24 -> 10200 | K57: =K56*(1+Assumptions!B30) -> 13.37899 | L57: =ROUND(K57*F57,0) -> 13 | M57: =L57*Assumptions!B31 -> 3900 | N57: =J57+M57 -> 14100 | O57: =IF(DAY(B57)=1,Assumptions!B38*G57,0) -> 0 | P57: =IF(DAY(B57)=1,Assumptions!B39*G57,0) -> 0 | Q57: =IF(DAY(B57)=1,Assumptions!B40*G57,0) -> 0 | R57: =IF(DAY(B57)=1,Assumptions!B41*G57,0) -> 0 | S57: =IF(AND(DAY(B57)=1,D57>=13),Assumptions!B42*G57,0) -> 0 | T57: =IF(DAY(B57)=1,Assumptions!B43*G57,0) -> 0 | U57: =SUM(O57:T57) -> 0 | V57: =N57-U57 -> 14100 | W57: =W56+V57 -> -4824600 | X57: =IF(W57>=0,"YES","No") -> No
A58: 57 | B58: =B57+1 -> 46079 | C58: =MIN(ROUNDUP(A58/365,0),5) -> 1 | D58: =DATEDIF(Assumptions!B5,B58,"m")+1 -> 2 | E58: =TEXT(B58,"ddd") -> Thu | F58: =IF(WEEKDAY(B58,2)>=6,Assumptions!B34,Assumptions!B35) -> 1 | G58: =IF(D58>=13,(1+Assumptions!B46)^(D58-12),1) -> 1 | H58: =H57*(1+IF(C58=1,Assumptions!B22,Assumptions!B23)) -> 17.035189 | I58: =ROUND(H58*F58,0) -> 17 | J58: =I58*Assumptions!B24 -> 10200 | K58: =K57*(1+Assumptions!B30) -> 13.383365 | L58: =ROUND(K58*F58,0) -> 13 | M58: =L58*Assumptions!B31 -> 3900 | N58: =J58+M58 -> 14100 | O58: =IF(DAY(B58)=1,Assumptions!B38*G58,0) -> 0 | P58: =IF(DAY(B58)=1,Assumptions!B39*G58,0) -> 0 | Q58: =IF(DAY(B58)=1,Assumptions!B40*G58,0) -> 0 | R58: =IF(DAY(B58)=1,Assumptions!B41*G58,0) -> 0 | S58: =IF(AND(DAY(B58)=1,D58>=13),Assumptions!B42*G58,0) -> 0 | T58: =IF(DAY(B58)=1,Assumptions!B43*G58,0) -> 0 | U58: =SUM(O58:T58) -> 0 | V58: =N58-U58 -> 14100 | W58: =W57+V58 -> -4810500 | X58: =IF(W58>=0,"YES","No") -> No
A59: 58 | B59: =B58+1 -> 46080 | C59: =MIN(ROUNDUP(A59/365,0),5) -> 1 | D59: =DATEDIF(Assumptions!B5,B59,"m")+1 -> 2 | E59: =TEXT(B59,"ddd") -> Fri | F59: =IF(WEEKDAY(B59,2)>=6,Assumptions!B34,Assumptions!B35) -> 1 | G59: =IF(D59>=13,(1+Assumptions!B46)^(D59-12),1) -> 1 | H59: =H58*(1+IF(C59=1,Assumptions!B22,Assumptions!B23)) -> 17.046275 | I59: =ROUND(H59*F59,0) -> 17 | J59: =I59*Assumptions!B24 -> 10200 | K59: =K58*(1+Assumptions!B30) -> 13.38774 | L59: =ROUND(K59*F59,0) -> 13 | M59: =L59*Assumptions!B31 -> 3900 | N59: =J59+M59 -> 14100 | O59: =IF(DAY(B59)=1,Assumptions!B38*G59,0) -> 0 | P59: =IF(DAY(B59)=1,Assumptions!B39*G59,0) -> 0 | Q59: =IF(DAY(B59)=1,Assumptions!B40*G59,0) -> 0 | R59: =IF(DAY(B59)=1,Assumptions!B41*G59,0) -> 0 | S59: =IF(AND(DAY(B59)=1,D59>=13),Assumptions!B42*G59,0) -> 0 | T59: =IF(DAY(B59)=1,Assumptions!B43*G59,0) -> 0 | U59: =SUM(O59:T59) -> 0 | V59: =N59-U59 -> 14100 | W59: =W58+V59 -> -4796400 | X59: =IF(W59>=0,"YES","No") -> No
A60: 59 | B60: =B59+1 -> 46081 | C60: =MIN(ROUNDUP(A60/365,0),5) -> 1 | D60: =DATEDIF(Assumptions!B5,B60,"m")+1 -> 2 | E60: =TEXT(B60,"ddd") -> Sat | F60: =IF(WEEKDAY(B60,2)>=6,Assumptions!B34,Assumptions!B35) -> 0.6 | G60: =IF(D60>=13,(1+Assumptions!B46)^(D60-12),1) -> 1 | H60: =H59*(1+IF(C60=1,Assumptions!B22,Assumptions!B23)) -> 17.057368 | I60: =ROUND(H60*F60,0) -> 10 | J60: =I60*Assumptions!B24 -> 6000 | K60: =K59*(1+Assumptions!B30) -> 13.392117 | L60: =ROUND(K60*F60,0) -> 8 | M60: =L60*Assumptions!B31 -> 2400 | N60: =J60+M60 -> 8400 | O60: =IF(DAY(B60)=1,Assumptions!B38*G60,0) -> 0 | P60: =IF(DAY(B60)=1,Assumptions!B39*G60,0) -> 0 | Q60: =IF(DAY(B60)=1,Assumptions!B40*G60,0) -> 0 | R60: =IF(DAY(B60)=1,Assumptions!B41*G60,0) -> 0 | S60: =IF(AND(DAY(B60)=1,D60>=13),Assumptions!B42*G60,0) -> 0 | T60: =IF(DAY(B60)=1,Assumptions!B43*G60,0) -> 0 | U60: =SUM(O60:T60) -> 0 | V60: =N60-U60 -> 8400 | W60: =W59+V60 -> -4788000 | X60: =IF(W60>=0,"YES","No") -> No
A61: 60 | B61: =B60+1 -> 46082 | C61: =MIN(ROUNDUP(A61/365,0),5) -> 1 | D61: =DATEDIF(Assumptions!B5,B61,"m")+1 -> 3 | E61: =TEXT(B61,"ddd") -> Sun | F61: =IF(WEEKDAY(B61,2)>=6,Assumptions!B34,Assumptions!B35) -> 0.6 | G61: =IF(D61>=13,(1+Assumptions!B46)^(D61-12),1) -> 1 | H61: =H60*(1+IF(C61=1,Assumptions!B22,Assumptions!B23)) -> 17.068468 | I61: =ROUND(H61*F61,0) -> 10 | J61: =I61*Assumptions!B24 -> 6000 | K61: =K60*(1+Assumptions!B30) -> 13.396495 | L61: =ROUND(K61*F61,0) -> 8 | M61: =L61*Assumptions!B31 -> 2400 | N61: =J61+M61 -> 8400 | O61: =IF(DAY(B61)=1,Assumptions!B38*G61,0) -> 150000 | P61: =IF(DAY(B61)=1,Assumptions!B39*G61,0) -> 40000 | Q61: =IF(DAY(B61)=1,Assumptions!B40*G61,0) -> 30000 | R61: =IF(DAY(B61)=1,Assumptions!B41*G61,0) -> 20000 | S61: =IF(AND(DAY(B61)=1,D61>=13),Assumptions!B42*G61,0) -> 0 | T61: =IF(DAY(B61)=1,Assumptions!B43*G61,0) -> 20000 | U61: =SUM(O61:T61) -> 260000 | V61: =N61-U61 -> -251600 | W61: =W60+V61 -> -5039600 | X61: =IF(W61>=0,"YES","No") -> No
A62: 61 | B62: =B61+1 -> 46083 | C62: =MIN(ROUNDUP(A62/365,0),5) -> 1 | D62: =DATEDIF(Assumptions!B5,B62,"m")+1 -> 3 | E62: =TEXT(B62,"ddd") -> Mon | F62: =IF(WEEKDAY(B62,2)>=6,Assumptions!B34,Assumptions!B35) -> 1 | G62: =IF(D62>=13,(1+Assumptions!B46)^(D62-12),1) -> 1 | H62: =H61*(1+IF(C62=1,Assumptions!B22,Assumptions!B23)) -> 17.079576 | I62: =ROUND(H62*F62,0) -> 17 | J62: =I62*Assumptions!B24 -> 10200 | K62: =K61*(1+Assumptions!B30) -> 13.400875 | L62: =ROUND(K62*F62,0) -> 13 | M62: =L62*Assumptions!B31 -> 3900 | N62: =J62+M62 -> 14100 | O62: =IF(DAY(B62)=1,Assumptions!B38*G62,0) -> 0 | P62: =IF(DAY(B62)=1,Assumptions!B39*G62,0) -> 0 | Q62: =IF(DAY(B62)=1,Assumptions!B40*G62,0) -> 0 | R62: =IF(DAY(B62)=1,Assumptions!B41*G62,0) -> 0 | S62: =IF(AND(DAY(B62)=1,D62>=13),Assumptions!B42*G62,0) -> 0 | T62: =IF(DAY(B62)=1,Assumptions!B43*G62,0) -> 0 | U62: =SUM(O62:T62) -> 0 | V62: =N62-U62 -> 14100 | W62: =W61+V62 -> -5025500 | X62: =IF(W62>=0,"YES","No") -> No
A63: 62 | B63: =B62+1 -> 46084 | C63: =MIN(ROUNDUP(A63/365,0),5) -> 1 | D63: =DATEDIF(Assumptions!B5,B63,"m")+1 -> 3 | E63: =TEXT(B63,"ddd") -> Tue | F63: =IF(WEEKDAY(B63,2)>=6,Assumptions!B34,Assumptions!B35) -> 1 | G63: =IF(D63>=13,(1+Assumptions!B46)^(D63-12),1) -> 1 | H63: =H62*(1+IF(C63=1,Assumptions!B22,Assumptions!B23)) -> 17.09069 | I63: =ROUND(H63*F63,0) -> 17 | J63: =I63*Assumptions!B24 -> 10200 | K63: =K62*(1+Assumptions!B30) -> 13.405256 | L63: =ROUND(K63*F63,0) -> 13 | M63: =L63*Assumptions!B31 -> 3900 | N63: =J63+M63 -> 14100 | O63: =IF(DAY(B63)=1,Assumptions!B38*G63,0) -> 0 | P63: =IF(DAY(B63)=1,Assumptions!B39*G63,0) -> 0 | Q63: =IF(DAY(B63)=1,Assumptions!B40*G63,0) -> 0 | R63: =IF(DAY(B63)=1,Assumptions!B41*G63,0) -> 0 | S63: =IF(AND(DAY(B63)=1,D63>=13),Assumptions!B42*G63,0) -> 0 | T63: =IF(DAY(B63)=1,Assumptions!B43*G63,0) -> 0 | U63: =SUM(O63:T63) -> 0 | V63: =N63-U63 -> 14100 | W63: =W62+V63 -> -5011400 | X63: =IF(W63>=0,"YES","No") -> No
A64: 63 | B64: =B63+1 -> 46085 | C64: =MIN(ROUNDUP(A64/365,0),5) -> 1 | D64: =DATEDIF(Assumptions!B5,B64,"m")+1 -> 3 | E64: =TEXT(B64,"ddd") -> Wed | F64: =IF(WEEKDAY(B64,2)>=6,Assumptions!B34,Assumptions!B35) -> 1 | G64: =IF(D64>=13,(1+Assumptions!B46)^(D64-12),1) -> 1 | H64: =H63*(1+IF(C64=1,Assumptions!B22,Assumptions!B23)) -> 17.101812 | I64: =ROUND(H64*F64,0) -> 17 | J64: =I64*Assumptions!B24 -> 10200 | K64: =K63*(1+Assumptions!B30) -> 13.409639 | L64: =ROUND(K64*F64,0) -> 13 | M64: =L64*Assumptions!B31 -> 3900 | N64: =J64+M64 -> 14100 | O64: =IF(DAY(B64)=1,Assumptions!B38*G64,0) -> 0 | P64: =IF(DAY(B64)=1,Assumptions!B39*G64,0) -> 0 | Q64: =IF(DAY(B64)=1,Assumptions!B40*G64,0) -> 0 | R64: =IF(DAY(B64)=1,Assumptions!B41*G64,0) -> 0 | S64: =IF(AND(DAY(B64)=1,D64>=13),Assumptions!B42*G64,0) -> 0 | T64: =IF(DAY(B64)=1,Assumptions!B43*G64,0) -> 0 | U64: =SUM(O64:T64) -> 0 | V64: =N64-U64 -> 14100 | W64: =W63+V64 -> -4997300 | X64: =IF(W64>=0,"YES","No") -> No
A65: 64 | B65: =B64+1 -> 46086 | C65: =MIN(ROUNDUP(A65/365,0),5) -> 1 | D65: =DATEDIF(Assumptions!B5,B65,"m")+1 -> 3 | E65: =TEXT(B65,"ddd") -> Thu | F65: =IF(WEEKDAY(B65,2)>=6,Assumptions!B34,Assumptions!B35) -> 1 | G65: =IF(D65>=13,(1+Assumptions!B46)^(D65-12),1) -> 1 | H65: =H64*(1+IF(C65=1,Assumptions!B22,Assumptions!B23)) -> 17.112941 | I65: =ROUND(H65*F65,0) -> 17 | J65: =I65*Assumptions!B24 -> 10200 | K65: =K64*(1+Assumptions!B30) -> 13.414023 | L65: =ROUND(K65*F65,0) -> 13 | M65: =L65*Assumptions!B31 -> 3900 | N65: =J65+M65 -> 14100 | O65: =IF(DAY(B65)=1,Assumptions!B38*G65,0) -> 0 | P65: =IF(DAY(B65)=1,Assumptions!B39*G65,0) -> 0 | Q65: =IF(DAY(B65)=1,Assumptions!B40*G65,0) -> 0 | R65: =IF(DAY(B65)=1,Assumptions!B41*G65,0) -> 0 | S65: =IF(AND(DAY(B65)=1,D65>=13),Assumptions!B42*G65,0) -> 0 | T65: =IF(DAY(B65)=1,Assumptions!B43*G65,0) -> 0 | U65: =SUM(O65:T65) -> 0 | V65: =N65-U65 -> 14100 | W65: =W64+V65 -> -4983200 | X65: =IF(W65>=0,"YES","No") -> No
A66: 65 | B66: =B65+1 -> 46087 | C66: =MIN(ROUNDUP(A66/365,0),5) -> 1 | D66: =DATEDIF(Assumptions!B5,B66,"m")+1 -> 3 | E66: =TEXT(B66,"ddd") -> Fri | F66: =IF(WEEKDAY(B66,2)>=6,Assumptions!B34,Assumptions!B35) -> 1 | G66: =IF(D66>=13,(1+Assumptions!B46)^(D66-12),1) -> 1 | H66: =H65*(1+IF(C66=1,Assumptions!B22,Assumptions!B23)) -> 17.124078 | I66: =ROUND(H66*F66,0) -> 17 | J66: =I66*Assumptions!B24 -> 10200 | K66: =K65*(1+Assumptions!B30) -> 13.418409 | L66: =ROUND(K66*F66,0) -> 13 | M66: =L66*Assumptions!B31 -> 3900 | N66: =J66+M66 -> 14100 | O66: =IF(DAY(B66)=1,Assumptions!B38*G66,0) -> 0 | P66: =IF(DAY(B66)=1,Assumptions!B39*G66,0) -> 0 | Q66: =IF(DAY(B66)=1,Assumptions!B40*G66,0) -> 0 | R66: =IF(DAY(B66)=1,Assumptions!B41*G66,0) -> 0 | S66: =IF(AND(DAY(B66)=1,D66>=13),Assumptions!B42*G66,0) -> 0 | T66: =IF(DAY(B66)=1,Assumptions!B43*G66,0) -> 0 | U66: =SUM(O66:T66) -> 0 | V66: =N66-U66 -> 14100 | W66: =W65+V66 -> -4969100 | X66: =IF(W66>=0,"YES","No") -> No
A67: 66 | B67: =B66+1 -> 46088 | C67: =MIN(ROUNDUP(A67/365,0),5) -> 1 | D67: =DATEDIF(Assumptions!B5,B67,"m")+1 -> 3 | E67: =TEXT(B67,"ddd") -> Sat | F67: =IF(WEEKDAY(B67,2)>=6,Assumptions!B34,Assumptions!B35) -> 0.6 | G67: =IF(D67>=13,(1+Assumptions!B46)^(D67-12),1) -> 1 | H67: =H66*(1+IF(C67=1,Assumptions!B22,Assumptions!B23)) -> 17.135221 | I67: =ROUND(H67*F67,0) -> 10 | J67: =I67*Assumptions!B24 -> 6000 | K67: =K66*(1+Assumptions!B30) -> 13.422796 | L67: =ROUND(K67*F67,0) -> 8 | M67: =L67*Assumptions!B31 -> 2400 | N67: =J67+M67 -> 8400 | O67: =IF(DAY(B67)=1,Assumptions!B38*G67,0) -> 0 | P67: =IF(DAY(B67)=1,Assumptions!B39*G67,0) -> 0 | Q67: =IF(DAY(B67)=1,Assumptions!B40*G67,0) -> 0 | R67: =IF(DAY(B67)=1,Assumptions!B41*G67,0) -> 0 | S67: =IF(AND(DAY(B67)=1,D67>=13),Assumptions!B42*G67,0) -> 0 | T67: =IF(DAY(B67)=1,Assumptions!B43*G67,0) -> 0 | U67: =SUM(O67:T67) -> 0 | V67: =N67-U67 -> 8400 | W67: =W66+V67 -> -4960700 | X67: =IF(W67>=0,"YES","No") -> No
A68: 67 | B68: =B67+1 -> 46089 | C68: =MIN(ROUNDUP(A68/365,0),5) -> 1 | D68: =DATEDIF(Assumptions!B5,B68,"m")+1 -> 3 | E68: =TEXT(B68,"ddd") -> Sun | F68: =IF(WEEKDAY(B68,2)>=6,Assumptions!B34,Assumptions!B35) -> 0.6 | G68: =IF(D68>=13,(1+Assumptions!B46)^(D68-12),1) -> 1 | H68: =H67*(1+IF(C68=1,Assumptions!B22,Assumptions!B23)) -> 17.146372 | I68: =ROUND(H68*F68,0) -> 10 | J68: =I68*Assumptions!B24 -> 6000 | K68: =K67*(1+Assumptions!B30) -> 13.427184 | L68: =ROUND(K68*F68,0) -> 8 | M68: =L68*Assumptions!B31 -> 2400 | N68: =J68+M68 -> 8400 | O68: =IF(DAY(B68)=1,Assumptions!B38*G68,0) -> 0 | P68: =IF(DAY(B68)=1,Assumptions!B39*G68,0) -> 0 | Q68: =IF(DAY(B68)=1,Assumptions!B40*G68,0) -> 0 | R68: =IF(DAY(B68)=1,Assumptions!B41*G68,0) -> 0 | S68: =IF(AND(DAY(B68)=1,D68>=13),Assumptions!B42*G68,0) -> 0 | T68: =IF(DAY(B68)=1,Assumptions!B43*G68,0) -> 0 | U68: =SUM(O68:T68) -> 0 | V68: =N68-U68 -> 8400 | W68: =W67+V68 -> -4952300 | X68: =IF(W68>=0,"YES","No") -> No
A69: 68 | B69: =B68+1 -> 46090 | C69: =MIN(ROUNDUP(A69/365,0),5) -> 1 | D69: =DATEDIF(Assumptions!B5,B69,"m")+1 -> 3 | E69: =TEXT(B69,"ddd") -> Mon | F69: =IF(WEEKDAY(B69,2)>=6,Assumptions!B34,Assumptions!B35) -> 1 | G69: =IF(D69>=13,(1+Assumptions!B46)^(D69-12),1) -> 1 | H69: =H68*(1+IF(C69=1,Assumptions!B22,Assumptions!B23)) -> 17.15753 | I69: =ROUND(H69*F69,0) -> 17 | J69: =I69*Assumptions!B24 -> 10200 | K69: =K68*(1+Assumptions!B30) -> 13.431574 | L69: =ROUND(K69*F69,0) -> 13 | M69: =L69*Assumptions!B31 -> 3900 | N69: =J69+M69 -> 14100 | O69: =IF(DAY(B69)=1,Assumptions!B38*G69,0) -> 0 | P69: =IF(DAY(B69)=1,Assumptions!B39*G69,0) -> 0 | Q69: =IF(DAY(B69)=1,Assumptions!B40*G69,0) -> 0 | R69: =IF(DAY(B69)=1,Assumptions!B41*G69,0) -> 0 | S69: =IF(AND(DAY(B69)=1,D69>=13),Assumptions!B42*G69,0) -> 0 | T69: =IF(DAY(B69)=1,Assumptions!B43*G69,0) -> 0 | U69: =SUM(O69:T69) -> 0 | V69: =N69-U69 -> 14100 | W69: =W68+V69 -> -4938200 | X69: =IF(W69>=0,"YES","No") -> No
A70: 69 | B70: =B69+1 -> 46091 | C70: =MIN(ROUNDUP(A70/365,0),5) -> 1 | D70: =DATEDIF(Assumptions!B5,B70,"m")+1 -> 3 | E70: =TEXT(B70,"ddd") -> Tue | F70: =IF(WEEKDAY(B70,2)>=6,Assumptions!B34,Assumptions!B35) -> 1 | G70: =IF(D70>=13,(1+Assumptions!B46)^(D70-12),1) -> 1 | H70: =H69*(1+IF(C70=1,Assumptions!B22,Assumptions!B23)) -> 17.168696 | I70: =ROUND(H70*F70,0) -> 17 | J70: =I70*Assumptions!B24 -> 10200 | K70: =K69*(1+Assumptions!B30) -> 13.435965 | L70: =ROUND(K70*F70,0) -> 13 | M70: =L70*Assumptions!B31 -> 3900 | N70: =J70+M70 -> 14100 | O70: =IF(DAY(B70)=1,Assumptions!B38*G70,0) -> 0 | P70: =IF(DAY(B70)=1,Assumptions!B39*G70,0) -> 0 | Q70: =IF(DAY(B70)=1,Assumptions!B40*G70,0) -> 0 | R70: =IF(DAY(B70)=1,Assumptions!B41*G70,0) -> 0 | S70: =IF(AND(DAY(B70)=1,D70>=13),Assumptions!B42*G70,0) -> 0 | T70: =IF(DAY(B70)=1,Assumptions!B43*G70,0) -> 0 | U70: =SUM(O70:T70) -> 0 | V70: =N70-U70 -> 14100 | W70: =W69+V70 -> -4924100 | X70: =IF(W70>=0,"YES","No") -> No
A71: 70 | B71: =B70+1 -> 46092 | C71: =MIN(ROUNDUP(A71/365,0),5) -> 1 | D71: =DATEDIF(Assumptions!B5,B71,"m")+1 -> 3 | E71: =TEXT(B71,"ddd") -> Wed | F71: =IF(WEEKDAY(B71,2)>=6,Assumptions!B34,Assumptions!B35) -> 1 | G71: =IF(D71>=13,(1+Assumptions!B46)^(D71-12),1) -> 1 | H71: =H70*(1+IF(C71=1,Assumptions!B22,Assumptions!B23)) -> 17.179868 | I71: =ROUND(H71*F71,0) -> 17 | J71: =I71*Assumptions!B24 -> 10200 | K71: =K70*(1+Assumptions!B30) -> 13.440358 | L71: =ROUND(K71*F71,0) -> 13 | M71: =L71*Assumptions!B31 -> 3900 | N71: =J71+M71 -> 14100 | O71: =IF(DAY(B71)=1,Assumptions!B38*G71,0) -> 0 | P71: =IF(DAY(B71)=1,Assumptions!B39*G71,0) -> 0 | Q71: =IF(DAY(B71)=1,Assumptions!B40*G71,0) -> 0 | R71: =IF(DAY(B71)=1,Assumptions!B41*G71,0) -> 0 | S71: =IF(AND(DAY(B71)=1,D71>=13),Assumptions!B42*G71,0) -> 0 | T71: =IF(DAY(B71)=1,Assumptions!B43*G71,0) -> 0 | U71: =SUM(O71:T71) -> 0 | V71: =N71-U71 -> 14100 | W71: =W70+V71 -> -4910000 | X71: =IF(W71>=0,"YES","No") -> No
A72: 71 | B72: =B71+1 -> 46093 | C72: =MIN(ROUNDUP(A72/365,0),5) -> 1 | D72: =DATEDIF(Assumptions!B5,B72,"m")+1 -> 3 | E72: =TEXT(B72,"ddd") -> Thu | F72: =IF(WEEKDAY(B72,2)>=6,Assumptions!B34,Assumptions!B35) -> 1 | G72: =IF(D72>=13,(1+Assumptions!B46)^(D72-12),1) -> 1 | H72: =H71*(1+IF(C72=1,Assumptions!B22,Assumptions!B23)) -> 17.191048 | I72: =ROUND(H72*F72,0) -> 17 | J72: =I72*Assumptions!B24 -> 10200 | K72: =K71*(1+Assumptions!B30) -> 13.444752 | L72: =ROUND(K72*F72,0) -> 13 | M72: =L72*Assumptions!B31 -> 3900 | N72: =J72+M72 -> 14100 | O72: =IF(DAY(B72)=1,Assumptions!B38*G72,0) -> 0 | P72: =IF(DAY(B72)=1,Assumptions!B39*G72,0) -> 0 | Q72: =IF(DAY(B72)=1,Assumptions!B40*G72,0) -> 0 | R72: =IF(DAY(B72)=1,Assumptions!B41*G72,0) -> 0 | S72: =IF(AND(DAY(B72)=1,D72>=13),Assumptions!B42*G72,0) -> 0 | T72: =IF(DAY(B72)=1,Assumptions!B43*G72,0) -> 0 | U72: =SUM(O72:T72) -> 0 | V72: =N72-U72 -> 14100 | W72: =W71+V72 -> -4895900 | X72: =IF(W72>=0,"YES","No") -> No
A73: 72 | B73: =B72+1 -> 46094 | C73: =MIN(ROUNDUP(A73/365,0),5) -> 1 | D73: =DATEDIF(Assumptions!B5,B73,"m")+1 -> 3 | E73: =TEXT(B73,"ddd") -> Fri | F73: =IF(WEEKDAY(B73,2)>=6,Assumptions!B34,Assumptions!B35) -> 1 | G73: =IF(D73>=13,(1+Assumptions!B46)^(D73-12),1) -> 1 | H73: =H72*(1+IF(C73=1,Assumptions!B22,Assumptions!B23)) -> 17.202236 | I73: =ROUND(H73*F73,0) -> 17 | J73: =I73*Assumptions!B24 -> 10200 | K73: =K72*(1+Assumptions!B30) -> 13.449148 | L73: =ROUND(K73*F73,0) -> 13 | M73: =L73*Assumptions!B31 -> 3900 | N73: =J73+M73 -> 14100 | O73: =IF(DAY(B73)=1,Assumptions!B38*G73,0) -> 0 | P73: =IF(DAY(B73)=1,Assumptions!B39*G73,0) -> 0 | Q73: =IF(DAY(B73)=1,Assumptions!B40*G73,0) -> 0 | R73: =IF(DAY(B73)=1,Assumptions!B41*G73,0) -> 0 | S73: =IF(AND(DAY(B73)=1,D73>=13),Assumptions!B42*G73,0) -> 0 | T73: =IF(DAY(B73)=1,Assumptions!B43*G73,0) -> 0 | U73: =SUM(O73:T73) -> 0 | V73: =N73-U73 -> 14100 | W73: =W72+V73 -> -4881800 | X73: =IF(W73>=0,"YES","No") -> No
A74: 73 | B74: =B73+1 -> 46095 | C74: =MIN(ROUNDUP(A74/365,0),5) -> 1 | D74: =DATEDIF(Assumptions!B5,B74,"m")+1 -> 3 | E74: =TEXT(B74,"ddd") -> Sat | F74: =IF(WEEKDAY(B74,2)>=6,Assumptions!B34,Assumptions!B35) -> 0.6 | G74: =IF(D74>=13,(1+Assumptions!B46)^(D74-12),1) -> 1 | H74: =H73*(1+IF(C74=1,Assumptions!B22,Assumptions!B23)) -> 17.21343 | I74: =ROUND(H74*F74,0) -> 10 | J74: =I74*Assumptions!B24 -> 6000 | K74: =K73*(1+Assumptions!B30) -> 13.453545 | L74: =ROUND(K74*F74,0) -> 8 | M74: =L74*Assumptions!B31 -> 2400 | N74: =J74+M74 -> 8400 | O74: =IF(DAY(B74)=1,Assumptions!B38*G74,0) -> 0 | P74: =IF(DAY(B74)=1,Assumptions!B39*G74,0) -> 0 | Q74: =IF(DAY(B74)=1,Assumptions!B40*G74,0) -> 0 | R74: =IF(DAY(B74)=1,Assumptions!B41*G74,0) -> 0 | S74: =IF(AND(DAY(B74)=1,D74>=13),Assumptions!B42*G74,0) -> 0 | T74: =IF(DAY(B74)=1,Assumptions!B43*G74,0) -> 0 | U74: =SUM(O74:T74) -> 0 | V74: =N74-U74 -> 8400 | W74: =W73+V74 -> -4873400 | X74: =IF(W74>=0,"YES","No") -> No
A75: 74 | B75: =B74+1 -> 46096 | C75: =MIN(ROUNDUP(A75/365,0),5) -> 1 | D75: =DATEDIF(Assumptions!B5,B75,"m")+1 -> 3 | E75: =TEXT(B75,"ddd") -> Sun | F75: =IF(WEEKDAY(B75,2)>=6,Assumptions!B34,Assumptions!B35) -> 0.6 | G75: =IF(D75>=13,(1+Assumptions!B46)^(D75-12),1) -> 1 | H75: =H74*(1+IF(C75=1,Assumptions!B22,Assumptions!B23)) -> 17.224632 | I75: =ROUND(H75*F75,0) -> 10 | J75: =I75*Assumptions!B24 -> 6000 | K75: =K74*(1+Assumptions!B30) -> 13.457943 | L75: =ROUND(K75*F75,0) -> 8 | M75: =L75*Assumptions!B31 -> 2400 | N75: =J75+M75 -> 8400 | O75: =IF(DAY(B75)=1,Assumptions!B38*G75,0) -> 0 | P75: =IF(DAY(B75)=1,Assumptions!B39*G75,0) -> 0 | Q75: =IF(DAY(B75)=1,Assumptions!B40*G75,0) -> 0 | R75: =IF(DAY(B75)=1,Assumptions!B41*G75,0) -> 0 | S75: =IF(AND(DAY(B75)=1,D75>=13),Assumptions!B42*G75,0) -> 0 | T75: =IF(DAY(B75)=1,Assumptions!B43*G75,0) -> 0 | U75: =SUM(O75:T75) -> 0 | V75: =N75-U75 -> 8400 | W75: =W74+V75 -> -4865000 | X75: =IF(W75>=0,"YES","No") -> No
A76: 75 | B76: =B75+1 -> 46097 | C76: =MIN(ROUNDUP(A76/365,0),5) -> 1 | D76: =DATEDIF(Assumptions!B5,B76,"m")+1 -> 3 | E76: =TEXT(B76,"ddd") -> Mon | F76: =IF(WEEKDAY(B76,2)>=6,Assumptions!B34,Assumptions!B35) -> 1 | G76: =IF(D76>=13,(1+Assumptions!B46)^(D76-12),1) -> 1 | H76: =H75*(1+IF(C76=1,Assumptions!B22,Assumptions!B23)) -> 17.235841 | I76: =ROUND(H76*F76,0) -> 17 | J76: =I76*Assumptions!B24 -> 10200 | K76: =K75*(1+Assumptions!B30) -> 13.462343 | L76: =ROUND(K76*F76,0) -> 13 | M76: =L76*Assumptions!B31 -> 3900 | N76: =J76+M76 -> 14100 | O76: =IF(DAY(B76)=1,Assumptions!B38*G76,0) -> 0 | P76: =IF(DAY(B76)=1,Assumptions!B39*G76,0) -> 0 | Q76: =IF(DAY(B76)=1,Assumptions!B40*G76,0) -> 0 | R76: =IF(DAY(B76)=1,Assumptions!B41*G76,0) -> 0 | S76: =IF(AND(DAY(B76)=1,D76>=13),Assumptions!B42*G76,0) -> 0 | T76: =IF(DAY(B76)=1,Assumptions!B43*G76,0) -> 0 | U76: =SUM(O76:T76) -> 0 | V76: =N76-U76 -> 14100 | W76: =W75+V76 -> -4850900 | X76: =IF(W76>=0,"YES","No") -> No
A77: 76 | B77: =B76+1 -> 46098 | C77: =MIN(ROUNDUP(A77/365,0),5) -> 1 | D77: =DATEDIF(Assumptions!B5,B77,"m")+1 -> 3 | E77: =TEXT(B77,"ddd") -> Tue | F77: =IF(WEEKDAY(B77,2)>=6,Assumptions!B34,Assumptions!B35) -> 1 | G77: =IF(D77>=13,(1+Assumptions!B46)^(D77-12),1) -> 1 | H77: =H76*(1+IF(C77=1,Assumptions!B22,Assumptions!B23)) -> 17.247057 | I77: =ROUND(H77*F77,0) -> 17 | J77: =I77*Assumptions!B24 -> 10200 | K77: =K76*(1+Assumptions!B30) -> 13.466744 | L77: =ROUND(K77*F77,0) -> 13 | M77: =L77*Assumptions!B31 -> 3900 | N77: =J77+M77 -> 14100 | O77: =IF(DAY(B77)=1,Assumptions!B38*G77,0) -> 0 | P77: =IF(DAY(B77)=1,Assumptions!B39*G77,0) -> 0 | Q77: =IF(DAY(B77)=1,Assumptions!B40*G77,0) -> 0 | R77: =IF(DAY(B77)=1,Assumptions!B41*G77,0) -> 0 | S77: =IF(AND(DAY(B77)=1,D77>=13),Assumptions!B42*G77,0) -> 0 | T77: =IF(DAY(B77)=1,Assumptions!B43*G77,0) -> 0 | U77: =SUM(O77:T77) -> 0 | V77: =N77-U77 -> 14100 | W77: =W76+V77 -> -4836800 | X77: =IF(W77>=0,"YES","No") -> No
A78: 77 | B78: =B77+1 -> 46099 | C78: =MIN(ROUNDUP(A78/365,0),5) -> 1 | D78: =DATEDIF(Assumptions!B5,B78,"m")+1 -> 3 | E78: =TEXT(B78,"ddd") -> Wed | F78: =IF(WEEKDAY(B78,2)>=6,Assumptions!B34,Assumptions!B35) -> 1 | G78: =IF(D78>=13,(1+Assumptions!B46)^(D78-12),1) -> 1 | H78: =H77*(1+IF(C78=1,Assumptions!B22,Assumptions!B23)) -> 17.258281 | I78: =ROUND(H78*F78,0) -> 17 | J78: =I78*Assumptions!B24 -> 10200 | K78: =K77*(1+Assumptions!B30) -> 13.471147 | L78: =ROUND(K78*F78,0) -> 13 | M78: =L78*Assumptions!B31 -> 3900 | N78: =J78+M78 -> 14100 | O78: =IF(DAY(B78)=1,Assumptions!B38*G78,0) -> 0 | P78: =IF(DAY(B78)=1,Assumptions!B39*G78,0) -> 0 | Q78: =IF(DAY(B78)=1,Assumptions!B40*G78,0) -> 0 | R78: =IF(DAY(B78)=1,Assumptions!B41*G78,0) -> 0 | S78: =IF(AND(DAY(B78)=1,D78>=13),Assumptions!B42*G78,0) -> 0 | T78: =IF(DAY(B78)=1,Assumptions!B43*G78,0) -> 0 | U78: =SUM(O78:T78) -> 0 | V78: =N78-U78 -> 14100 | W78: =W77+V78 -> -4822700 | X78: =IF(W78>=0,"YES","No") -> No
A79: 78 | B79: =B78+1 -> 46100 | C79: =MIN(ROUNDUP(A79/365,0),5) -> 1 | D79: =DATEDIF(Assumptions!B5,B79,"m")+1 -> 3 | E79: =TEXT(B79,"ddd") -> Thu | F79: =IF(WEEKDAY(B79,2)>=6,Assumptions!B34,Assumptions!B35) -> 1 | G79: =IF(D79>=13,(1+Assumptions!B46)^(D79-12),1) -> 1 | H79: =H78*(1+IF(C79=1,Assumptions!B22,Assumptions!B23)) -> 17.269512 | I79: =ROUND(H79*F79,0) -> 17 | J79: =I79*Assumptions!B24 -> 10200 | K79: =K78*(1+Assumptions!B30) -> 13.475551 | L79: =ROUND(K79*F79,0) -> 13 | M79: =L79*Assumptions!B31 -> 3900 | N79: =J79+M79 -> 14100 | O79: =IF(DAY(B79)=1,Assumptions!B38*G79,0) -> 0 | P79: =IF(DAY(B79)=1,Assumptions!B39*G79,0) -> 0 | Q79: =IF(DAY(B79)=1,Assumptions!B40*G79,0) -> 0 | R79: =IF(DAY(B79)=1,Assumptions!B41*G79,0) -> 0 | S79: =IF(AND(DAY(B79)=1,D79>=13),Assumptions!B42*G79,0) -> 0 | T79: =IF(DAY(B79)=1,Assumptions!B43*G79,0) -> 0 | U79: =SUM(O79:T79) -> 0 | V79: =N79-U79 -> 14100 | W79: =W78+V79 -> -4808600 | X79: =IF(W79>=0,"YES","No") -> No
A80: 79 | B80: =B79+1 -> 46101 | C80: =MIN(ROUNDUP(A80/365,0),5) -> 1 | D80: =DATEDIF(Assumptions!B5,B80,"m")+1 -> 3 | E80: =TEXT(B80,"ddd") -> Fri | F80: =IF(WEEKDAY(B80,2)>=6,Assumptions!B34,Assumptions!B35) -> 1 | G80: =IF(D80>=13,(1+Assumptions!B46)^(D80-12),1) -> 1 | H80: =H79*(1+IF(C80=1,Assumptions!B22,Assumptions!B23)) -> 17.28075 | I80: =ROUND(H80*F80,0) -> 17 | J80: =I80*Assumptions!B24 -> 10200 | K80: =K79*(1+Assumptions!B30) -> 13.479957 | L80: =ROUND(K80*F80,0) -> 13 | M80: =L80*Assumptions!B31 -> 3900 | N80: =J80+M80 -> 14100 | O80: =IF(DAY(B80)=1,Assumptions!B38*G80,0) -> 0 | P80: =IF(DAY(B80)=1,Assumptions!B39*G80,0) -> 0 | Q80: =IF(DAY(B80)=1,Assumptions!B40*G80,0) -> 0 | R80: =IF(DAY(B80)=1,Assumptions!B41*G80,0) -> 0 | S80: =IF(AND(DAY(B80)=1,D80>=13),Assumptions!B42*G80,0) -> 0 | T80: =IF(DAY(B80)=1,Assumptions!B43*G80,0) -> 0 | U80: =SUM(O80:T80) -> 0 | V80: =N80-U80 -> 14100 | W80: =W79+V80 -> -4794500 | X80: =IF(W80>=0,"YES","No") -> No
A81: 80 | B81: =B80+1 -> 46102 | C81: =MIN(ROUNDUP(A81/365,0),5) -> 1 | D81: =DATEDIF(Assumptions!B5,B81,"m")+1 -> 3 | E81: =TEXT(B81,"ddd") -> Sat | F81: =IF(WEEKDAY(B81,2)>=6,Assumptions!B34,Assumptions!B35) -> 0.6 | G81: =IF(D81>=13,(1+Assumptions!B46)^(D81-12),1) -> 1 | H81: =H80*(1+IF(C81=1,Assumptions!B22,Assumptions!B23)) -> 17.291996 | I81: =ROUND(H81*F81,0) -> 10 | J81: =I81*Assumptions!B24 -> 6000 | K81: =K80*(1+Assumptions!B30) -> 13.484364 | L81: =ROUND(K81*F81,0) -> 8 | M81: =L81*Assumptions!B31 -> 2400 | N81: =J81+M81 -> 8400 | O81: =IF(DAY(B81)=1,Assumptions!B38*G81,0) -> 0 | P81: =IF(DAY(B81)=1,Assumptions!B39*G81,0) -> 0 | Q81: =IF(DAY(B81)=1,Assumptions!B40*G81,0) -> 0 | R81: =IF(DAY(B81)=1,Assumptions!B41*G81,0) -> 0 | S81: =IF(AND(DAY(B81)=1,D81>=13),Assumptions!B42*G81,0) -> 0 | T81: =IF(DAY(B81)=1,Assumptions!B43*G81,0) -> 0 | U81: =SUM(O81:T81) -> 0 | V81: =N81-U81 -> 8400 | W81: =W80+V81 -> -4786100 | X81: =IF(W81>=0,"YES","No") -> No
A82: 81 | B82: =B81+1 -> 46103 | C82: =MIN(ROUNDUP(A82/365,0),5) -> 1 | D82: =DATEDIF(Assumptions!B5,B82,"m")+1 -> 3 | E82: =TEXT(B82,"ddd") -> Sun | F82: =IF(WEEKDAY(B82,2)>=6,Assumptions!B34,Assumptions!B35) -> 0.6 | G82: =IF(D82>=13,(1+Assumptions!B46)^(D82-12),1) -> 1 | H82: =H81*(1+IF(C82=1,Assumptions!B22,Assumptions!B23)) -> 17.303249 | I82: =ROUND(H82*F82,0) -> 10 | J82: =I82*Assumptions!B24 -> 6000 | K82: =K81*(1+Assumptions!B30) -> 13.488773 | L82: =ROUND(K82*F82,0) -> 8 | M82: =L82*Assumptions!B31 -> 2400 | N82: =J82+M82 -> 8400 | O82: =IF(DAY(B82)=1,Assumptions!B38*G82,0) -> 0 | P82: =IF(DAY(B82)=1,Assumptions!B39*G82,0) -> 0 | Q82: =IF(DAY(B82)=1,Assumptions!B40*G82,0) -> 0 | R82: =IF(DAY(B82)=1,Assumptions!B41*G82,0) -> 0 | S82: =IF(AND(DAY(B82)=1,D82>=13),Assumptions!B42*G82,0) -> 0 | T82: =IF(DAY(B82)=1,Assumptions!B43*G82,0) -> 0 | U82: =SUM(O82:T82) -> 0 | V82: =N82-U82 -> 8400 | W82: =W81+V82 -> -4777700 | X82: =IF(W82>=0,"YES","No") -> No
A83: 82 | B83: =B82+1 -> 46104 | C83: =MIN(ROUNDUP(A83/365,0),5) -> 1 | D83: =DATEDIF(Assumptions!B5,B83,"m")+1 -> 3 | E83: =TEXT(B83,"ddd") -> Mon | F83: =IF(WEEKDAY(B83,2)>=6,Assumptions!B34,Assumptions!B35) -> 1 | G83: =IF(D83>=13,(1+Assumptions!B46)^(D83-12),1) -> 1 | H83: =H82*(1+IF(C83=1,Assumptions!B22,Assumptions!B23)) -> 17.314509 | I83: =ROUND(H83*F83,0) -> 17 | J83: =I83*Assumptions!B24 -> 10200 | K83: =K82*(1+Assumptions!B30) -> 13.493183 | L83: =ROUND(K83*F83,0) -> 13 | M83: =L83*Assumptions!B31 -> 3900 | N83: =J83+M83 -> 14100 | O83: =IF(DAY(B83)=1,Assumptions!B38*G83,0) -> 0 | P83: =IF(DAY(B83)=1,Assumptions!B39*G83,0) -> 0 | Q83: =IF(DAY(B83)=1,Assumptions!B40*G83,0) -> 0 | R83: =IF(DAY(B83)=1,Assumptions!B41*G83,0) -> 0 | S83: =IF(AND(DAY(B83)=1,D83>=13),Assumptions!B42*G83,0) -> 0 | T83: =IF(DAY(B83)=1,Assumptions!B43*G83,0) -> 0 | U83: =SUM(O83:T83) -> 0 | V83: =N83-U83 -> 14100 | W83: =W82+V83 -> -4763600 | X83: =IF(W83>=0,"YES","No") -> No
A84: 83 | B84: =B83+1 -> 46105 | C84: =MIN(ROUNDUP(A84/365,0),5) -> 1 | D84: =DATEDIF(Assumptions!B5,B84,"m")+1 -> 3 | E84: =TEXT(B84,"ddd") -> Tue | F84: =IF(WEEKDAY(B84,2)>=6,Assumptions!B34,Assumptions!B35) -> 1 | G84: =IF(D84>=13,(1+Assumptions!B46)^(D84-12),1) -> 1 | H84: =H83*(1+IF(C84=1,Assumptions!B22,Assumptions!B23)) -> 17.325776 | I84: =ROUND(H84*F84,0) -> 17 | J84: =I84*Assumptions!B24 -> 10200 | K84: =K83*(1+Assumptions!B30) -> 13.497594 | L84: =ROUND(K84*F84,0) -> 13 | M84: =L84*Assumptions!B31 -> 3900 | N84: =J84+M84 -> 14100 | O84: =IF(DAY(B84)=1,Assumptions!B38*G84,0) -> 0 | P84: =IF(DAY(B84)=1,Assumptions!B39*G84,0) -> 0 | Q84: =IF(DAY(B84)=1,Assumptions!B40*G84,0) -> 0 | R84: =IF(DAY(B84)=1,Assumptions!B41*G84,0) -> 0 | S84: =IF(AND(DAY(B84)=1,D84>=13),Assumptions!B42*G84,0) -> 0 | T84: =IF(DAY(B84)=1,Assumptions!B43*G84,0) -> 0 | U84: =SUM(O84:T84) -> 0 | V84: =N84-U84 -> 14100 | W84: =W83+V84 -> -4749500 | X84: =IF(W84>=0,"YES","No") -> No
A85: 84 | B85: =B84+1 -> 46106 | C85: =MIN(ROUNDUP(A85/365,0),5) -> 1 | D85: =DATEDIF(Assumptions!B5,B85,"m")+1 -> 3 | E85: =TEXT(B85,"ddd") -> Wed | F85: =IF(WEEKDAY(B85,2)>=6,Assumptions!B34,Assumptions!B35) -> 1 | G85: =IF(D85>=13,(1+Assumptions!B46)^(D85-12),1) -> 1 | H85: =H84*(1+IF(C85=1,Assumptions!B22,Assumptions!B23)) -> 17.337051 | I85: =ROUND(H85*F85,0) -> 17 | J85: =I85*Assumptions!B24 -> 10200 | K85: =K84*(1+Assumptions!B30) -> 13.502007 | L85: =ROUND(K85*F85,0) -> 14 | M85: =L85*Assumptions!B31 -> 4200 | N85: =J85+M85 -> 14400 | O85: =IF(DAY(B85)=1,Assumptions!B38*G85,0) -> 0 | P85: =IF(DAY(B85)=1,Assumptions!B39*G85,0) -> 0 | Q85: =IF(DAY(B85)=1,Assumptions!B40*G85,0) -> 0 | R85: =IF(DAY(B85)=1,Assumptions!B41*G85,0) -> 0 | S85: =IF(AND(DAY(B85)=1,D85>=13),Assumptions!B42*G85,0) -> 0 | T85: =IF(DAY(B85)=1,Assumptions!B43*G85,0) -> 0 | U85: =SUM(O85:T85) -> 0 | V85: =N85-U85 -> 14400 | W85: =W84+V85 -> -4735100 | X85: =IF(W85>=0,"YES","No") -> No
A86: 85 | B86: =B85+1 -> 46107 | C86: =MIN(ROUNDUP(A86/365,0),5) -> 1 | D86: =DATEDIF(Assumptions!B5,B86,"m")+1 -> 3 | E86: =TEXT(B86,"ddd") -> Thu | F86: =IF(WEEKDAY(B86,2)>=6,Assumptions!B34,Assumptions!B35) -> 1 | G86: =IF(D86>=13,(1+Assumptions!B46)^(D86-12),1) -> 1 | H86: =H85*(1+IF(C86=1,Assumptions!B22,Assumptions!B23)) -> 17.348333 | I86: =ROUND(H86*F86,0) -> 17 | J86: =I86*Assumptions!B24 -> 10200 | K86: =K85*(1+Assumptions!B30) -> 13.506421 | L86: =ROUND(K86*F86,0) -> 14 | M86: =L86*Assumptions!B31 -> 4200 | N86: =J86+M86 -> 14400 | O86: =IF(DAY(B86)=1,Assumptions!B38*G86,0) -> 0 | P86: =IF(DAY(B86)=1,Assumptions!B39*G86,0) -> 0 | Q86: =IF(DAY(B86)=1,Assumptions!B40*G86,0) -> 0 | R86: =IF(DAY(B86)=1,Assumptions!B41*G86,0) -> 0 | S86: =IF(AND(DAY(B86)=1,D86>=13),Assumptions!B42*G86,0) -> 0 | T86: =IF(DAY(B86)=1,Assumptions!B43*G86,0) -> 0 | U86: =SUM(O86:T86) -> 0 | V86: =N86-U86 -> 14400 | W86: =W85+V86 -> -4720700 | X86: =IF(W86>=0,"YES","No") -> No
A87: 86 | B87: =B86+1 -> 46108 | C87: =MIN(ROUNDUP(A87/365,0),5) -> 1 | D87: =DATEDIF(Assumptions!B5,B87,"m")+1 -> 3 | E87: =TEXT(B87,"ddd") -> Fri | F87: =IF(WEEKDAY(B87,2)>=6,Assumptions!B34,Assumptions!B35) -> 1 | G87: =IF(D87>=13,(1+Assumptions!B46)^(D87-12),1) -> 1 | H87: =H86*(1+IF(C87=1,Assumptions!B22,Assumptions!B23)) -> 17.359623 | I87: =ROUND(H87*F87,0) -> 17 | J87: =I87*Assumptions!B24 -> 10200 | K87: =K86*(1+Assumptions!B30) -> 13.510837 | L87: =ROUND(K87*F87,0) -> 14 | M87: =L87*Assumptions!B31 -> 4200 | N87: =J87+M87 -> 14400 | O87: =IF(DAY(B87)=1,Assumptions!B38*G87,0) -> 0 | P87: =IF(DAY(B87)=1,Assumptions!B39*G87,0) -> 0 | Q87: =IF(DAY(B87)=1,Assumptions!B40*G87,0) -> 0 | R87: =IF(DAY(B87)=1,Assumptions!B41*G87,0) -> 0 | S87: =IF(AND(DAY(B87)=1,D87>=13),Assumptions!B42*G87,0) -> 0 | T87: =IF(DAY(B87)=1,Assumptions!B43*G87,0) -> 0 | U87: =SUM(O87:T87) -> 0 | V87: =N87-U87 -> 14400 | W87: =W86+V87 -> -4706300 | X87: =IF(W87>=0,"YES","No") -> No
A88: 87 | B88: =B87+1 -> 46109 | C88: =MIN(ROUNDUP(A88/365,0),5) -> 1 | D88: =DATEDIF(Assumptions!B5,B88,"m")+1 -> 3 | E88: =TEXT(B88,"ddd") -> Sat | F88: =IF(WEEKDAY(B88,2)>=6,Assumptions!B34,Assumptions!B35) -> 0.6 | G88: =IF(D88>=13,(1+Assumptions!B46)^(D88-12),1) -> 1 | H88: =H87*(1+IF(C88=1,Assumptions!B22,Assumptions!B23)) -> 17.37092 | I88: =ROUND(H88*F88,0) -> 10 | J88: =I88*Assumptions!B24 -> 6000 | K88: =K87*(1+Assumptions!B30) -> 13.515254 | L88: =ROUND(K88*F88,0) -> 8 | M88: =L88*Assumptions!B31 -> 2400 | N88: =J88+M88 -> 8400 | O88: =IF(DAY(B88)=1,Assumptions!B38*G88,0) -> 0 | P88: =IF(DAY(B88)=1,Assumptions!B39*G88,0) -> 0 | Q88: =IF(DAY(B88)=1,Assumptions!B40*G88,0) -> 0 | R88: =IF(DAY(B88)=1,Assumptions!B41*G88,0) -> 0 | S88: =IF(AND(DAY(B88)=1,D88>=13),Assumptions!B42*G88,0) -> 0 | T88: =IF(DAY(B88)=1,Assumptions!B43*G88,0) -> 0 | U88: =SUM(O88:T88) -> 0 | V88: =N88-U88 -> 8400 | W88: =W87+V88 -> -4697900 | X88: =IF(W88>=0,"YES","No") -> No
A89: 88 | B89: =B88+1 -> 46110 | C89: =MIN(ROUNDUP(A89/365,0),5) -> 1 | D89: =DATEDIF(Assumptions!B5,B89,"m")+1 -> 3 | E89: =TEXT(B89,"ddd") -> Sun | F89: =IF(WEEKDAY(B89,2)>=6,Assumptions!B34,Assumptions!B35) -> 0.6 | G89: =IF(D89>=13,(1+Assumptions!B46)^(D89-12),1) -> 1 | H89: =H88*(1+IF(C89=1,Assumptions!B22,Assumptions!B23)) -> 17.382224 | I89: =ROUND(H89*F89,0) -> 10 | J89: =I89*Assumptions!B24 -> 6000 | K89: =K88*(1+Assumptions!B30) -> 13.519673 | L89: =ROUND(K89*F89,0) -> 8 | M89: =L89*Assumptions!B31 -> 2400 | N89: =J89+M89 -> 8400 | O89: =IF(DAY(B89)=1,Assumptions!B38*G89,0) -> 0 | P89: =IF(DAY(B89)=1,Assumptions!B39*G89,0) -> 0 | Q89: =IF(DAY(B89)=1,Assumptions!B40*G89,0) -> 0 | R89: =IF(DAY(B89)=1,Assumptions!B41*G89,0) -> 0 | S89: =IF(AND(DAY(B89)=1,D89>=13),Assumptions!B42*G89,0) -> 0 | T89: =IF(DAY(B89)=1,Assumptions!B43*G89,0) -> 0 | U89: =SUM(O89:T89) -> 0 | V89: =N89-U89 -> 8400 | W89: =W88+V89 -> -4689500 | X89: =IF(W89>=0,"YES","No") -> No
A90: 89 | B90: =B89+1 -> 46111 | C90: =MIN(ROUNDUP(A90/365,0),5) -> 1 | D90: =DATEDIF(Assumptions!B5,B90,"m")+1 -> 3 | E90: =TEXT(B90,"ddd") -> Mon | F90: =IF(WEEKDAY(B90,2)>=6,Assumptions!B34,Assumptions!B35) -> 1 | G90: =IF(D90>=13,(1+Assumptions!B46)^(D90-12),1) -> 1 | H90: =H89*(1+IF(C90=1,Assumptions!B22,Assumptions!B23)) -> 17.393536 | I90: =ROUND(H90*F90,0) -> 17 | J90: =I90*Assumptions!B24 -> 10200 | K90: =K89*(1+Assumptions!B30) -> 13.524093 | L90: =ROUND(K90*F90,0) -> 14 | M90: =L90*Assumptions!B31 -> 4200 | N90: =J90+M90 -> 14400 | O90: =IF(DAY(B90)=1,Assumptions!B38*G90,0) -> 0 | P90: =IF(DAY(B90)=1,Assumptions!B39*G90,0) -> 0 | Q90: =IF(DAY(B90)=1,Assumptions!B40*G90,0) -> 0 | R90: =IF(DAY(B90)=1,Assumptions!B41*G90,0) -> 0 | S90: =IF(AND(DAY(B90)=1,D90>=13),Assumptions!B42*G90,0) -> 0 | T90: =IF(DAY(B90)=1,Assumptions!B43*G90,0) -> 0 | U90: =SUM(O90:T90) -> 0 | V90: =N90-U90 -> 14400 | W90: =W89+V90 -> -4675100 | X90: =IF(W90>=0,"YES","No") -> No
A91: 90 | B91: =B90+1 -> 46112 | C91: =MIN(ROUNDUP(A91/365,0),5) -> 1 | D91: =DATEDIF(Assumptions!B5,B91,"m")+1 -> 3 | E91: =TEXT(B91,"ddd") -> Tue | F91: =IF(WEEKDAY(B91,2)>=6,Assumptions!B34,Assumptions!B35) -> 1 | G91: =IF(D91>=13,(1+Assumptions!B46)^(D91-12),1) -> 1 | H91: =H90*(1+IF(C91=1,Assumptions!B22,Assumptions!B23)) -> 17.404855 | I91: =ROUND(H91*F91,0) -> 17 | J91: =I91*Assumptions!B24 -> 10200 | K91: =K90*(1+Assumptions!B30) -> 13.528514 | L91: =ROUND(K91*F91,0) -> 14 | M91: =L91*Assumptions!B31 -> 4200 | N91: =J91+M91 -> 14400 | O91: =IF(DAY(B91)=1,Assumptions!B38*G91,0) -> 0 | P91: =IF(DAY(B91)=1,Assumptions!B39*G91,0) -> 0 | Q91: =IF(DAY(B91)=1,Assumptions!B40*G91,0) -> 0 | R91: =IF(DAY(B91)=1,Assumptions!B41*G91,0) -> 0 | S91: =IF(AND(DAY(B91)=1,D91>=13),Assumptions!B42*G91,0) -> 0 | T91: =IF(DAY(B91)=1,Assumptions!B43*G91,0) -> 0 | U91: =SUM(O91:T91) -> 0 | V91: =N91-U91 -> 14400 | W91: =W90+V91 -> -4660700 | X91: =IF(W91>=0,"YES","No") -> No
A92: 91 | B92: =B91+1 -> 46113 | C92: =MIN(ROUNDUP(A92/365,0),5) -> 1 | D92: =DATEDIF(Assumptions!B5,B92,"m")+1 -> 4 | E92: =TEXT(B92,"ddd") -> Wed | F92: =IF(WEEKDAY(B92,2)>=6,Assumptions!B34,Assumptions!B35) -> 1 | G92: =IF(D92>=13,(1+Assumptions!B46)^(D92-12),1) -> 1 | H92: =H91*(1+IF(C92=1,Assumptions!B22,Assumptions!B23)) -> 17.416181 | I92: =ROUND(H92*F92,0) -> 17 | J92: =I92*Assumptions!B24 -> 10200 | K92: =K91*(1+Assumptions!B30) -> 13.532937 | L92: =ROUND(K92*F92,0) -> 14 | M92: =L92*Assumptions!B31 -> 4200 | N92: =J92+M92 -> 14400 | O92: =IF(DAY(B92)=1,Assumptions!B38*G92,0) -> 150000 | P92: =IF(DAY(B92)=1,Assumptions!B39*G92,0) -> 40000 | Q92: =IF(DAY(B92)=1,Assumptions!B40*G92,0) -> 30000 | R92: =IF(DAY(B92)=1,Assumptions!B41*G92,0) -> 20000 | S92: =IF(AND(DAY(B92)=1,D92>=13),Assumptions!B42*G92,0) -> 0 | T92: =IF(DAY(B92)=1,Assumptions!B43*G92,0) -> 20000 | U92: =SUM(O92:T92) -> 260000 | V92: =N92-U92 -> -245600 | W92: =W91+V92 -> -4906300 | X92: =IF(W92>=0,"YES","No") -> No
A93: 92 | B93: =B92+1 -> 46114 | C93: =MIN(ROUNDUP(A93/365,0),5) -> 1 | D93: =DATEDIF(Assumptions!B5,B93,"m")+1 -> 4 | E93: =TEXT(B93,"ddd") -> Thu | F93: =IF(WEEKDAY(B93,2)>=6,Assumptions!B34,Assumptions!B35) -> 1 | G93: =IF(D93>=13,(1+Assumptions!B46)^(D93-12),1) -> 1 | H93: =H92*(1+IF(C93=1,Assumptions!B22,Assumptions!B23)) -> 17.427515 | I93: =ROUND(H93*F93,0) -> 17 | J93: =I93*Assumptions!B24 -> 10200 | K93: =K92*(1+Assumptions!B30) -> 13.537362 | L93: =ROUND(K93*F93,0) -> 14 | M93: =L93*Assumptions!B31 -> 4200 | N93: =J93+M93 -> 14400 | O93: =IF(DAY(B93)=1,Assumptions!B38*G93,0) -> 0 | P93: =IF(DAY(B93)=1,Assumptions!B39*G93,0) -> 0 | Q93: =IF(DAY(B93)=1,Assumptions!B40*G93,0) -> 0 | R93: =IF(DAY(B93)=1,Assumptions!B41*G93,0) -> 0 | S93: =IF(AND(DAY(B93)=1,D93>=13),Assumptions!B42*G93,0) -> 0 | T93: =IF(DAY(B93)=1,Assumptions!B43*G93,0) -> 0 | U93: =SUM(O93:T93) -> 0 | V93: =N93-U93 -> 14400 | W93: =W92+V93 -> -4891900 | X93: =IF(W93>=0,"YES","No") -> No
A94: 93 | B94: =B93+1 -> 46115 | C94: =MIN(ROUNDUP(A94/365,0),5) -> 1 | D94: =DATEDIF(Assumptions!B5,B94,"m")+1 -> 4 | E94: =TEXT(B94,"ddd") -> Fri | F94: =IF(WEEKDAY(B94,2)>=6,Assumptions!B34,Assumptions!B35) -> 1 | G94: =IF(D94>=13,(1+Assumptions!B46)^(D94-12),1) -> 1 | H94: =H93*(1+IF(C94=1,Assumptions!B22,Assumptions!B23)) -> 17.438856 | I94: =ROUND(H94*F94,0) -> 17 | J94: =I94*Assumptions!B24 -> 10200 | K94: =K93*(1+Assumptions!B30) -> 13.541788 | L94: =ROUND(K94*F94,0) -> 14 | M94: =L94*Assumptions!B31 -> 4200 | N94: =J94+M94 -> 14400 | O94: =IF(DAY(B94)=1,Assumptions!B38*G94,0) -> 0 | P94: =IF(DAY(B94)=1,Assumptions!B39*G94,0) -> 0 | Q94: =IF(DAY(B94)=1,Assumptions!B40*G94,0) -> 0 | R94: =IF(DAY(B94)=1,Assumptions!B41*G94,0) -> 0 | S94: =IF(AND(DAY(B94)=1,D94>=13),Assumptions!B42*G94,0) -> 0 | T94: =IF(DAY(B94)=1,Assumptions!B43*G94,0) -> 0 | U94: =SUM(O94:T94) -> 0 | V94: =N94-U94 -> 14400 | W94: =W93+V94 -> -4877500 | X94: =IF(W94>=0,"YES","No") -> No
A95: 94 | B95: =B94+1 -> 46116 | C95: =MIN(ROUNDUP(A95/365,0),5) -> 1 | D95: =DATEDIF(Assumptions!B5,B95,"m")+1 -> 4 | E95: =TEXT(B95,"ddd") -> Sat | F95: =IF(WEEKDAY(B95,2)>=6,Assumptions!B34,Assumptions!B35) -> 0.6 | G95: =IF(D95>=13,(1+Assumptions!B46)^(D95-12),1) -> 1 | H95: =H94*(1+IF(C95=1,Assumptions!B22,Assumptions!B23)) -> 17.450204 | I95: =ROUND(H95*F95,0) -> 10 | J95: =I95*Assumptions!B24 -> 6000 | K95: =K94*(1+Assumptions!B30) -> 13.546215 | L95: =ROUND(K95*F95,0) -> 8 | M95: =L95*Assumptions!B31 -> 2400 | N95: =J95+M95 -> 8400 | O95: =IF(DAY(B95)=1,Assumptions!B38*G95,0) -> 0 | P95: =IF(DAY(B95)=1,Assumptions!B39*G95,0) -> 0 | Q95: =IF(DAY(B95)=1,Assumptions!B40*G95,0) -> 0 | R95: =IF(DAY(B95)=1,Assumptions!B41*G95,0) -> 0 | S95: =IF(AND(DAY(B95)=1,D95>=13),Assumptions!B42*G95,0) -> 0 | T95: =IF(DAY(B95)=1,Assumptions!B43*G95,0) -> 0 | U95: =SUM(O95:T95) -> 0 | V95: =N95-U95 -> 8400 | W95: =W94+V95 -> -4869100 | X95: =IF(W95>=0,"YES","No") -> No
A96: 95 | B96: =B95+1 -> 46117 | C96: =MIN(ROUNDUP(A96/365,0),5) -> 1 | D96: =DATEDIF(Assumptions!B5,B96,"m")+1 -> 4 | E96: =TEXT(B96,"ddd") -> Sun | F96: =IF(WEEKDAY(B96,2)>=6,Assumptions!B34,Assumptions!B35) -> 0.6 | G96: =IF(D96>=13,(1+Assumptions!B46)^(D96-12),1) -> 1 | H96: =H95*(1+IF(C96=1,Assumptions!B22,Assumptions!B23)) -> 17.46156 | I96: =ROUND(H96*F96,0) -> 10 | J96: =I96*Assumptions!B24 -> 6000 | K96: =K95*(1+Assumptions!B30) -> 13.550644 | L96: =ROUND(K96*F96,0) -> 8 | M96: =L96*Assumptions!B31 -> 2400 | N96: =J96+M96 -> 8400 | O96: =IF(DAY(B96)=1,Assumptions!B38*G96,0) -> 0 | P96: =IF(DAY(B96)=1,Assumptions!B39*G96,0) -> 0 | Q96: =IF(DAY(B96)=1,Assumptions!B40*G96,0) -> 0 | R96: =IF(DAY(B96)=1,Assumptions!B41*G96,0) -> 0 | S96: =IF(AND(DAY(B96)=1,D96>=13),Assumptions!B42*G96,0) -> 0 | T96: =IF(DAY(B96)=1,Assumptions!B43*G96,0) -> 0 | U96: =SUM(O96:T96) -> 0 | V96: =N96-U96 -> 8400 | W96: =W95+V96 -> -4860700 | X96: =IF(W96>=0,"YES","No") -> No
A97: 96 | B97: =B96+1 -> 46118 | C97: =MIN(ROUNDUP(A97/365,0),5) -> 1 | D97: =DATEDIF(Assumptions!B5,B97,"m")+1 -> 4 | E97: =TEXT(B97,"ddd") -> Mon | F97: =IF(WEEKDAY(B97,2)>=6,Assumptions!B34,Assumptions!B35) -> 1 | G97: =IF(D97>=13,(1+Assumptions!B46)^(D97-12),1) -> 1 | H97: =H96*(1+IF(C97=1,Assumptions!B22,Assumptions!B23)) -> 17.472924 | I97: =ROUND(H97*F97,0) -> 17 | J97: =I97*Assumptions!B24 -> 10200 | K97: =K96*(1+Assumptions!B30) -> 13.555074 | L97: =ROUND(K97*F97,0) -> 14 | M97: =L97*Assumptions!B31 -> 4200 | N97: =J97+M97 -> 14400 | O97: =IF(DAY(B97)=1,Assumptions!B38*G97,0) -> 0 | P97: =IF(DAY(B97)=1,Assumptions!B39*G97,0) -> 0 | Q97: =IF(DAY(B97)=1,Assumptions!B40*G97,0) -> 0 | R97: =IF(DAY(B97)=1,Assumptions!B41*G97,0) -> 0 | S97: =IF(AND(DAY(B97)=1,D97>=13),Assumptions!B42*G97,0) -> 0 | T97: =IF(DAY(B97)=1,Assumptions!B43*G97,0) -> 0 | U97: =SUM(O97:T97) -> 0 | V97: =N97-U97 -> 14400 | W97: =W96+V97 -> -4846300 | X97: =IF(W97>=0,"YES","No") -> No
A98: 97 | B98: =B97+1 -> 46119 | C98: =MIN(ROUNDUP(A98/365,0),5) -> 1 | D98: =DATEDIF(Assumptions!B5,B98,"m")+1 -> 4 | E98: =TEXT(B98,"ddd") -> Tue | F98: =IF(WEEKDAY(B98,2)>=6,Assumptions!B34,Assumptions!B35) -> 1 | G98: =IF(D98>=13,(1+Assumptions!B46)^(D98-12),1) -> 1 | H98: =H97*(1+IF(C98=1,Assumptions!B22,Assumptions!B23)) -> 17.484294 | I98: =ROUND(H98*F98,0) -> 17 | J98: =I98*Assumptions!B24 -> 10200 | K98: =K97*(1+Assumptions!B30) -> 13.559506 | L98: =ROUND(K98*F98,0) -> 14 | M98: =L98*Assumptions!B31 -> 4200 | N98: =J98+M98 -> 14400 | O98: =IF(DAY(B98)=1,Assumptions!B38*G98,0) -> 0 | P98: =IF(DAY(B98)=1,Assumptions!B39*G98,0) -> 0 | Q98: =IF(DAY(B98)=1,Assumptions!B40*G98,0) -> 0 | R98: =IF(DAY(B98)=1,Assumptions!B41*G98,0) -> 0 | S98: =IF(AND(DAY(B98)=1,D98>=13),Assumptions!B42*G98,0) -> 0 | T98: =IF(DAY(B98)=1,Assumptions!B43*G98,0) -> 0 | U98: =SUM(O98:T98) -> 0 | V98: =N98-U98 -> 14400 | W98: =W97+V98 -> -4831900 | X98: =IF(W98>=0,"YES","No") -> No
A99: 98 | B99: =B98+1 -> 46120 | C99: =MIN(ROUNDUP(A99/365,0),5) -> 1 | D99: =DATEDIF(Assumptions!B5,B99,"m")+1 -> 4 | E99: =TEXT(B99,"ddd") -> Wed | F99: =IF(WEEKDAY(B99,2)>=6,Assumptions!B34,Assumptions!B35) -> 1 | G99: =IF(D99>=13,(1+Assumptions!B46)^(D99-12),1) -> 1 | H99: =H98*(1+IF(C99=1,Assumptions!B22,Assumptions!B23)) -> 17.495672 | I99: =ROUND(H99*F99,0) -> 17 | J99: =I99*Assumptions!B24 -> 10200 | K99: =K98*(1+Assumptions!B30) -> 13.563939 | L99: =ROUND(K99*F99,0) -> 14 | M99: =L99*Assumptions!B31 -> 4200 | N99: =J99+M99 -> 14400 | O99: =IF(DAY(B99)=1,Assumptions!B38*G99,0) -> 0 | P99: =IF(DAY(B99)=1,Assumptions!B39*G99,0) -> 0 | Q99: =IF(DAY(B99)=1,Assumptions!B40*G99,0) -> 0 | R99: =IF(DAY(B99)=1,Assumptions!B41*G99,0) -> 0 | S99: =IF(AND(DAY(B99)=1,D99>=13),Assumptions!B42*G99,0) -> 0 | T99: =IF(DAY(B99)=1,Assumptions!B43*G99,0) -> 0 | U99: =SUM(O99:T99) -> 0 | V99: =N99-U99 -> 14400 | W99: =W98+V99 -> -4817500 | X99: =IF(W99>=0,"YES","No") -> No
A100: 99 | B100: =B99+1 -> 46121 | C100: =MIN(ROUNDUP(A100/365,0),5) -> 1 | D100: =DATEDIF(Assumptions!B5,B100,"m")+1 -> 4 | E100: =TEXT(B100,"ddd") -> Thu | F100: =IF(WEEKDAY(B100,2)>=6,Assumptions!B34,Assumptions!B35) -> 1 | G100: =IF(D100>=13,(1+Assumptions!B46)^(D100-12),1) -> 1 | H100: =H99*(1+IF(C100=1,Assumptions!B22,Assumptions!B23)) -> 17.507058 | I100: =ROUND(H100*F100,0) -> 18 | J100: =I100*Assumptions!B24 -> 10800 | K100: =K99*(1+Assumptions!B30) -> 13.568373 | L100: =ROUND(K100*F100,0) -> 14 | M100: =L100*Assumptions!B31 -> 4200 | N100: =J100+M100 -> 15000 | O100: =IF(DAY(B100)=1,Assumptions!B38*G100,0) -> 0 | P100: =IF(DAY(B100)=1,Assumptions!B39*G100,0) -> 0 | Q100: =IF(DAY(B100)=1,Assumptions!B40*G100,0) -> 0 | R100: =IF(DAY(B100)=1,Assumptions!B41*G100,0) -> 0 | S100: =IF(AND(DAY(B100)=1,D100>=13),Assumptions!B42*G100,0) -> 0 | T100: =IF(DAY(B100)=1,Assumptions!B43*G100,0) -> 0 | U100: =SUM(O100:T100) -> 0 | V100: =N100-U100 -> 15000 | W100: =W99+V100 -> -4802500 | X100: =IF(W100>=0,"YES","No") -> No
...

Sheet Monthly Summary
A1: Calendar Month # | B1: MM Transactions | C1: Commission Revenue | D1: Airtime Transactions | E1: Airtime Revenue | F1: Total Revenue | G1: Total Costs | H1: Net Profit | I1: Cumulative Net Cash Position (month-end)
A2: 1 | B2: =SUMIF('Daily Ledger'!$D$2:$D$1827,A2,'Daily Ledger'!$I$2:$I$1827) -> 459 | C2: =SUMIF('Daily Ledger'!$D$2:$D$1827,A2,'Daily Ledger'!$J$2:$J$1827) -> 275400 | D2: =SUMIF('Daily Ledger'!$D$2:$D$1827,A2,'Daily Ledger'!$L$2:$L$1827) -> 358 | E2: =SUMIF('Daily Ledger'!$D$2:$D$1827,A2,'Daily Ledger'!$M$2:$M$1827) -> 107400 | F2: =SUMIF('Daily Ledger'!$D$2:$D$1827,A2,'Daily Ledger'!$N$2:$N$1827) -> 382800 | G2: =SUMIF('Daily Ledger'!$D$2:$D$1827,A2,'Daily Ledger'!$U$2:$U$1827) -> 260000 | H2: =SUMIF('Daily Ledger'!$D$2:$D$1827,A2,'Daily Ledger'!$V$2:$V$1827) -> 122800 | I2: =LOOKUP(2,1/('Daily Ledger'!$D$2:$D$1827=A2),'Daily Ledger'!$W$2:$W$1827) -> -4877200
A3: 2 | B3: =SUMIF('Daily Ledger'!$D$2:$D$1827,A3,'Daily Ledger'!$I$2:$I$1827) -> 420 | C3: =SUMIF('Daily Ledger'!$D$2:$D$1827,A3,'Daily Ledger'!$J$2:$J$1827) -> 252000 | D3: =SUMIF('Daily Ledger'!$D$2:$D$1827,A3,'Daily Ledger'!$L$2:$L$1827) -> 324 | E3: =SUMIF('Daily Ledger'!$D$2:$D$1827,A3,'Daily Ledger'!$M$2:$M$1827) -> 97200 | F3: =SUMIF('Daily Ledger'!$D$2:$D$1827,A3,'Daily Ledger'!$N$2:$N$1827) -> 349200 | G3: =SUMIF('Daily Ledger'!$D$2:$D$1827,A3,'Daily Ledger'!$U$2:$U$1827) -> 260000 | H3: =SUMIF('Daily Ledger'!$D$2:$D$1827,A3,'Daily Ledger'!$V$2:$V$1827) -> 89200 | I3: =LOOKUP(2,1/('Daily Ledger'!$D$2:$D$1827=A3),'Daily Ledger'!$W$2:$W$1827) -> -4788000
A4: 3 | B4: =SUMIF('Daily Ledger'!$D$2:$D$1827,A4,'Daily Ledger'!$I$2:$I$1827) -> 464 | C4: =SUMIF('Daily Ledger'!$D$2:$D$1827,A4,'Daily Ledger'!$J$2:$J$1827) -> 278400 | D4: =SUMIF('Daily Ledger'!$D$2:$D$1827,A4,'Daily Ledger'!$L$2:$L$1827) -> 363 | E4: =SUMIF('Daily Ledger'!$D$2:$D$1827,A4,'Daily Ledger'!$M$2:$M$1827) -> 108900 | F4: =SUMIF('Daily Ledger'!$D$2:$D$1827,A4,'Daily Ledger'!$N$2:$N$1827) -> 387300 | G4: =SUMIF('Daily Ledger'!$D$2:$D$1827,A4,'Daily Ledger'!$U$2:$U$1827) -> 260000 | H4: =SUMIF('Daily Ledger'!$D$2:$D$1827,A4,'Daily Ledger'!$V$2:$V$1827) -> 127300 | I4: =LOOKUP(2,1/('Daily Ledger'!$D$2:$D$1827=A4),'Daily Ledger'!$W$2:$W$1827) -> -4660700
A5: 4 | B5: =SUMIF('Daily Ledger'!$D$2:$D$1827,A5,'Daily Ledger'!$I$2:$I$1827) -> 476 | C5: =SUMIF('Daily Ledger'!$D$2:$D$1827,A5,'Daily Ledger'!$J$2:$J$1827) -> 285600 | D5: =SUMIF('Daily Ledger'!$D$2:$D$1827,A5,'Daily Ledger'!$L$2:$L$1827) -> 372 | E5: =SUMIF('Daily Ledger'!$D$2:$D$1827,A5,'Daily Ledger'!$M$2:$M$1827) -> 111600 | F5: =SUMIF('Daily Ledger'!$D$2:$D$1827,A5,'Daily Ledger'!$N$2:$N$1827) -> 397200 | G5: =SUMIF('Daily Ledger'!$D$2:$D$1827,A5,'Daily Ledger'!$U$2:$U$1827) -> 260000 | H5: =SUMIF('Daily Ledger'!$D$2:$D$1827,A5,'Daily Ledger'!$V$2:$V$1827) -> 137200 | I5: =LOOKUP(2,1/('Daily Ledger'!$D$2:$D$1827=A5),'Daily Ledger'!$W$2:$W$1827) -> -4523500
A6: 5 | B6: =SUMIF('Daily Ledger'!$D$2:$D$1827,A6,'Daily Ledger'!$I$2:$I$1827) -> 488 | C6: =SUMIF('Daily Ledger'!$D$2:$D$1827,A6,'Daily Ledger'!$J$2:$J$1827) -> 292800 | D6: =SUMIF('Daily Ledger'!$D$2:$D$1827,A6,'Daily Ledger'!$L$2:$L$1827) -> 374 | E6: =SUMIF('Daily Ledger'!$D$2:$D$1827,A6,'Daily Ledger'!$M$2:$M$1827) -> 112200 | F6: =SUMIF('Daily Ledger'!$D$2:$D$1827,A6,'Daily Ledger'!$N$2:$N$1827) -> 405000 | G6: =SUMIF('Daily Ledger'!$D$2:$D$1827,A6,'Daily Ledger'!$U$2:$U$1827) -> 260000 | H6: =SUMIF('Daily Ledger'!$D$2:$D$1827,A6,'Daily Ledger'!$V$2:$V$1827) -> 145000 | I6: =LOOKUP(2,1/('Daily Ledger'!$D$2:$D$1827=A6),'Daily Ledger'!$W$2:$W$1827) -> -4378500
A7: 6 | B7: =SUMIF('Daily Ledger'!$D$2:$D$1827,A7,'Daily Ledger'!$I$2:$I$1827) -> 484 | C7: =SUMIF('Daily Ledger'!$D$2:$D$1827,A7,'Daily Ledger'!$J$2:$J$1827) -> 290400 | D7: =SUMIF('Daily Ledger'!$D$2:$D$1827,A7,'Daily Ledger'!$L$2:$L$1827) -> 372 | E7: =SUMIF('Daily Ledger'!$D$2:$D$1827,A7,'Daily Ledger'!$M$2:$M$1827) -> 111600 | F7: =SUMIF('Daily Ledger'!$D$2:$D$1827,A7,'Daily Ledger'!$N$2:$N$1827) -> 402000 | G7: =SUMIF('Daily Ledger'!$D$2:$D$1827,A7,'Daily Ledger'!$U$2:$U$1827) -> 260000 | H7: =SUMIF('Daily Ledger'!$D$2:$D$1827,A7,'Daily Ledger'!$V$2:$V$1827) -> 142000 | I7: =LOOKUP(2,1/('Daily Ledger'!$D$2:$D$1827=A7),'Daily Ledger'!$W$2:$W$1827) -> -4236500
A8: 7 | B8: =SUMIF('Daily Ledger'!$D$2:$D$1827,A8,'Daily Ledger'!$I$2:$I$1827) -> 523 | C8: =SUMIF('Daily Ledger'!$D$2:$D$1827,A8,'Daily Ledger'!$J$2:$J$1827) -> 313800 | D8: =SUMIF('Daily Ledger'!$D$2:$D$1827,A8,'Daily Ledger'!$L$2:$L$1827) -> 386 | E8: =SUMIF('Daily Ledger'!$D$2:$D$1827,A8,'Daily Ledger'!$M$2:$M$1827) -> 115800 | F8: =SUMIF('Daily Ledger'!$D$2:$D$1827,A8,'Daily Ledger'!$N$2:$N$1827) -> 429600 | G8: =SUMIF('Daily Ledger'!$D$2:$D$1827,A8,'Daily Ledger'!$U$2:$U$1827) -> 260000 | H8: =SUMIF('Daily Ledger'!$D$2:$D$1827,A8,'Daily Ledger'!$V$2:$V$1827) -> 169600 | I8: =LOOKUP(2,1/('Daily Ledger'!$D$2:$D$1827=A8),'Daily Ledger'!$W$2:$W$1827) -> -4066900
A9: 8 | B9: =SUMIF('Daily Ledger'!$D$2:$D$1827,A9,'Daily Ledger'!$I$2:$I$1827) -> 511 | C9: =SUMIF('Daily Ledger'!$D$2:$D$1827,A9,'Daily Ledger'!$J$2:$J$1827) -> 306600 | D9: =SUMIF('Daily Ledger'!$D$2:$D$1827,A9,'Daily Ledger'!$L$2:$L$1827) -> 378 | E9: =SUMIF('Daily Ledger'!$D$2:$D$1827,A9,'Daily Ledger'!$M$2:$M$1827) -> 113400 | F9: =SUMIF('Daily Ledger'!$D$2:$D$1827,A9,'Daily Ledger'!$N$2:$N$1827) -> 420000 | G9: =SUMIF('Daily Ledger'!$D$2:$D$1827,A9,'Daily Ledger'!$U$2:$U$1827) -> 260000 | H9: =SUMIF('Daily Ledger'!$D$2:$D$1827,A9,'Daily Ledger'!$V$2:$V$1827) -> 160000 | I9: =LOOKUP(2,1/('Daily Ledger'!$D$2:$D$1827=A9),'Daily Ledger'!$W$2:$W$1827) -> -3906900
A10: 9 | B10: =SUMIF('Daily Ledger'!$D$2:$D$1827,A10,'Daily Ledger'!$I$2:$I$1827) -> 521 | C10: =SUMIF('Daily Ledger'!$D$2:$D$1827,A10,'Daily Ledger'!$J$2:$J$1827) -> 312600 | D10: =SUMIF('Daily Ledger'!$D$2:$D$1827,A10,'Daily Ledger'!$L$2:$L$1827) -> 380 | E10: =SUMIF('Daily Ledger'!$D$2:$D$1827,A10,'Daily Ledger'!$M$2:$M$1827) -> 114000 | F10: =SUMIF('Daily Ledger'!$D$2:$D$1827,A10,'Daily Ledger'!$N$2:$N$1827) -> 426600 | G10: =SUMIF('Daily Ledger'!$D$2:$D$1827,A10,'Daily Ledger'!$U$2:$U$1827) -> 260000 | H10: =SUMIF('Daily Ledger'!$D$2:$D$1827,A10,'Daily Ledger'!$V$2:$V$1827) -> 166600 | I10: =LOOKUP(2,1/('Daily Ledger'!$D$2:$D$1827=A10),'Daily Ledger'!$W$2:$W$1827) -> -3740300
A11: 10 | B11: =SUMIF('Daily Ledger'!$D$2:$D$1827,A11,'Daily Ledger'!$I$2:$I$1827) -> 548 | C11: =SUMIF('Daily Ledger'!$D$2:$D$1827,A11,'Daily Ledger'!$J$2:$J$1827) -> 328800 | D11: =SUMIF('Daily Ledger'!$D$2:$D$1827,A11,'Daily Ledger'!$L$2:$L$1827) -> 390 | E11: =SUMIF('Daily Ledger'!$D$2:$D$1827,A11,'Daily Ledger'!$M$2:$M$1827) -> 117000 | F11: =SUMIF('Daily Ledger'!$D$2:$D$1827,A11,'Daily Ledger'!$N$2:$N$1827) -> 445800 | G11: =SUMIF('Daily Ledger'!$D$2:$D$1827,A11,'Daily Ledger'!$U$2:$U$1827) -> 260000 | H11: =SUMIF('Daily Ledger'!$D$2:$D$1827,A11,'Daily Ledger'!$V$2:$V$1827) -> 185800 | I11: =LOOKUP(2,1/('Daily Ledger'!$D$2:$D$1827=A11),'Daily Ledger'!$W$2:$W$1827) -> -3554500
A12: 11 | B12: =SUMIF('Daily Ledger'!$D$2:$D$1827,A12,'Daily Ledger'!$I$2:$I$1827) -> 528 | C12: =SUMIF('Daily Ledger'!$D$2:$D$1827,A12,'Daily Ledger'!$J$2:$J$1827) -> 316800 | D12: =SUMIF('Daily Ledger'!$D$2:$D$1827,A12,'Daily Ledger'!$L$2:$L$1827) -> 396 | E12: =SUMIF('Daily Ledger'!$D$2:$D$1827,A12,'Daily Ledger'!$M$2:$M$1827) -> 118800 | F12: =SUMIF('Daily Ledger'!$D$2:$D$1827,A12,'Daily Ledger'!$N$2:$N$1827) -> 435600 | G12: =SUMIF('Daily Ledger'!$D$2:$D$1827,A12,'Daily Ledger'!$U$2:$U$1827) -> 260000 | H12: =SUMIF('Daily Ledger'!$D$2:$D$1827,A12,'Daily Ledger'!$V$2:$V$1827) -> 175600 | I12: =LOOKUP(2,1/('Daily Ledger'!$D$2:$D$1827=A12),'Daily Ledger'!$W$2:$W$1827) -> -3378900
A13: 12 | B13: =SUMIF('Daily Ledger'!$D$2:$D$1827,A13,'Daily Ledger'!$I$2:$I$1827) -> 574 | C13: =SUMIF('Daily Ledger'!$D$2:$D$1827,A13,'Daily Ledger'!$J$2:$J$1827) -> 344400 | D13: =SUMIF('Daily Ledger'!$D$2:$D$1827,A13,'Daily Ledger'!$L$2:$L$1827) -> 417 | E13: =SUMIF('Daily Ledger'!$D$2:$D$1827,A13,'Daily Ledger'!$M$2:$M$1827) -> 125100 | F13: =SUMIF('Daily Ledger'!$D$2:$D$1827,A13,'Daily Ledger'!$N$2:$N$1827) -> 469500 | G13: =SUMIF('Daily Ledger'!$D$2:$D$1827,A13,'Daily Ledger'!$U$2:$U$1827) -> 260000 | H13: =SUMIF('Daily Ledger'!$D$2:$D$1827,A13,'Daily Ledger'!$V$2:$V$1827) -> 209500 | I13: =LOOKUP(2,1/('Daily Ledger'!$D$2:$D$1827=A13),'Daily Ledger'!$W$2:$W$1827) -> -3169400
... A61: 60 | B61: =SUMIF('Daily Ledger'!$D$2:$D$1827,A61,'Daily Ledger'!$I$2:$I$1827) -> 716 | C61: =SUMIF('Daily Ledger'!$D$2:$D$1827,A61,'Daily Ledger'!$J$2:$J$1827) -> 429600 | D61: =SUMIF('Daily Ledger'!$D$2:$D$1827,A61,'Daily Ledger'!$L$2:$L$1827) -> 654 | E61: =SUMIF('Daily Ledger'!$D$2:$D$1827,A61,'Daily Ledger'!$M$2:$M$1827) -> 196200 | F61: =SUMIF('Daily Ledger'!$D$2:$D$1827,A61,'Daily Ledger'!$N$2:$N$1827) -> 625800 | G61: =SUMIF('Daily Ledger'!$D$2:$D$1827,A61,'Daily Ledger'!$U$2:$U$1827) -> 473400.42 | H61: =SUMIF('Daily Ledger'!$D$2:$D$1827,A61,'Daily Ledger'!$V$2:$V$1827) -> 152399.58 | I61: =LOOKUP(2,1/('Daily Ledger'!$D$2:$D$1827=A61),'Daily Ledger'!$W$2:$W$1827) -> 1254025.2

Sheet Annual Summary
A1: Sim Year | B1: MM Transactions | C1: Commission Revenue | D1: Airtime Transactions | E1: Airtime Revenue | F1: Total Revenue | G1: Total Costs | H1: Net Profit | I1: Cumulative Net Cash Position (year-end)
A2: 1 | B2: =SUMIF('Daily Ledger'!$C$2:$C$1827,A2,'Daily Ledger'!$I$2:$I$1827) -> 5996 | C2: =SUMIF('Daily Ledger'!$C$2:$C$1827,A2,'Daily Ledger'!$J$2:$J$1827) -> 3597600 | D2: =SUMIF('Daily Ledger'!$C$2:$C$1827,A2,'Daily Ledger'!$L$2:$L$1827) -> 4510 | E2: =SUMIF('Daily Ledger'!$C$2:$C$1827,A2,'Daily Ledger'!$M$2:$M$1827) -> 1353000 | F2: =SUMIF('Daily Ledger'!$C$2:$C$1827,A2,'Daily Ledger'!$N$2:$N$1827) -> 4950600 | G2: =SUMIF('Daily Ledger'!$C$2:$C$1827,A2,'Daily Ledger'!$U$2:$U$1827) -> 3120000 | H2: =SUMIF('Daily Ledger'!$C$2:$C$1827,A2,'Daily Ledger'!$V$2:$V$1827) -> 1830600 | I2: =LOOKUP(2,1/('Daily Ledger'!$C$2:$C$1827=A2),'Daily Ledger'!$W$2:$W$1827) -> -3169400
A3: 2 | B3: =SUMIF('Daily Ledger'!$C$2:$C$1827,A3,'Daily Ledger'!$I$2:$I$1827) -> 6951 | C3: =SUMIF('Daily Ledger'!$C$2:$C$1827,A3,'Daily Ledger'!$J$2:$J$1827) -> 4170600 | D3: =SUMIF('Daily Ledger'!$C$2:$C$1827,A3,'Daily Ledger'!$L$2:$L$1827) -> 5080 | E3: =SUMIF('Daily Ledger'!$C$2:$C$1827,A3,'Daily Ledger'!$M$2:$M$1827) -> 1524000 | F3: =SUMIF('Daily Ledger'!$C$2:$C$1827,A3,'Daily Ledger'!$N$2:$N$1827) -> 5694600 | G3: =SUMIF('Daily Ledger'!$C$2:$C$1827,A3,'Daily Ledger'!$U$2:$U$1827) -> 5017003.3 | H3: =SUMIF('Daily Ledger'!$C$2:$C$1827,A3,'Daily Ledger'!$V$2:$V$1827) -> 677596.7 | I3: =LOOKUP(2,1/('Daily Ledger'!$C$2:$C$1827=A3),'Daily Ledger'!$W$2:$W$1827) -> -2491803.3
A4: 3 | B4: =SUMIF('Daily Ledger'!$C$2:$C$1827,A4,'Daily Ledger'!$I$2:$I$1827) -> 7340 | C4: =SUMIF('Daily Ledger'!$C$2:$C$1827,A4,'Daily Ledger'!$J$2:$J$1827) -> 4404000 | D4: =SUMIF('Daily Ledger'!$C$2:$C$1827,A4,'Daily Ledger'!$L$2:$L$1827) -> 5723 | E4: =SUMIF('Daily Ledger'!$C$2:$C$1827,A4,'Daily Ledger'!$M$2:$M$1827) -> 1716900 | F4: =SUMIF('Daily Ledger'!$C$2:$C$1827,A4,'Daily Ledger'!$N$2:$N$1827) -> 6120900 | G4: =SUMIF('Daily Ledger'!$C$2:$C$1827,A4,'Daily Ledger'!$U$2:$U$1827) -> 5200625.5 | H4: =SUMIF('Daily Ledger'!$C$2:$C$1827,A4,'Daily Ledger'!$V$2:$V$1827) -> 920274.48 | I4: =LOOKUP(2,1/('Daily Ledger'!$C$2:$C$1827=A4),'Daily Ledger'!$W$2:$W$1827) -> -1571528.8
A5: 4 | B5: =SUMIF('Daily Ledger'!$C$2:$C$1827,A5,'Daily Ledger'!$I$2:$I$1827) -> 7828 | C5: =SUMIF('Daily Ledger'!$C$2:$C$1827,A5,'Daily Ledger'!$J$2:$J$1827) -> 4696800 | D5: =SUMIF('Daily Ledger'!$C$2:$C$1827,A5,'Daily Ledger'!$L$2:$L$1827) -> 6448 | E5: =SUMIF('Daily Ledger'!$C$2:$C$1827,A5,'Daily Ledger'!$M$2:$M$1827) -> 1934400 | F5: =SUMIF('Daily Ledger'!$C$2:$C$1827,A5,'Daily Ledger'!$N$2:$N$1827) -> 6631200 | G5: =SUMIF('Daily Ledger'!$C$2:$C$1827,A5,'Daily Ledger'!$U$2:$U$1827) -> 5390968.3 | H5: =SUMIF('Daily Ledger'!$C$2:$C$1827,A5,'Daily Ledger'!$V$2:$V$1827) -> 1240231.7 | I5: =LOOKUP(2,1/('Daily Ledger'!$C$2:$C$1827=A5),'Daily Ledger'!$W$2:$W$1827) -> -331297.13
A6: 5 | B6: =SUMIF('Daily Ledger'!$C$2:$C$1827,A6,'Daily Ledger'!$I$2:$I$1827) -> 8309 | C6: =SUMIF('Daily Ledger'!$C$2:$C$1827,A6,'Daily Ledger'!$J$2:$J$1827) -> 4985400 | D6: =SUMIF('Daily Ledger'!$C$2:$C$1827,A6,'Daily Ledger'!$L$2:$L$1827) -> 7294 | E6: =SUMIF('Daily Ledger'!$C$2:$C$1827,A6,'Daily Ledger'!$M$2:$M$1827) -> 2188200 | F6: =SUMIF('Daily Ledger'!$C$2:$C$1827,A6,'Daily Ledger'!$N$2:$N$1827) -> 7173600 | G6: =SUMIF('Daily Ledger'!$C$2:$C$1827,A6,'Daily Ledger'!$U$2:$U$1827) -> 5588277.6 | H6: =SUMIF('Daily Ledger'!$C$2:$C$1827,A6,'Daily Ledger'!$V$2:$V$1827) -> 1585322.4 | I6: =LOOKUP(2,1/('Daily Ledger'!$C$2:$C$1827=A6),'Daily Ledger'!$W$2:$W$1827) -> 1254025.2
A7: TOTAL / 5-YR | B7: =SUM(B2:B6) -> 36424 | C7: =SUM(C2:C6) -> 21854400 | D7: =SUM(D2:D6) -> 29055 | E7: =SUM(E2:E6) -> 8716500 | F7: =SUM(F2:F6) -> 30570900 | G7: =SUM(G2:G6) -> 24316875 | H7: =SUM(H2:H6) -> 6254025.2 | I7: ='Daily Ledger'!W1827 -> 1254025.2

Sheet Break-Even Analysis
A1: Break-Even Analysis — Daily Model
A3: Total Initial Investment (Starting Capital) | B3: =Assumptions!B15 -> 5000000
A4: Average Net Daily Profit (Year 1) | B4: =AVERAGE('Daily Ledger'!V2:V366) -> 5015.3425
A5: Simple break-even (days), constant Year-1 average profit | B5: =B3/B4 -> 996.94089
A7: Break-even Day # (from cumulative cash position, dynamic model) | B7: =IFERROR(INDEX('Daily Ledger'!A2:A1827,MATCH(TRUE(),INDEX('Daily Ledger'!W2:W1827>=0,0),0)),"Not reached within simulation period") -> 1550
A8: Break-even Date | B8: =IFERROR(INDEX('Daily Ledger'!B2:B1827,MATCH(B7,'Daily Ledger'!A2:A1827,0)),"n/a") -> 47572
A9: Break-even Sim Year | B9: =ROUNDUP(B7/365,0) -> 5
A11: Interpretation
A12: The break-even point is the exact day on which the Cumulative Net Cash Position (Daily Ledger, column W) crosses from negative to zero/positive — the accumulated daily profit has fully repaid the starting capital in row 3. Every shilling of net profit from that day forward is clean profit for the investor.
