Workbook

Sheet Assumptions
A1: Mobile Money & Airtime Kiosk — 5-Year Model Assumptions
A2: All monetary values in Ugandan Shillings (UGX). Blue cells are editable inputs.
A4: 1. INITIAL (STARTUP) CAPITAL
A5: Float capital (mobile money agent line) | B5: 3000000 | C5: Source: user-provided business scenario
A6: Initial airtime / data bundle stock | B6: 500000
A7: Kiosk setup (structure, signage, stool, umbrella) | B7: 800000
A8: Rent deposit (advance) | B8: 300000
A9: Equipment (phone, register book, solar charger, POS) | B9: 400000
A10: TOTAL INITIAL INVESTMENT (Starting Capital) | B10: =SUM(B5:B9) -> 5000000
A12: 2. MOBILE MONEY REVENUE DRIVERS
A13: Starting mobile money transactions / month | B13: 500 | C13: Forecast given in the scenario
A14: Monthly transaction growth rate — Year 1 | B14: 0.02 | C14: Student traffic builds up as the kiosk gets known
A15: Monthly transaction growth rate — Year 2 onward | B15: 0.005 | C15: Growth slows once the market matures
A16: Average commission earned per transaction (UGX) | B16: 600 | C16: Blended tier commission from telecom/MM provider
A18: 3. AIRTIME / DATA BUNDLE REVENUE DRIVERS
A19: Starting airtime/data transactions / month | B19: 400
A20: Monthly airtime transaction growth rate | B20: 0.01
A21: Average markup profit per airtime/data sale (UGX) | B21: 300 | C21: Difference between buying and selling price
A23: 4. MONTHLY OPERATING COSTS
A24: Kiosk rent | B24: 150000
A25: Transport for float top-up | B25: 40000
A26: Agent line / mobile money service charges | B26: 30000
A27: Utilities (phone charging, lighting) | B27: 20000
A28: Attendant wage (starts Month 13, once volumes justify hiring help) | B28: 150000
A29: Miscellaneous / contingency | B29: 20000
A31: 5. OTHER
A32: Monthly discount/inflation adjustment on costs | B32: 0.003 | C32: Small monthly cost inflation applied from Month 13

Sheet Monthly Model
A1: Month # | B1: Year | C1: Calendar Month | D1: MM Transactions | E1: Commission Revenue | F1: Airtime Transactions | G1: Airtime Revenue | H1: Total Revenue | I1: Rent | J1: Transport | K1: Agent Charges | L1: Utilities | M1: Wage | N1: Misc | O1: Total Costs | P1: Net Profit (Monthly) | Q1: Cumulative Net Cash Position | R1: Breakeven Reached?
A2: 1 | B2: =ROUNDUP(A2/12,0) -> 1 | C2: ="Month "&A2 -> Month 1 | D2: =Assumptions!B13 -> 500 | E2: =D2*Assumptions!B16 -> 300000 | F2: =Assumptions!B19 -> 400 | G2: =F2*Assumptions!B21 -> 120000 | H2: =E2+G2 -> 420000 | I2: =Assumptions!B24*IF(A2>=13,(1+Assumptions!B32)^(A2-12),1) -> 150000 | J2: =Assumptions!B25*IF(A2>=13,(1+Assumptions!B32)^(A2-12),1) -> 40000 | K2: =Assumptions!B26*IF(A2>=13,(1+Assumptions!B32)^(A2-12),1) -> 30000 | L2: =Assumptions!B27*IF(A2>=13,(1+Assumptions!B32)^(A2-12),1) -> 20000 | M2: =IF(A2>=13,Assumptions!B28*IF(A2>=13,(1+Assumptions!B32)^(A2-12),1),0) -> 0 | N2: =Assumptions!B29*IF(A2>=13,(1+Assumptions!B32)^(A2-12),1) -> 20000 | O2: =SUM(I2:N2) -> 260000 | P2: =H2-O2 -> 160000 | Q2: =-Assumptions!B10+P2 -> -4840000 | R2: =IF(Q2>=0,"YES","No") -> No
A3: 2 | B3: =ROUNDUP(A3/12,0) -> 1 | C3: ="Month "&A3 -> Month 2 | D3: =D2*(1+IF(B3=1,Assumptions!B14,Assumptions!B15)) -> 510 | E3: =D3*Assumptions!B16 -> 306000 | F3: =F2*(1+Assumptions!B20) -> 404 | G3: =F3*Assumptions!B21 -> 121200 | H3: =E3+G3 -> 427200 | I3: =Assumptions!B24*IF(A3>=13,(1+Assumptions!B32)^(A3-12),1) -> 150000 | J3: =Assumptions!B25*IF(A3>=13,(1+Assumptions!B32)^(A3-12),1) -> 40000 | K3: =Assumptions!B26*IF(A3>=13,(1+Assumptions!B32)^(A3-12),1) -> 30000 | L3: =Assumptions!B27*IF(A3>=13,(1+Assumptions!B32)^(A3-12),1) -> 20000 | M3: =IF(A3>=13,Assumptions!B28*IF(A3>=13,(1+Assumptions!B32)^(A3-12),1),0) -> 0 | N3: =Assumptions!B29*IF(A3>=13,(1+Assumptions!B32)^(A3-12),1) -> 20000 | O3: =SUM(I3:N3) -> 260000 | P3: =H3-O3 -> 167200 | Q3: =Q2+P3 -> -4672800 | R3: =IF(Q3>=0,"YES","No") -> No
A4: 3 | B4: =ROUNDUP(A4/12,0) -> 1 | C4: ="Month "&A4 -> Month 3 | D4: =D3*(1+IF(B4=1,Assumptions!B14,Assumptions!B15)) -> 520.2 | E4: =D4*Assumptions!B16 -> 312120 | F4: =F3*(1+Assumptions!B20) -> 408.04 | G4: =F4*Assumptions!B21 -> 122412 | H4: =E4+G4 -> 434532 | I4: =Assumptions!B24*IF(A4>=13,(1+Assumptions!B32)^(A4-12),1) -> 150000 | J4: =Assumptions!B25*IF(A4>=13,(1+Assumptions!B32)^(A4-12),1) -> 40000 | K4: =Assumptions!B26*IF(A4>=13,(1+Assumptions!B32)^(A4-12),1) -> 30000 | L4: =Assumptions!B27*IF(A4>=13,(1+Assumptions!B32)^(A4-12),1) -> 20000 | M4: =IF(A4>=13,Assumptions!B28*IF(A4>=13,(1+Assumptions!B32)^(A4-12),1),0) -> 0 | N4: =Assumptions!B29*IF(A4>=13,(1+Assumptions!B32)^(A4-12),1) -> 20000 | O4: =SUM(I4:N4) -> 260000 | P4: =H4-O4 -> 174532 | Q4: =Q3+P4 -> -4498268 | R4: =IF(Q4>=0,"YES","No") -> No
A5: 4 | B5: =ROUNDUP(A5/12,0) -> 1 | C5: ="Month "&A5 -> Month 4 | D5: =D4*(1+IF(B5=1,Assumptions!B14,Assumptions!B15)) -> 530.604 | E5: =D5*Assumptions!B16 -> 318362.4 | F5: =F4*(1+Assumptions!B20) -> 412.1204 | G5: =F5*Assumptions!B21 -> 123636.12 | H5: =E5+G5 -> 441998.52 | I5: =Assumptions!B24*IF(A5>=13,(1+Assumptions!B32)^(A5-12),1) -> 150000 | J5: =Assumptions!B25*IF(A5>=13,(1+Assumptions!B32)^(A5-12),1) -> 40000 | K5: =Assumptions!B26*IF(A5>=13,(1+Assumptions!B32)^(A5-12),1) -> 30000 | L5: =Assumptions!B27*IF(A5>=13,(1+Assumptions!B32)^(A5-12),1) -> 20000 | M5: =IF(A5>=13,Assumptions!B28*IF(A5>=13,(1+Assumptions!B32)^(A5-12),1),0) -> 0 | N5: =Assumptions!B29*IF(A5>=13,(1+Assumptions!B32)^(A5-12),1) -> 20000 | O5: =SUM(I5:N5) -> 260000 | P5: =H5-O5 -> 181998.52 | Q5: =Q4+P5 -> -4316269.5 | R5: =IF(Q5>=0,"YES","No") -> No
A6: 5 | B6: =ROUNDUP(A6/12,0) -> 1 | C6: ="Month "&A6 -> Month 5 | D6: =D5*(1+IF(B6=1,Assumptions!B14,Assumptions!B15)) -> 541.21608 | E6: =D6*Assumptions!B16 -> 324729.65 | F6: =F5*(1+Assumptions!B20) -> 416.2416 | G6: =F6*Assumptions!B21 -> 124872.48 | H6: =E6+G6 -> 449602.13 | I6: =Assumptions!B24*IF(A6>=13,(1+Assumptions!B32)^(A6-12),1) -> 150000 | J6: =Assumptions!B25*IF(A6>=13,(1+Assumptions!B32)^(A6-12),1) -> 40000 | K6: =Assumptions!B26*IF(A6>=13,(1+Assumptions!B32)^(A6-12),1) -> 30000 | L6: =Assumptions!B27*IF(A6>=13,(1+Assumptions!B32)^(A6-12),1) -> 20000 | M6: =IF(A6>=13,Assumptions!B28*IF(A6>=13,(1+Assumptions!B32)^(A6-12),1),0) -> 0 | N6: =Assumptions!B29*IF(A6>=13,(1+Assumptions!B32)^(A6-12),1) -> 20000 | O6: =SUM(I6:N6) -> 260000 | P6: =H6-O6 -> 189602.13 | Q6: =Q5+P6 -> -4126667.4 | R6: =IF(Q6>=0,"YES","No") -> No
A7: 6 | B7: =ROUNDUP(A7/12,0) -> 1 | C7: ="Month "&A7 -> Month 6 | D7: =D6*(1+IF(B7=1,Assumptions!B14,Assumptions!B15)) -> 552.0404 | E7: =D7*Assumptions!B16 -> 331224.24 | F7: =F6*(1+Assumptions!B20) -> 420.40402 | G7: =F7*Assumptions!B21 -> 126121.21 | H7: =E7+G7 -> 457345.45 | I7: =Assumptions!B24*IF(A7>=13,(1+Assumptions!B32)^(A7-12),1) -> 150000 | J7: =Assumptions!B25*IF(A7>=13,(1+Assumptions!B32)^(A7-12),1) -> 40000 | K7: =Assumptions!B26*IF(A7>=13,(1+Assumptions!B32)^(A7-12),1) -> 30000 | L7: =Assumptions!B27*IF(A7>=13,(1+Assumptions!B32)^(A7-12),1) -> 20000 | M7: =IF(A7>=13,Assumptions!B28*IF(A7>=13,(1+Assumptions!B32)^(A7-12),1),0) -> 0 | N7: =Assumptions!B29*IF(A7>=13,(1+Assumptions!B32)^(A7-12),1) -> 20000 | O7: =SUM(I7:N7) -> 260000 | P7: =H7-O7 -> 197345.45 | Q7: =Q6+P7 -> -3929321.9 | R7: =IF(Q7>=0,"YES","No") -> No
A8: 7 | B8: =ROUNDUP(A8/12,0) -> 1 | C8: ="Month "&A8 -> Month 7 | D8: =D7*(1+IF(B8=1,Assumptions!B14,Assumptions!B15)) -> 563.08121 | E8: =D8*Assumptions!B16 -> 337848.73 | F8: =F7*(1+Assumptions!B20) -> 424.60806 | G8: =F8*Assumptions!B21 -> 127382.42 | H8: =E8+G8 -> 465231.14 | I8: =Assumptions!B24*IF(A8>=13,(1+Assumptions!B32)^(A8-12),1) -> 150000 | J8: =Assumptions!B25*IF(A8>=13,(1+Assumptions!B32)^(A8-12),1) -> 40000 | K8: =Assumptions!B26*IF(A8>=13,(1+Assumptions!B32)^(A8-12),1) -> 30000 | L8: =Assumptions!B27*IF(A8>=13,(1+Assumptions!B32)^(A8-12),1) -> 20000 | M8: =IF(A8>=13,Assumptions!B28*IF(A8>=13,(1+Assumptions!B32)^(A8-12),1),0) -> 0 | N8: =Assumptions!B29*IF(A8>=13,(1+Assumptions!B32)^(A8-12),1) -> 20000 | O8: =SUM(I8:N8) -> 260000 | P8: =H8-O8 -> 205231.14 | Q8: =Q7+P8 -> -3724090.8 | R8: =IF(Q8>=0,"YES","No") -> No
A9: 8 | B9: =ROUNDUP(A9/12,0) -> 1 | C9: ="Month "&A9 -> Month 8 | D9: =D8*(1+IF(B9=1,Assumptions!B14,Assumptions!B15)) -> 574.34283 | E9: =D9*Assumptions!B16 -> 344605.7 | F9: =F8*(1+Assumptions!B20) -> 428.85414 | G9: =F9*Assumptions!B21 -> 128656.24 | H9: =E9+G9 -> 473261.94 | I9: =Assumptions!B24*IF(A9>=13,(1+Assumptions!B32)^(A9-12),1) -> 150000 | J9: =Assumptions!B25*IF(A9>=13,(1+Assumptions!B32)^(A9-12),1) -> 40000 | K9: =Assumptions!B26*IF(A9>=13,(1+Assumptions!B32)^(A9-12),1) -> 30000 | L9: =Assumptions!B27*IF(A9>=13,(1+Assumptions!B32)^(A9-12),1) -> 20000 | M9: =IF(A9>=13,Assumptions!B28*IF(A9>=13,(1+Assumptions!B32)^(A9-12),1),0) -> 0 | N9: =Assumptions!B29*IF(A9>=13,(1+Assumptions!B32)^(A9-12),1) -> 20000 | O9: =SUM(I9:N9) -> 260000 | P9: =H9-O9 -> 213261.94 | Q9: =Q8+P9 -> -3510828.8 | R9: =IF(Q9>=0,"YES","No") -> No
A10: 9 | B10: =ROUNDUP(A10/12,0) -> 1 | C10: ="Month "&A10 -> Month 9 | D10: =D9*(1+IF(B10=1,Assumptions!B14,Assumptions!B15)) -> 585.82969 | E10: =D10*Assumptions!B16 -> 351497.81 | F10: =F9*(1+Assumptions!B20) -> 433.14268 | G10: =F10*Assumptions!B21 -> 129942.8 | H10: =E10+G10 -> 481440.62 | I10: =Assumptions!B24*IF(A10>=13,(1+Assumptions!B32)^(A10-12),1) -> 150000 | J10: =Assumptions!B25*IF(A10>=13,(1+Assumptions!B32)^(A10-12),1) -> 40000 | K10: =Assumptions!B26*IF(A10>=13,(1+Assumptions!B32)^(A10-12),1) -> 30000 | L10: =Assumptions!B27*IF(A10>=13,(1+Assumptions!B32)^(A10-12),1) -> 20000 | M10: =IF(A10>=13,Assumptions!B28*IF(A10>=13,(1+Assumptions!B32)^(A10-12),1),0) -> 0 | N10: =Assumptions!B29*IF(A10>=13,(1+Assumptions!B32)^(A10-12),1) -> 20000 | O10: =SUM(I10:N10) -> 260000 | P10: =H10-O10 -> 221440.62 | Q10: =Q9+P10 -> -3289388.2 | R10: =IF(Q10>=0,"YES","No") -> No
A11: 10 | B11: =ROUNDUP(A11/12,0) -> 1 | C11: ="Month "&A11 -> Month 10 | D11: =D10*(1+IF(B11=1,Assumptions!B14,Assumptions!B15)) -> 597.54628 | E11: =D11*Assumptions!B16 -> 358527.77 | F11: =F10*(1+Assumptions!B20) -> 437.47411 | G11: =F11*Assumptions!B21 -> 131242.23 | H11: =E11+G11 -> 489770 | I11: =Assumptions!B24*IF(A11>=13,(1+Assumptions!B32)^(A11-12),1) -> 150000 | J11: =Assumptions!B25*IF(A11>=13,(1+Assumptions!B32)^(A11-12),1) -> 40000 | K11: =Assumptions!B26*IF(A11>=13,(1+Assumptions!B32)^(A11-12),1) -> 30000 | L11: =Assumptions!B27*IF(A11>=13,(1+Assumptions!B32)^(A11-12),1) -> 20000 | M11: =IF(A11>=13,Assumptions!B28*IF(A11>=13,(1+Assumptions!B32)^(A11-12),1),0) -> 0 | N11: =Assumptions!B29*IF(A11>=13,(1+Assumptions!B32)^(A11-12),1) -> 20000 | O11: =SUM(I11:N11) -> 260000 | P11: =H11-O11 -> 229770 | Q11: =Q10+P11 -> -3059618.2 | R11: =IF(Q11>=0,"YES","No") -> No
A12: 11 | B12: =ROUNDUP(A12/12,0) -> 1 | C12: ="Month "&A12 -> Month 11 | D12: =D11*(1+IF(B12=1,Assumptions!B14,Assumptions!B15)) -> 609.49721 | E12: =D12*Assumptions!B16 -> 365698.33 | F12: =F11*(1+Assumptions!B20) -> 441.84885 | G12: =F12*Assumptions!B21 -> 132554.66 | H12: =E12+G12 -> 498252.98 | I12: =Assumptions!B24*IF(A12>=13,(1+Assumptions!B32)^(A12-12),1) -> 150000 | J12: =Assumptions!B25*IF(A12>=13,(1+Assumptions!B32)^(A12-12),1) -> 40000 | K12: =Assumptions!B26*IF(A12>=13,(1+Assumptions!B32)^(A12-12),1) -> 30000 | L12: =Assumptions!B27*IF(A12>=13,(1+Assumptions!B32)^(A12-12),1) -> 20000 | M12: =IF(A12>=13,Assumptions!B28*IF(A12>=13,(1+Assumptions!B32)^(A12-12),1),0) -> 0 | N12: =Assumptions!B29*IF(A12>=13,(1+Assumptions!B32)^(A12-12),1) -> 20000 | O12: =SUM(I12:N12) -> 260000 | P12: =H12-O12 -> 238252.98 | Q12: =Q11+P12 -> -2821365.2 | R12: =IF(Q12>=0,"YES","No") -> No
A13: 12 | B13: =ROUNDUP(A13/12,0) -> 1 | C13: ="Month "&A13 -> Month 12 | D13: =D12*(1+IF(B13=1,Assumptions!B14,Assumptions!B15)) -> 621.68715 | E13: =D13*Assumptions!B16 -> 373012.29 | F13: =F12*(1+Assumptions!B20) -> 446.26734 | G13: =F13*Assumptions!B21 -> 133880.2 | H13: =E13+G13 -> 506892.49 | I13: =Assumptions!B24*IF(A13>=13,(1+Assumptions!B32)^(A13-12),1) -> 150000 | J13: =Assumptions!B25*IF(A13>=13,(1+Assumptions!B32)^(A13-12),1) -> 40000 | K13: =Assumptions!B26*IF(A13>=13,(1+Assumptions!B32)^(A13-12),1) -> 30000 | L13: =Assumptions!B27*IF(A13>=13,(1+Assumptions!B32)^(A13-12),1) -> 20000 | M13: =IF(A13>=13,Assumptions!B28*IF(A13>=13,(1+Assumptions!B32)^(A13-12),1),0) -> 0 | N13: =Assumptions!B29*IF(A13>=13,(1+Assumptions!B32)^(A13-12),1) -> 20000 | O13: =SUM(I13:N13) -> 260000 | P13: =H13-O13 -> 246892.49 | Q13: =Q12+P13 -> -2574472.7 | R13: =IF(Q13>=0,"YES","No") -> No
A14: 13 | B14: =ROUNDUP(A14/12,0) -> 2 | C14: ="Month "&A14 -> Month 13 | D14: =D13*(1+IF(B14=1,Assumptions!B14,Assumptions!B15)) -> 624.79559 | E14: =D14*Assumptions!B16 -> 374877.35 | F14: =F13*(1+Assumptions!B20) -> 450.73001 | G14: =F14*Assumptions!B21 -> 135219 | H14: =E14+G14 -> 510096.36 | I14: =Assumptions!B24*IF(A14>=13,(1+Assumptions!B32)^(A14-12),1) -> 150450 | J14: =Assumptions!B25*IF(A14>=13,(1+Assumptions!B32)^(A14-12),1) -> 40120 | K14: =Assumptions!B26*IF(A14>=13,(1+Assumptions!B32)^(A14-12),1) -> 30090 | L14: =Assumptions!B27*IF(A14>=13,(1+Assumptions!B32)^(A14-12),1) -> 20060 | M14: =IF(A14>=13,Assumptions!B28*IF(A14>=13,(1+Assumptions!B32)^(A14-12),1),0) -> 150450 | N14: =Assumptions!B29*IF(A14>=13,(1+Assumptions!B32)^(A14-12),1) -> 20060 | O14: =SUM(I14:N14) -> 411230 | P14: =H14-O14 -> 98866.358 | Q14: =Q13+P14 -> -2475606.4 | R14: =IF(Q14>=0,"YES","No") -> No
A15: 14 | B15: =ROUNDUP(A15/12,0) -> 2 | C15: ="Month "&A15 -> Month 14 | D15: =D14*(1+IF(B15=1,Assumptions!B14,Assumptions!B15)) -> 627.91957 | E15: =D15*Assumptions!B16 -> 376751.74 | F15: =F14*(1+Assumptions!B20) -> 455.23731 | G15: =F15*Assumptions!B21 -> 136571.19 | H15: =E15+G15 -> 513322.93 | I15: =Assumptions!B24*IF(A15>=13,(1+Assumptions!B32)^(A15-12),1) -> 150901.35 | J15: =Assumptions!B25*IF(A15>=13,(1+Assumptions!B32)^(A15-12),1) -> 40240.36 | K15: =Assumptions!B26*IF(A15>=13,(1+Assumptions!B32)^(A15-12),1) -> 30180.27 | L15: =Assumptions!B27*IF(A15>=13,(1+Assumptions!B32)^(A15-12),1) -> 20120.18 | M15: =IF(A15>=13,Assumptions!B28*IF(A15>=13,(1+Assumptions!B32)^(A15-12),1),0) -> 150901.35 | N15: =Assumptions!B29*IF(A15>=13,(1+Assumptions!B32)^(A15-12),1) -> 20120.18 | O15: =SUM(I15:N15) -> 412463.69 | P15: =H15-O15 -> 100859.24 | Q15: =Q14+P15 -> -2374747.1 | R15: =IF(Q15>=0,"YES","No") -> No
A16: 15 | B16: =ROUNDUP(A16/12,0) -> 2 | C16: ="Month "&A16 -> Month 15 | D16: =D15*(1+IF(B16=1,Assumptions!B14,Assumptions!B15)) -> 631.05917 | E16: =D16*Assumptions!B16 -> 378635.5 | F16: =F15*(1+Assumptions!B20) -> 459.78969 | G16: =F16*Assumptions!B21 -> 137936.91 | H16: =E16+G16 -> 516572.41 | I16: =Assumptions!B24*IF(A16>=13,(1+Assumptions!B32)^(A16-12),1) -> 151354.05 | J16: =Assumptions!B25*IF(A16>=13,(1+Assumptions!B32)^(A16-12),1) -> 40361.081 | K16: =Assumptions!B26*IF(A16>=13,(1+Assumptions!B32)^(A16-12),1) -> 30270.811 | L16: =Assumptions!B27*IF(A16>=13,(1+Assumptions!B32)^(A16-12),1) -> 20180.541 | M16: =IF(A16>=13,Assumptions!B28*IF(A16>=13,(1+Assumptions!B32)^(A16-12),1),0) -> 151354.05 | N16: =Assumptions!B29*IF(A16>=13,(1+Assumptions!B32)^(A16-12),1) -> 20180.541 | O16: =SUM(I16:N16) -> 413701.08 | P16: =H16-O16 -> 102871.32 | Q16: =Q15+P16 -> -2271875.8 | R16: =IF(Q16>=0,"YES","No") -> No
A17: 16 | B17: =ROUNDUP(A17/12,0) -> 2 | C17: ="Month "&A17 -> Month 16 | D17: =D16*(1+IF(B17=1,Assumptions!B14,Assumptions!B15)) -> 634.21446 | E17: =D17*Assumptions!B16 -> 380528.68 | F17: =F16*(1+Assumptions!B20) -> 464.38758 | G17: =F17*Assumptions!B21 -> 139316.27 | H17: =E17+G17 -> 519844.95 | I17: =Assumptions!B24*IF(A17>=13,(1+Assumptions!B32)^(A17-12),1) -> 151808.12 | J17: =Assumptions!B25*IF(A17>=13,(1+Assumptions!B32)^(A17-12),1) -> 40482.164 | K17: =Assumptions!B26*IF(A17>=13,(1+Assumptions!B32)^(A17-12),1) -> 30361.623 | L17: =Assumptions!B27*IF(A17>=13,(1+Assumptions!B32)^(A17-12),1) -> 20241.082 | M17: =IF(A17>=13,Assumptions!B28*IF(A17>=13,(1+Assumptions!B32)^(A17-12),1),0) -> 151808.12 | N17: =Assumptions!B29*IF(A17>=13,(1+Assumptions!B32)^(A17-12),1) -> 20241.082 | O17: =SUM(I17:N17) -> 414942.18 | P17: =H17-O17 -> 104902.77 | Q17: =Q16+P17 -> -2166973 | R17: =IF(Q17>=0,"YES","No") -> No
A18: 17 | B18: =ROUNDUP(A18/12,0) -> 2 | C18: ="Month "&A18 -> Month 17 | D18: =D17*(1+IF(B18=1,Assumptions!B14,Assumptions!B15)) -> 637.38553 | E18: =D18*Assumptions!B16 -> 382431.32 | F18: =F17*(1+Assumptions!B20) -> 469.03146 | G18: =F18*Assumptions!B21 -> 140709.44 | H18: =E18+G18 -> 523140.76 | I18: =Assumptions!B24*IF(A18>=13,(1+Assumptions!B32)^(A18-12),1) -> 152263.54 | J18: =Assumptions!B25*IF(A18>=13,(1+Assumptions!B32)^(A18-12),1) -> 40603.611 | K18: =Assumptions!B26*IF(A18>=13,(1+Assumptions!B32)^(A18-12),1) -> 30452.708 | L18: =Assumptions!B27*IF(A18>=13,(1+Assumptions!B32)^(A18-12),1) -> 20301.805 | M18: =IF(A18>=13,Assumptions!B28*IF(A18>=13,(1+Assumptions!B32)^(A18-12),1),0) -> 152263.54 | N18: =Assumptions!B29*IF(A18>=13,(1+Assumptions!B32)^(A18-12),1) -> 20301.805 | O18: =SUM(I18:N18) -> 416187.01 | P18: =H18-O18 -> 106953.75 | Q18: =Q17+P18 -> -2060019.3 | R18: =IF(Q18>=0,"YES","No") -> No
A19: 18 | B19: =ROUNDUP(A19/12,0) -> 2 | C19: ="Month "&A19 -> Month 18 | D19: =D18*(1+IF(B19=1,Assumptions!B14,Assumptions!B15)) -> 640.57246 | E19: =D19*Assumptions!B16 -> 384343.48 | F19: =F18*(1+Assumptions!B20) -> 473.72177 | G19: =F19*Assumptions!B21 -> 142116.53 | H19: =E19+G19 -> 526460.01 | I19: =Assumptions!B24*IF(A19>=13,(1+Assumptions!B32)^(A19-12),1) -> 152720.33 | J19: =Assumptions!B25*IF(A19>=13,(1+Assumptions!B32)^(A19-12),1) -> 40725.422 | K19: =Assumptions!B26*IF(A19>=13,(1+Assumptions!B32)^(A19-12),1) -> 30544.066 | L19: =Assumptions!B27*IF(A19>=13,(1+Assumptions!B32)^(A19-12),1) -> 20362.711 | M19: =IF(A19>=13,Assumptions!B28*IF(A19>=13,(1+Assumptions!B32)^(A19-12),1),0) -> 152720.33 | N19: =Assumptions!B29*IF(A19>=13,(1+Assumptions!B32)^(A19-12),1) -> 20362.711 | O19: =SUM(I19:N19) -> 417435.57 | P19: =H19-O19 -> 109024.44 | Q19: =Q18+P19 -> -1950994.8 | R19: =IF(Q19>=0,"YES","No") -> No
A20: 19 | B20: =ROUNDUP(A20/12,0) -> 2 | C20: ="Month "&A20 -> Month 19 | D20: =D19*(1+IF(B20=1,Assumptions!B14,Assumptions!B15)) -> 643.77532 | E20: =D20*Assumptions!B16 -> 386265.19 | F20: =F19*(1+Assumptions!B20) -> 478.45899 | G20: =F20*Assumptions!B21 -> 143537.7 | H20: =E20+G20 -> 529802.89 | I20: =Assumptions!B24*IF(A20>=13,(1+Assumptions!B32)^(A20-12),1) -> 153178.49 | J20: =Assumptions!B25*IF(A20>=13,(1+Assumptions!B32)^(A20-12),1) -> 40847.598 | K20: =Assumptions!B26*IF(A20>=13,(1+Assumptions!B32)^(A20-12),1) -> 30635.698 | L20: =Assumptions!B27*IF(A20>=13,(1+Assumptions!B32)^(A20-12),1) -> 20423.799 | M20: =IF(A20>=13,Assumptions!B28*IF(A20>=13,(1+Assumptions!B32)^(A20-12),1),0) -> 153178.49 | N20: =Assumptions!B29*IF(A20>=13,(1+Assumptions!B32)^(A20-12),1) -> 20423.799 | O20: =SUM(I20:N20) -> 418687.88 | P20: =H20-O20 -> 111115.01 | Q20: =Q19+P20 -> -1839879.8 | R20: =IF(Q20>=0,"YES","No") -> No
A21: 20 | B21: =ROUNDUP(A21/12,0) -> 2 | C21: ="Month "&A21 -> Month 20 | D21: =D20*(1+IF(B21=1,Assumptions!B14,Assumptions!B15)) -> 646.9942 | E21: =D21*Assumptions!B16 -> 388196.52 | F21: =F20*(1+Assumptions!B20) -> 483.24358 | G21: =F21*Assumptions!B21 -> 144973.07 | H21: =E21+G21 -> 533169.59 | I21: =Assumptions!B24*IF(A21>=13,(1+Assumptions!B32)^(A21-12),1) -> 153638.03 | J21: =Assumptions!B25*IF(A21>=13,(1+Assumptions!B32)^(A21-12),1) -> 40970.141 | K21: =Assumptions!B26*IF(A21>=13,(1+Assumptions!B32)^(A21-12),1) -> 30727.606 | L21: =Assumptions!B27*IF(A21>=13,(1+Assumptions!B32)^(A21-12),1) -> 20485.07 | M21: =IF(A21>=13,Assumptions!B28*IF(A21>=13,(1+Assumptions!B32)^(A21-12),1),0) -> 153638.03 | N21: =Assumptions!B29*IF(A21>=13,(1+Assumptions!B32)^(A21-12),1) -> 20485.07 | O21: =SUM(I21:N21) -> 419943.94 | P21: =H21-O21 -> 113225.65 | Q21: =Q20+P21 -> -1726654.2 | R21: =IF(Q21>=0,"YES","No") -> No
A22: 21 | B22: =ROUNDUP(A22/12,0) -> 2 | C22: ="Month "&A22 -> Month 21 | D22: =D21*(1+IF(B22=1,Assumptions!B14,Assumptions!B15)) -> 650.22917 | E22: =D22*Assumptions!B16 -> 390137.5 | F22: =F21*(1+Assumptions!B20) -> 488.07602 | G22: =F22*Assumptions!B21 -> 146422.8 | H22: =E22+G22 -> 536560.31 | I22: =Assumptions!B24*IF(A22>=13,(1+Assumptions!B32)^(A22-12),1) -> 154098.94 | J22: =Assumptions!B25*IF(A22>=13,(1+Assumptions!B32)^(A22-12),1) -> 41093.051 | K22: =Assumptions!B26*IF(A22>=13,(1+Assumptions!B32)^(A22-12),1) -> 30819.788 | L22: =Assumptions!B27*IF(A22>=13,(1+Assumptions!B32)^(A22-12),1) -> 20546.526 | M22: =IF(A22>=13,Assumptions!B28*IF(A22>=13,(1+Assumptions!B32)^(A22-12),1),0) -> 154098.94 | N22: =Assumptions!B29*IF(A22>=13,(1+Assumptions!B32)^(A22-12),1) -> 20546.526 | O22: =SUM(I22:N22) -> 421203.77 | P22: =H22-O22 -> 115356.53 | Q22: =Q21+P22 -> -1611297.6 | R22: =IF(Q22>=0,"YES","No") -> No
A23: 22 | B23: =ROUNDUP(A23/12,0) -> 2 | C23: ="Month "&A23 -> Month 22 | D23: =D22*(1+IF(B23=1,Assumptions!B14,Assumptions!B15)) -> 653.48032 | E23: =D23*Assumptions!B16 -> 392088.19 | F23: =F22*(1+Assumptions!B20) -> 492.95678 | G23: =F23*Assumptions!B21 -> 147887.03 | H23: =E23+G23 -> 539975.22 | I23: =Assumptions!B24*IF(A23>=13,(1+Assumptions!B32)^(A23-12),1) -> 154561.24 | J23: =Assumptions!B25*IF(A23>=13,(1+Assumptions!B32)^(A23-12),1) -> 41216.33 | K23: =Assumptions!B26*IF(A23>=13,(1+Assumptions!B32)^(A23-12),1) -> 30912.248 | L23: =Assumptions!B27*IF(A23>=13,(1+Assumptions!B32)^(A23-12),1) -> 20608.165 | M23: =IF(A23>=13,Assumptions!B28*IF(A23>=13,(1+Assumptions!B32)^(A23-12),1),0) -> 154561.24 | N23: =Assumptions!B29*IF(A23>=13,(1+Assumptions!B32)^(A23-12),1) -> 20608.165 | O23: =SUM(I23:N23) -> 422467.39 | P23: =H23-O23 -> 117507.84 | Q23: =Q22+P23 -> -1493789.8 | R23: =IF(Q23>=0,"YES","No") -> No
A24: 23 | B24: =ROUNDUP(A24/12,0) -> 2 | C24: ="Month "&A24 -> Month 23 | D24: =D23*(1+IF(B24=1,Assumptions!B14,Assumptions!B15)) -> 656.74772 | E24: =D24*Assumptions!B16 -> 394048.63 | F24: =F23*(1+Assumptions!B20) -> 497.88634 | G24: =F24*Assumptions!B21 -> 149365.9 | H24: =E24+G24 -> 543414.53 | I24: =Assumptions!B24*IF(A24>=13,(1+Assumptions!B32)^(A24-12),1) -> 155024.92 | J24: =Assumptions!B25*IF(A24>=13,(1+Assumptions!B32)^(A24-12),1) -> 41339.979 | K24: =Assumptions!B26*IF(A24>=13,(1+Assumptions!B32)^(A24-12),1) -> 31004.984 | L24: =Assumptions!B27*IF(A24>=13,(1+Assumptions!B32)^(A24-12),1) -> 20669.99 | M24: =IF(A24>=13,Assumptions!B28*IF(A24>=13,(1+Assumptions!B32)^(A24-12),1),0) -> 155024.92 | N24: =Assumptions!B29*IF(A24>=13,(1+Assumptions!B32)^(A24-12),1) -> 20669.99 | O24: =SUM(I24:N24) -> 423734.79 | P24: =H24-O24 -> 119679.75 | Q24: =Q23+P24 -> -1374110.1 | R24: =IF(Q24>=0,"YES","No") -> No
A25: 24 | B25: =ROUNDUP(A25/12,0) -> 2 | C25: ="Month "&A25 -> Month 24 | D25: =D24*(1+IF(B25=1,Assumptions!B14,Assumptions!B15)) -> 660.03146 | E25: =D25*Assumptions!B16 -> 396018.87 | F25: =F24*(1+Assumptions!B20) -> 502.86521 | G25: =F25*Assumptions!B21 -> 150859.56 | H25: =E25+G25 -> 546878.44 | I25: =Assumptions!B24*IF(A25>=13,(1+Assumptions!B32)^(A25-12),1) -> 155490 | J25: =Assumptions!B25*IF(A25>=13,(1+Assumptions!B32)^(A25-12),1) -> 41463.999 | K25: =Assumptions!B26*IF(A25>=13,(1+Assumptions!B32)^(A25-12),1) -> 31097.999 | L25: =Assumptions!B27*IF(A25>=13,(1+Assumptions!B32)^(A25-12),1) -> 20732 | M25: =IF(A25>=13,Assumptions!B28*IF(A25>=13,(1+Assumptions!B32)^(A25-12),1),0) -> 155490 | N25: =Assumptions!B29*IF(A25>=13,(1+Assumptions!B32)^(A25-12),1) -> 20732 | O25: =SUM(I25:N25) -> 425005.99 | P25: =H25-O25 -> 121872.44 | Q25: =Q24+P25 -> -1252237.6 | R25: =IF(Q25>=0,"YES","No") -> No
A26: 25 | B26: =ROUNDUP(A26/12,0) -> 3 | C26: ="Month "&A26 -> Month 25 | D26: =D25*(1+IF(B26=1,Assumptions!B14,Assumptions!B15)) -> 663.33161 | E26: =D26*Assumptions!B16 -> 397998.97 | F26: =F25*(1+Assumptions!B20) -> 507.89386 | G26: =F26*Assumptions!B21 -> 152368.16 | H26: =E26+G26 -> 550367.13 | I26: =Assumptions!B24*IF(A26>=13,(1+Assumptions!B32)^(A26-12),1) -> 155956.47 | J26: =Assumptions!B25*IF(A26>=13,(1+Assumptions!B32)^(A26-12),1) -> 41588.391 | K26: =Assumptions!B26*IF(A26>=13,(1+Assumptions!B32)^(A26-12),1) -> 31191.293 | L26: =Assumptions!B27*IF(A26>=13,(1+Assumptions!B32)^(A26-12),1) -> 20794.196 | M26: =IF(A26>=13,Assumptions!B28*IF(A26>=13,(1+Assumptions!B32)^(A26-12),1),0) -> 155956.47 | N26: =Assumptions!B29*IF(A26>=13,(1+Assumptions!B32)^(A26-12),1) -> 20794.196 | O26: =SUM(I26:N26) -> 426281.01 | P26: =H26-O26 -> 124086.12 | Q26: =Q25+P26 -> -1128151.5 | R26: =IF(Q26>=0,"YES","No") -> No
A27: 26 | B27: =ROUNDUP(A27/12,0) -> 3 | C27: ="Month "&A27 -> Month 26 | D27: =D26*(1+IF(B27=1,Assumptions!B14,Assumptions!B15)) -> 666.64827 | E27: =D27*Assumptions!B16 -> 399988.96 | F27: =F26*(1+Assumptions!B20) -> 512.9728 | G27: =F27*Assumptions!B21 -> 153891.84 | H27: =E27+G27 -> 553880.8 | I27: =Assumptions!B24*IF(A27>=13,(1+Assumptions!B32)^(A27-12),1) -> 156424.34 | J27: =Assumptions!B25*IF(A27>=13,(1+Assumptions!B32)^(A27-12),1) -> 41713.156 | K27: =Assumptions!B26*IF(A27>=13,(1+Assumptions!B32)^(A27-12),1) -> 31284.867 | L27: =Assumptions!B27*IF(A27>=13,(1+Assumptions!B32)^(A27-12),1) -> 20856.578 | M27: =IF(A27>=13,Assumptions!B28*IF(A27>=13,(1+Assumptions!B32)^(A27-12),1),0) -> 156424.34 | N27: =Assumptions!B29*IF(A27>=13,(1+Assumptions!B32)^(A27-12),1) -> 20856.578 | O27: =SUM(I27:N27) -> 427559.85 | P27: =H27-O27 -> 126320.95 | Q27: =Q26+P27 -> -1001830.5 | R27: =IF(Q27>=0,"YES","No") -> No
A28: 27 | B28: =ROUNDUP(A28/12,0) -> 3 | C28: ="Month "&A28 -> Month 27 | D28: =D27*(1+IF(B28=1,Assumptions!B14,Assumptions!B15)) -> 669.98151 | E28: =D28*Assumptions!B16 -> 401988.91 | F28: =F27*(1+Assumptions!B20) -> 518.10253 | G28: =F28*Assumptions!B21 -> 155430.76 | H28: =E28+G28 -> 557419.67 | I28: =Assumptions!B24*IF(A28>=13,(1+Assumptions!B32)^(A28-12),1) -> 156893.61 | J28: =Assumptions!B25*IF(A28>=13,(1+Assumptions!B32)^(A28-12),1) -> 41838.296 | K28: =Assumptions!B26*IF(A28>=13,(1+Assumptions!B32)^(A28-12),1) -> 31378.722 | L28: =Assumptions!B27*IF(A28>=13,(1+Assumptions!B32)^(A28-12),1) -> 20919.148 | M28: =IF(A28>=13,Assumptions!B28*IF(A28>=13,(1+Assumptions!B32)^(A28-12),1),0) -> 156893.61 | N28: =Assumptions!B29*IF(A28>=13,(1+Assumptions!B32)^(A28-12),1) -> 20919.148 | O28: =SUM(I28:N28) -> 428842.53 | P28: =H28-O28 -> 128577.13 | Q28: =Q27+P28 -> -873253.41 | R28: =IF(Q28>=0,"YES","No") -> No
A29: 28 | B29: =ROUNDUP(A29/12,0) -> 3 | C29: ="Month "&A29 -> Month 28 | D29: =D28*(1+IF(B29=1,Assumptions!B14,Assumptions!B15)) -> 673.33142 | E29: =D29*Assumptions!B16 -> 403998.85 | F29: =F28*(1+Assumptions!B20) -> 523.28355 | G29: =F29*Assumptions!B21 -> 156985.07 | H29: =E29+G29 -> 560983.92 | I29: =Assumptions!B24*IF(A29>=13,(1+Assumptions!B32)^(A29-12),1) -> 157364.29 | J29: =Assumptions!B25*IF(A29>=13,(1+Assumptions!B32)^(A29-12),1) -> 41963.811 | K29: =Assumptions!B26*IF(A29>=13,(1+Assumptions!B32)^(A29-12),1) -> 31472.858 | L29: =Assumptions!B27*IF(A29>=13,(1+Assumptions!B32)^(A29-12),1) -> 20981.905 | M29: =IF(A29>=13,Assumptions!B28*IF(A29>=13,(1+Assumptions!B32)^(A29-12),1),0) -> 157364.29 | N29: =Assumptions!B29*IF(A29>=13,(1+Assumptions!B32)^(A29-12),1) -> 20981.905 | O29: =SUM(I29:N29) -> 430129.06 | P29: =H29-O29 -> 130854.86 | Q29: =Q28+P29 -> -742398.56 | R29: =IF(Q29>=0,"YES","No") -> No
A30: 29 | B30: =ROUNDUP(A30/12,0) -> 3 | C30: ="Month "&A30 -> Month 29 | D30: =D29*(1+IF(B30=1,Assumptions!B14,Assumptions!B15)) -> 676.69808 | E30: =D30*Assumptions!B16 -> 406018.85 | F30: =F29*(1+Assumptions!B20) -> 528.51639 | G30: =F30*Assumptions!B21 -> 158554.92 | H30: =E30+G30 -> 564573.76 | I30: =Assumptions!B24*IF(A30>=13,(1+Assumptions!B32)^(A30-12),1) -> 157836.38 | J30: =Assumptions!B25*IF(A30>=13,(1+Assumptions!B32)^(A30-12),1) -> 42089.702 | K30: =Assumptions!B26*IF(A30>=13,(1+Assumptions!B32)^(A30-12),1) -> 31567.277 | L30: =Assumptions!B27*IF(A30>=13,(1+Assumptions!B32)^(A30-12),1) -> 21044.851 | M30: =IF(A30>=13,Assumptions!B28*IF(A30>=13,(1+Assumptions!B32)^(A30-12),1),0) -> 157836.38 | N30: =Assumptions!B29*IF(A30>=13,(1+Assumptions!B32)^(A30-12),1) -> 21044.851 | O30: =SUM(I30:N30) -> 431419.45 | P30: =H30-O30 -> 133154.32 | Q30: =Q29+P30 -> -609244.24 | R30: =IF(Q30>=0,"YES","No") -> No
A31: 30 | B31: =ROUNDUP(A31/12,0) -> 3 | C31: ="Month "&A31 -> Month 30 | D31: =D30*(1+IF(B31=1,Assumptions!B14,Assumptions!B15)) -> 680.08157 | E31: =D31*Assumptions!B16 -> 408048.94 | F31: =F30*(1+Assumptions!B20) -> 533.80155 | G31: =F31*Assumptions!B21 -> 160140.47 | H31: =E31+G31 -> 568189.41 | I31: =Assumptions!B24*IF(A31>=13,(1+Assumptions!B32)^(A31-12),1) -> 158309.89 | J31: =Assumptions!B25*IF(A31>=13,(1+Assumptions!B32)^(A31-12),1) -> 42215.971 | K31: =Assumptions!B26*IF(A31>=13,(1+Assumptions!B32)^(A31-12),1) -> 31661.978 | L31: =Assumptions!B27*IF(A31>=13,(1+Assumptions!B32)^(A31-12),1) -> 21107.986 | M31: =IF(A31>=13,Assumptions!B28*IF(A31>=13,(1+Assumptions!B32)^(A31-12),1),0) -> 158309.89 | N31: =Assumptions!B29*IF(A31>=13,(1+Assumptions!B32)^(A31-12),1) -> 21107.986 | O31: =SUM(I31:N31) -> 432713.71 | P31: =H31-O31 -> 135475.7 | Q31: =Q30+P31 -> -473768.54 | R31: =IF(Q31>=0,"YES","No") -> No
A32: 31 | B32: =ROUNDUP(A32/12,0) -> 3 | C32: ="Month "&A32 -> Month 31 | D32: =D31*(1+IF(B32=1,Assumptions!B14,Assumptions!B15)) -> 683.48198 | E32: =D32*Assumptions!B16 -> 410089.19 | F32: =F31*(1+Assumptions!B20) -> 539.13957 | G32: =F32*Assumptions!B21 -> 161741.87 | H32: =E32+G32 -> 571831.06 | I32: =Assumptions!B24*IF(A32>=13,(1+Assumptions!B32)^(A32-12),1) -> 158784.82 | J32: =Assumptions!B25*IF(A32>=13,(1+Assumptions!B32)^(A32-12),1) -> 42342.619 | K32: =Assumptions!B26*IF(A32>=13,(1+Assumptions!B32)^(A32-12),1) -> 31756.964 | L32: =Assumptions!B27*IF(A32>=13,(1+Assumptions!B32)^(A32-12),1) -> 21171.31 | M32: =IF(A32>=13,Assumptions!B28*IF(A32>=13,(1+Assumptions!B32)^(A32-12),1),0) -> 158784.82 | N32: =Assumptions!B29*IF(A32>=13,(1+Assumptions!B32)^(A32-12),1) -> 21171.31 | O32: =SUM(I32:N32) -> 434011.85 | P32: =H32-O32 -> 137819.21 | Q32: =Q31+P32 -> -335949.33 | R32: =IF(Q32>=0,"YES","No") -> No
A33: 32 | B33: =ROUNDUP(A33/12,0) -> 3 | C33: ="Month "&A33 -> Month 32 | D33: =D32*(1+IF(B33=1,Assumptions!B14,Assumptions!B15)) -> 686.89939 | E33: =D33*Assumptions!B16 -> 412139.63 | F33: =F32*(1+Assumptions!B20) -> 544.53096 | G33: =F33*Assumptions!B21 -> 163359.29 | H33: =E33+G33 -> 575498.92 | I33: =Assumptions!B24*IF(A33>=13,(1+Assumptions!B32)^(A33-12),1) -> 159261.18 | J33: =Assumptions!B25*IF(A33>=13,(1+Assumptions!B32)^(A33-12),1) -> 42469.647 | K33: =Assumptions!B26*IF(A33>=13,(1+Assumptions!B32)^(A33-12),1) -> 31852.235 | L33: =Assumptions!B27*IF(A33>=13,(1+Assumptions!B32)^(A33-12),1) -> 21234.824 | M33: =IF(A33>=13,Assumptions!B28*IF(A33>=13,(1+Assumptions!B32)^(A33-12),1),0) -> 159261.18 | N33: =Assumptions!B29*IF(A33>=13,(1+Assumptions!B32)^(A33-12),1) -> 21234.824 | O33: =SUM(I33:N33) -> 435313.88 | P33: =H33-O33 -> 140185.04 | Q33: =Q32+P33 -> -195764.29 | R33: =IF(Q33>=0,"YES","No") -> No
A34: 33 | B34: =ROUNDUP(A34/12,0) -> 3 | C34: ="Month "&A34 -> Month 33 | D34: =D33*(1+IF(B34=1,Assumptions!B14,Assumptions!B15)) -> 690.33388 | E34: =D34*Assumptions!B16 -> 414200.33 | F34: =F33*(1+Assumptions!B20) -> 549.97627 | G34: =F34*Assumptions!B21 -> 164992.88 | H34: =E34+G34 -> 579193.21 | I34: =Assumptions!B24*IF(A34>=13,(1+Assumptions!B32)^(A34-12),1) -> 159738.96 | J34: =Assumptions!B25*IF(A34>=13,(1+Assumptions!B32)^(A34-12),1) -> 42597.056 | K34: =Assumptions!B26*IF(A34>=13,(1+Assumptions!B32)^(A34-12),1) -> 31947.792 | L34: =Assumptions!B27*IF(A34>=13,(1+Assumptions!B32)^(A34-12),1) -> 21298.528 | M34: =IF(A34>=13,Assumptions!B28*IF(A34>=13,(1+Assumptions!B32)^(A34-12),1),0) -> 159738.96 | N34: =Assumptions!B29*IF(A34>=13,(1+Assumptions!B32)^(A34-12),1) -> 21298.528 | O34: =SUM(I34:N34) -> 436619.82 | P34: =H34-O34 -> 142573.39 | Q34: =Q33+P34 -> -53190.902 | R34: =IF(Q34>=0,"YES","No") -> No
A35: 34 | B35: =ROUNDUP(A35/12,0) -> 3 | C35: ="Month "&A35 -> Month 34 | D35: =D34*(1+IF(B35=1,Assumptions!B14,Assumptions!B15)) -> 693.78555 | E35: =D35*Assumptions!B16 -> 416271.33 | F35: =F34*(1+Assumptions!B20) -> 555.47603 | G35: =F35*Assumptions!B21 -> 166642.81 | H35: =E35+G35 -> 582914.14 | I35: =Assumptions!B24*IF(A35>=13,(1+Assumptions!B32)^(A35-12),1) -> 160218.18 | J35: =Assumptions!B25*IF(A35>=13,(1+Assumptions!B32)^(A35-12),1) -> 42724.847 | K35: =Assumptions!B26*IF(A35>=13,(1+Assumptions!B32)^(A35-12),1) -> 32043.635 | L35: =Assumptions!B27*IF(A35>=13,(1+Assumptions!B32)^(A35-12),1) -> 21362.424 | M35: =IF(A35>=13,Assumptions!B28*IF(A35>=13,(1+Assumptions!B32)^(A35-12),1),0) -> 160218.18 | N35: =Assumptions!B29*IF(A35>=13,(1+Assumptions!B32)^(A35-12),1) -> 21362.424 | O35: =SUM(I35:N35) -> 437929.68 | P35: =H35-O35 -> 144984.46 | Q35: =Q34+P35 -> 91793.556 | R35: =IF(Q35>=0,"YES","No") -> YES
A36: 35 | B36: =ROUNDUP(A36/12,0) -> 3 | C36: ="Month "&A36 -> Month 35 | D36: =D35*(1+IF(B36=1,Assumptions!B14,Assumptions!B15)) -> 697.25448 | E36: =D36*Assumptions!B16 -> 418352.69 | F36: =F35*(1+Assumptions!B20) -> 561.03079 | G36: =F36*Assumptions!B21 -> 168309.24 | H36: =E36+G36 -> 586661.93 | I36: =Assumptions!B24*IF(A36>=13,(1+Assumptions!B32)^(A36-12),1) -> 160698.83 | J36: =Assumptions!B25*IF(A36>=13,(1+Assumptions!B32)^(A36-12),1) -> 42853.022 | K36: =Assumptions!B26*IF(A36>=13,(1+Assumptions!B32)^(A36-12),1) -> 32139.766 | L36: =Assumptions!B27*IF(A36>=13,(1+Assumptions!B32)^(A36-12),1) -> 21426.511 | M36: =IF(A36>=13,Assumptions!B28*IF(A36>=13,(1+Assumptions!B32)^(A36-12),1),0) -> 160698.83 | N36: =Assumptions!B29*IF(A36>=13,(1+Assumptions!B32)^(A36-12),1) -> 21426.511 | O36: =SUM(I36:N36) -> 439243.47 | P36: =H36-O36 -> 147418.45 | Q36: =Q35+P36 -> 239212.01 | R36: =IF(Q36>=0,"YES","No") -> YES
A37: 36 | B37: =ROUNDUP(A37/12,0) -> 3 | C37: ="Month "&A37 -> Month 36 | D37: =D36*(1+IF(B37=1,Assumptions!B14,Assumptions!B15)) -> 700.74075 | E37: =D37*Assumptions!B16 -> 420444.45 | F37: =F36*(1+Assumptions!B20) -> 566.6411 | G37: =F37*Assumptions!B21 -> 169992.33 | H37: =E37+G37 -> 590436.78 | I37: =Assumptions!B24*IF(A37>=13,(1+Assumptions!B32)^(A37-12),1) -> 161180.93 | J37: =Assumptions!B25*IF(A37>=13,(1+Assumptions!B32)^(A37-12),1) -> 42981.581 | K37: =Assumptions!B26*IF(A37>=13,(1+Assumptions!B32)^(A37-12),1) -> 32236.186 | L37: =Assumptions!B27*IF(A37>=13,(1+Assumptions!B32)^(A37-12),1) -> 21490.79 | M37: =IF(A37>=13,Assumptions!B28*IF(A37>=13,(1+Assumptions!B32)^(A37-12),1),0) -> 161180.93 | N37: =Assumptions!B29*IF(A37>=13,(1+Assumptions!B32)^(A37-12),1) -> 21490.79 | O37: =SUM(I37:N37) -> 440561.2 | P37: =H37-O37 -> 149875.58 | Q37: =Q36+P37 -> 389087.59 | R37: =IF(Q37>=0,"YES","No") -> YES
A38: 37 | B38: =ROUNDUP(A38/12,0) -> 4 | C38: ="Month "&A38 -> Month 37 | D38: =D37*(1+IF(B38=1,Assumptions!B14,Assumptions!B15)) -> 704.24446 | E38: =D38*Assumptions!B16 -> 422546.67 | F38: =F37*(1+Assumptions!B20) -> 572.30751 | G38: =F38*Assumptions!B21 -> 171692.25 | H38: =E38+G38 -> 594238.93 | I38: =Assumptions!B24*IF(A38>=13,(1+Assumptions!B32)^(A38-12),1) -> 161664.47 | J38: =Assumptions!B25*IF(A38>=13,(1+Assumptions!B32)^(A38-12),1) -> 43110.526 | K38: =Assumptions!B26*IF(A38>=13,(1+Assumptions!B32)^(A38-12),1) -> 32332.894 | L38: =Assumptions!B27*IF(A38>=13,(1+Assumptions!B32)^(A38-12),1) -> 21555.263 | M38: =IF(A38>=13,Assumptions!B28*IF(A38>=13,(1+Assumptions!B32)^(A38-12),1),0) -> 161664.47 | N38: =Assumptions!B29*IF(A38>=13,(1+Assumptions!B32)^(A38-12),1) -> 21555.263 | O38: =SUM(I38:N38) -> 441882.89 | P38: =H38-O38 -> 152356.04 | Q38: =Q37+P38 -> 541443.63 | R38: =IF(Q38>=0,"YES","No") -> YES
A39: 38 | B39: =ROUNDUP(A39/12,0) -> 4 | C39: ="Month "&A39 -> Month 38 | D39: =D38*(1+IF(B39=1,Assumptions!B14,Assumptions!B15)) -> 707.76568 | E39: =D39*Assumptions!B16 -> 424659.41 | F39: =F38*(1+Assumptions!B20) -> 578.03059 | G39: =F39*Assumptions!B21 -> 173409.18 | H39: =E39+G39 -> 598068.58 | I39: =Assumptions!B24*IF(A39>=13,(1+Assumptions!B32)^(A39-12),1) -> 162149.46 | J39: =Assumptions!B25*IF(A39>=13,(1+Assumptions!B32)^(A39-12),1) -> 43239.857 | K39: =Assumptions!B26*IF(A39>=13,(1+Assumptions!B32)^(A39-12),1) -> 32429.893 | L39: =Assumptions!B27*IF(A39>=13,(1+Assumptions!B32)^(A39-12),1) -> 21619.929 | M39: =IF(A39>=13,Assumptions!B28*IF(A39>=13,(1+Assumptions!B32)^(A39-12),1),0) -> 162149.46 | N39: =Assumptions!B29*IF(A39>=13,(1+Assumptions!B32)^(A39-12),1) -> 21619.929 | O39: =SUM(I39:N39) -> 443208.54 | P39: =H39-O39 -> 154860.05 | Q39: =Q38+P39 -> 696303.68 | R39: =IF(Q39>=0,"YES","No") -> YES
A40: 39 | B40: =ROUNDUP(A40/12,0) -> 4 | C40: ="Month "&A40 -> Month 39 | D40: =D39*(1+IF(B40=1,Assumptions!B14,Assumptions!B15)) -> 711.30451 | E40: =D40*Assumptions!B16 -> 426782.7 | F40: =F39*(1+Assumptions!B20) -> 583.81089 | G40: =F40*Assumptions!B21 -> 175143.27 | H40: =E40+G40 -> 601925.97 | I40: =Assumptions!B24*IF(A40>=13,(1+Assumptions!B32)^(A40-12),1) -> 162635.91 | J40: =Assumptions!B25*IF(A40>=13,(1+Assumptions!B32)^(A40-12),1) -> 43369.577 | K40: =Assumptions!B26*IF(A40>=13,(1+Assumptions!B32)^(A40-12),1) -> 32527.182 | L40: =Assumptions!B27*IF(A40>=13,(1+Assumptions!B32)^(A40-12),1) -> 21684.788 | M40: =IF(A40>=13,Assumptions!B28*IF(A40>=13,(1+Assumptions!B32)^(A40-12),1),0) -> 162635.91 | N40: =Assumptions!B29*IF(A40>=13,(1+Assumptions!B32)^(A40-12),1) -> 21684.788 | O40: =SUM(I40:N40) -> 444538.16 | P40: =H40-O40 -> 157387.81 | Q40: =Q39+P40 -> 853691.49 | R40: =IF(Q40>=0,"YES","No") -> YES
A41: 40 | B41: =ROUNDUP(A41/12,0) -> 4 | C41: ="Month "&A41 -> Month 40 | D41: =D40*(1+IF(B41=1,Assumptions!B14,Assumptions!B15)) -> 714.86103 | E41: =D41*Assumptions!B16 -> 428916.62 | F41: =F40*(1+Assumptions!B20) -> 589.649 | G41: =F41*Assumptions!B21 -> 176894.7 | H41: =E41+G41 -> 605811.32 | I41: =Assumptions!B24*IF(A41>=13,(1+Assumptions!B32)^(A41-12),1) -> 163123.82 | J41: =Assumptions!B25*IF(A41>=13,(1+Assumptions!B32)^(A41-12),1) -> 43499.685 | K41: =Assumptions!B26*IF(A41>=13,(1+Assumptions!B32)^(A41-12),1) -> 32624.764 | L41: =Assumptions!B27*IF(A41>=13,(1+Assumptions!B32)^(A41-12),1) -> 21749.843 | M41: =IF(A41>=13,Assumptions!B28*IF(A41>=13,(1+Assumptions!B32)^(A41-12),1),0) -> 163123.82 | N41: =Assumptions!B29*IF(A41>=13,(1+Assumptions!B32)^(A41-12),1) -> 21749.843 | O41: =SUM(I41:N41) -> 445871.78 | P41: =H41-O41 -> 159939.54 | Q41: =Q40+P41 -> 1013631 | R41: =IF(Q41>=0,"YES","No") -> YES
A42: 41 | B42: =ROUNDUP(A42/12,0) -> 4 | C42: ="Month "&A42 -> Month 41 | D42: =D41*(1+IF(B42=1,Assumptions!B14,Assumptions!B15)) -> 718.43534 | E42: =D42*Assumptions!B16 -> 431061.2 | F42: =F41*(1+Assumptions!B20) -> 595.54549 | G42: =F42*Assumptions!B21 -> 178663.65 | H42: =E42+G42 -> 609724.85 | I42: =Assumptions!B24*IF(A42>=13,(1+Assumptions!B32)^(A42-12),1) -> 163613.19 | J42: =Assumptions!B25*IF(A42>=13,(1+Assumptions!B32)^(A42-12),1) -> 43630.184 | K42: =Assumptions!B26*IF(A42>=13,(1+Assumptions!B32)^(A42-12),1) -> 32722.638 | L42: =Assumptions!B27*IF(A42>=13,(1+Assumptions!B32)^(A42-12),1) -> 21815.092 | M42: =IF(A42>=13,Assumptions!B28*IF(A42>=13,(1+Assumptions!B32)^(A42-12),1),0) -> 163613.19 | N42: =Assumptions!B29*IF(A42>=13,(1+Assumptions!B32)^(A42-12),1) -> 21815.092 | O42: =SUM(I42:N42) -> 447209.39 | P42: =H42-O42 -> 162515.46 | Q42: =Q41+P42 -> 1176146.5 | R42: =IF(Q42>=0,"YES","No") -> YES
A43: 42 | B43: =ROUNDUP(A43/12,0) -> 4 | C43: ="Month "&A43 -> Month 42 | D43: =D42*(1+IF(B43=1,Assumptions!B14,Assumptions!B15)) -> 722.02751 | E43: =D43*Assumptions!B16 -> 433216.51 | F43: =F42*(1+Assumptions!B20) -> 601.50095 | G43: =F43*Assumptions!B21 -> 180450.28 | H43: =E43+G43 -> 613666.79 | I43: =Assumptions!B24*IF(A43>=13,(1+Assumptions!B32)^(A43-12),1) -> 164104.03 | J43: =Assumptions!B25*IF(A43>=13,(1+Assumptions!B32)^(A43-12),1) -> 43761.075 | K43: =Assumptions!B26*IF(A43>=13,(1+Assumptions!B32)^(A43-12),1) -> 32820.806 | L43: =Assumptions!B27*IF(A43>=13,(1+Assumptions!B32)^(A43-12),1) -> 21880.537 | M43: =IF(A43>=13,Assumptions!B28*IF(A43>=13,(1+Assumptions!B32)^(A43-12),1),0) -> 164104.03 | N43: =Assumptions!B29*IF(A43>=13,(1+Assumptions!B32)^(A43-12),1) -> 21880.537 | O43: =SUM(I43:N43) -> 448551.02 | P43: =H43-O43 -> 165115.77 | Q43: =Q42+P43 -> 1341262.3 | R43: =IF(Q43>=0,"YES","No") -> YES
A44: 43 | B44: =ROUNDUP(A44/12,0) -> 4 | C44: ="Month "&A44 -> Month 43 | D44: =D43*(1+IF(B44=1,Assumptions!B14,Assumptions!B15)) -> 725.63765 | E44: =D44*Assumptions!B16 -> 435382.59 | F44: =F43*(1+Assumptions!B20) -> 607.51596 | G44: =F44*Assumptions!B21 -> 182254.79 | H44: =E44+G44 -> 617637.38 | I44: =Assumptions!B24*IF(A44>=13,(1+Assumptions!B32)^(A44-12),1) -> 164596.34 | J44: =Assumptions!B25*IF(A44>=13,(1+Assumptions!B32)^(A44-12),1) -> 43892.358 | K44: =Assumptions!B26*IF(A44>=13,(1+Assumptions!B32)^(A44-12),1) -> 32919.269 | L44: =Assumptions!B27*IF(A44>=13,(1+Assumptions!B32)^(A44-12),1) -> 21946.179 | M44: =IF(A44>=13,Assumptions!B28*IF(A44>=13,(1+Assumptions!B32)^(A44-12),1),0) -> 164596.34 | N44: =Assumptions!B29*IF(A44>=13,(1+Assumptions!B32)^(A44-12),1) -> 21946.179 | O44: =SUM(I44:N44) -> 449896.67 | P44: =H44-O44 -> 167740.71 | Q44: =Q43+P44 -> 1509003 | R44: =IF(Q44>=0,"YES","No") -> YES
A45: 44 | B45: =ROUNDUP(A45/12,0) -> 4 | C45: ="Month "&A45 -> Month 44 | D45: =D44*(1+IF(B45=1,Assumptions!B14,Assumptions!B15)) -> 729.26584 | E45: =D45*Assumptions!B16 -> 437559.5 | F45: =F44*(1+Assumptions!B20) -> 613.59112 | G45: =F45*Assumptions!B21 -> 184077.34 | H45: =E45+G45 -> 621636.84 | I45: =Assumptions!B24*IF(A45>=13,(1+Assumptions!B32)^(A45-12),1) -> 165090.13 | J45: =Assumptions!B25*IF(A45>=13,(1+Assumptions!B32)^(A45-12),1) -> 44024.035 | K45: =Assumptions!B26*IF(A45>=13,(1+Assumptions!B32)^(A45-12),1) -> 33018.026 | L45: =Assumptions!B27*IF(A45>=13,(1+Assumptions!B32)^(A45-12),1) -> 22012.018 | M45: =IF(A45>=13,Assumptions!B28*IF(A45>=13,(1+Assumptions!B32)^(A45-12),1),0) -> 165090.13 | N45: =Assumptions!B29*IF(A45>=13,(1+Assumptions!B32)^(A45-12),1) -> 22012.018 | O45: =SUM(I45:N45) -> 451246.36 | P45: =H45-O45 -> 170390.48 | Q45: =Q44+P45 -> 1679393.5 | R45: =IF(Q45>=0,"YES","No") -> YES
A46: 45 | B46: =ROUNDUP(A46/12,0) -> 4 | C46: ="Month "&A46 -> Month 45 | D46: =D45*(1+IF(B46=1,Assumptions!B14,Assumptions!B15)) -> 732.91217 | E46: =D46*Assumptions!B16 -> 439747.3 | F46: =F45*(1+Assumptions!B20) -> 619.72703 | G46: =F46*Assumptions!B21 -> 185918.11 | H46: =E46+G46 -> 625665.41 | I46: =Assumptions!B24*IF(A46>=13,(1+Assumptions!B32)^(A46-12),1) -> 165585.4 | J46: =Assumptions!B25*IF(A46>=13,(1+Assumptions!B32)^(A46-12),1) -> 44156.107 | K46: =Assumptions!B26*IF(A46>=13,(1+Assumptions!B32)^(A46-12),1) -> 33117.081 | L46: =Assumptions!B27*IF(A46>=13,(1+Assumptions!B32)^(A46-12),1) -> 22078.054 | M46: =IF(A46>=13,Assumptions!B28*IF(A46>=13,(1+Assumptions!B32)^(A46-12),1),0) -> 165585.4 | N46: =Assumptions!B29*IF(A46>=13,(1+Assumptions!B32)^(A46-12),1) -> 22078.054 | O46: =SUM(I46:N46) -> 452600.1 | P46: =H46-O46 -> 173065.31 | Q46: =Q45+P46 -> 1852458.8 | R46: =IF(Q46>=0,"YES","No") -> YES
A47: 46 | B47: =ROUNDUP(A47/12,0) -> 4 | C47: ="Month "&A47 -> Month 46 | D47: =D46*(1+IF(B47=1,Assumptions!B14,Assumptions!B15)) -> 736.57673 | E47: =D47*Assumptions!B16 -> 441946.04 | F47: =F46*(1+Assumptions!B20) -> 625.9243 | G47: =F47*Assumptions!B21 -> 187777.29 | H47: =E47+G47 -> 629723.33 | I47: =Assumptions!B24*IF(A47>=13,(1+Assumptions!B32)^(A47-12),1) -> 166082.16 | J47: =Assumptions!B25*IF(A47>=13,(1+Assumptions!B32)^(A47-12),1) -> 44288.576 | K47: =Assumptions!B26*IF(A47>=13,(1+Assumptions!B32)^(A47-12),1) -> 33216.432 | L47: =Assumptions!B27*IF(A47>=13,(1+Assumptions!B32)^(A47-12),1) -> 22144.288 | M47: =IF(A47>=13,Assumptions!B28*IF(A47>=13,(1+Assumptions!B32)^(A47-12),1),0) -> 166082.16 | N47: =Assumptions!B29*IF(A47>=13,(1+Assumptions!B32)^(A47-12),1) -> 22144.288 | O47: =SUM(I47:N47) -> 453957.9 | P47: =H47-O47 -> 175765.43 | Q47: =Q46+P47 -> 2028224.2 | R47: =IF(Q47>=0,"YES","No") -> YES
A48: 47 | B48: =ROUNDUP(A48/12,0) -> 4 | C48: ="Month "&A48 -> Month 47 | D48: =D47*(1+IF(B48=1,Assumptions!B14,Assumptions!B15)) -> 740.25961 | E48: =D48*Assumptions!B16 -> 444155.77 | F48: =F47*(1+Assumptions!B20) -> 632.18354 | G48: =F48*Assumptions!B21 -> 189655.06 | H48: =E48+G48 -> 633810.83 | I48: =Assumptions!B24*IF(A48>=13,(1+Assumptions!B32)^(A48-12),1) -> 166580.41 | J48: =Assumptions!B25*IF(A48>=13,(1+Assumptions!B32)^(A48-12),1) -> 44421.441 | K48: =Assumptions!B26*IF(A48>=13,(1+Assumptions!B32)^(A48-12),1) -> 33316.081 | L48: =Assumptions!B27*IF(A48>=13,(1+Assumptions!B32)^(A48-12),1) -> 22210.721 | M48: =IF(A48>=13,Assumptions!B28*IF(A48>=13,(1+Assumptions!B32)^(A48-12),1),0) -> 166580.41 | N48: =Assumptions!B29*IF(A48>=13,(1+Assumptions!B32)^(A48-12),1) -> 22210.721 | O48: =SUM(I48:N48) -> 455319.77 | P48: =H48-O48 -> 178491.05 | Q48: =Q47+P48 -> 2206715.2 | R48: =IF(Q48>=0,"YES","No") -> YES
A49: 48 | B49: =ROUNDUP(A49/12,0) -> 4 | C49: ="Month "&A49 -> Month 48 | D49: =D48*(1+IF(B49=1,Assumptions!B14,Assumptions!B15)) -> 743.96091 | E49: =D49*Assumptions!B16 -> 446376.55 | F49: =F48*(1+Assumptions!B20) -> 638.50538 | G49: =F49*Assumptions!B21 -> 191551.61 | H49: =E49+G49 -> 637928.16 | I49: =Assumptions!B24*IF(A49>=13,(1+Assumptions!B32)^(A49-12),1) -> 167080.15 | J49: =Assumptions!B25*IF(A49>=13,(1+Assumptions!B32)^(A49-12),1) -> 44554.706 | K49: =Assumptions!B26*IF(A49>=13,(1+Assumptions!B32)^(A49-12),1) -> 33416.029 | L49: =Assumptions!B27*IF(A49>=13,(1+Assumptions!B32)^(A49-12),1) -> 22277.353 | M49: =IF(A49>=13,Assumptions!B28*IF(A49>=13,(1+Assumptions!B32)^(A49-12),1),0) -> 167080.15 | N49: =Assumptions!B29*IF(A49>=13,(1+Assumptions!B32)^(A49-12),1) -> 22277.353 | O49: =SUM(I49:N49) -> 456685.73 | P49: =H49-O49 -> 181242.42 | Q49: =Q48+P49 -> 2387957.7 | R49: =IF(Q49>=0,"YES","No") -> YES
A50: 49 | B50: =ROUNDUP(A50/12,0) -> 5 | C50: ="Month "&A50 -> Month 49 | D50: =D49*(1+IF(B50=1,Assumptions!B14,Assumptions!B15)) -> 747.68071 | E50: =D50*Assumptions!B16 -> 448608.43 | F50: =F49*(1+Assumptions!B20) -> 644.89043 | G50: =F50*Assumptions!B21 -> 193467.13 | H50: =E50+G50 -> 642075.56 | I50: =Assumptions!B24*IF(A50>=13,(1+Assumptions!B32)^(A50-12),1) -> 167581.39 | J50: =Assumptions!B25*IF(A50>=13,(1+Assumptions!B32)^(A50-12),1) -> 44688.37 | K50: =Assumptions!B26*IF(A50>=13,(1+Assumptions!B32)^(A50-12),1) -> 33516.277 | L50: =Assumptions!B27*IF(A50>=13,(1+Assumptions!B32)^(A50-12),1) -> 22344.185 | M50: =IF(A50>=13,Assumptions!B28*IF(A50>=13,(1+Assumptions!B32)^(A50-12),1),0) -> 167581.39 | N50: =Assumptions!B29*IF(A50>=13,(1+Assumptions!B32)^(A50-12),1) -> 22344.185 | O50: =SUM(I50:N50) -> 458055.79 | P50: =H50-O50 -> 184019.77 | Q50: =Q49+P50 -> 2571977.4 | R50: =IF(Q50>=0,"YES","No") -> YES
A51: 50 | B51: =ROUNDUP(A51/12,0) -> 5 | C51: ="Month "&A51 -> Month 50 | D51: =D50*(1+IF(B51=1,Assumptions!B14,Assumptions!B15)) -> 751.41912 | E51: =D51*Assumptions!B16 -> 450851.47 | F51: =F50*(1+Assumptions!B20) -> 651.33934 | G51: =F51*Assumptions!B21 -> 195401.8 | H51: =E51+G51 -> 646253.27 | I51: =Assumptions!B24*IF(A51>=13,(1+Assumptions!B32)^(A51-12),1) -> 168084.13 | J51: =Assumptions!B25*IF(A51>=13,(1+Assumptions!B32)^(A51-12),1) -> 44822.435 | K51: =Assumptions!B26*IF(A51>=13,(1+Assumptions!B32)^(A51-12),1) -> 33616.826 | L51: =Assumptions!B27*IF(A51>=13,(1+Assumptions!B32)^(A51-12),1) -> 22411.218 | M51: =IF(A51>=13,Assumptions!B28*IF(A51>=13,(1+Assumptions!B32)^(A51-12),1),0) -> 168084.13 | N51: =Assumptions!B29*IF(A51>=13,(1+Assumptions!B32)^(A51-12),1) -> 22411.218 | O51: =SUM(I51:N51) -> 459429.96 | P51: =H51-O51 -> 186823.31 | Q51: =Q50+P51 -> 2758800.7 | R51: =IF(Q51>=0,"YES","No") -> YES
A52: 51 | B52: =ROUNDUP(A52/12,0) -> 5 | C52: ="Month "&A52 -> Month 51 | D52: =D51*(1+IF(B52=1,Assumptions!B14,Assumptions!B15)) -> 755.17621 | E52: =D52*Assumptions!B16 -> 453105.73 | F52: =F51*(1+Assumptions!B20) -> 657.85273 | G52: =F52*Assumptions!B21 -> 197355.82 | H52: =E52+G52 -> 650461.55 | I52: =Assumptions!B24*IF(A52>=13,(1+Assumptions!B32)^(A52-12),1) -> 168588.38 | J52: =Assumptions!B25*IF(A52>=13,(1+Assumptions!B32)^(A52-12),1) -> 44956.902 | K52: =Assumptions!B26*IF(A52>=13,(1+Assumptions!B32)^(A52-12),1) -> 33717.677 | L52: =Assumptions!B27*IF(A52>=13,(1+Assumptions!B32)^(A52-12),1) -> 22478.451 | M52: =IF(A52>=13,Assumptions!B28*IF(A52>=13,(1+Assumptions!B32)^(A52-12),1),0) -> 168588.38 | N52: =Assumptions!B29*IF(A52>=13,(1+Assumptions!B32)^(A52-12),1) -> 22478.451 | O52: =SUM(I52:N52) -> 460808.25 | P52: =H52-O52 -> 189653.3 | Q52: =Q51+P52 -> 2948454 | R52: =IF(Q52>=0,"YES","No") -> YES
A53: 52 | B53: =ROUNDUP(A53/12,0) -> 5 | C53: ="Month "&A53 -> Month 52 | D53: =D52*(1+IF(B53=1,Assumptions!B14,Assumptions!B15)) -> 758.95209 | E53: =D53*Assumptions!B16 -> 455371.26 | F53: =F52*(1+Assumptions!B20) -> 664.43126 | G53: =F53*Assumptions!B21 -> 199329.38 | H53: =E53+G53 -> 654700.63 | I53: =Assumptions!B24*IF(A53>=13,(1+Assumptions!B32)^(A53-12),1) -> 169094.15 | J53: =Assumptions!B25*IF(A53>=13,(1+Assumptions!B32)^(A53-12),1) -> 45091.773 | K53: =Assumptions!B26*IF(A53>=13,(1+Assumptions!B32)^(A53-12),1) -> 33818.83 | L53: =Assumptions!B27*IF(A53>=13,(1+Assumptions!B32)^(A53-12),1) -> 22545.887 | M53: =IF(A53>=13,Assumptions!B28*IF(A53>=13,(1+Assumptions!B32)^(A53-12),1),0) -> 169094.15 | N53: =Assumptions!B29*IF(A53>=13,(1+Assumptions!B32)^(A53-12),1) -> 22545.887 | O53: =SUM(I53:N53) -> 462190.67 | P53: =H53-O53 -> 192509.96 | Q53: =Q52+P53 -> 3140964 | R53: =IF(Q53>=0,"YES","No") -> YES
A54: 53 | B54: =ROUNDUP(A54/12,0) -> 5 | C54: ="Month "&A54 -> Month 53 | D54: =D53*(1+IF(B54=1,Assumptions!B14,Assumptions!B15)) -> 762.74686 | E54: =D54*Assumptions!B16 -> 457648.11 | F54: =F53*(1+Assumptions!B20) -> 671.07557 | G54: =F54*Assumptions!B21 -> 201322.67 | H54: =E54+G54 -> 658970.78 | I54: =Assumptions!B24*IF(A54>=13,(1+Assumptions!B32)^(A54-12),1) -> 169601.43 | J54: =Assumptions!B25*IF(A54>=13,(1+Assumptions!B32)^(A54-12),1) -> 45227.048 | K54: =Assumptions!B26*IF(A54>=13,(1+Assumptions!B32)^(A54-12),1) -> 33920.286 | L54: =Assumptions!B27*IF(A54>=13,(1+Assumptions!B32)^(A54-12),1) -> 22613.524 | M54: =IF(A54>=13,Assumptions!B28*IF(A54>=13,(1+Assumptions!B32)^(A54-12),1),0) -> 169601.43 | N54: =Assumptions!B29*IF(A54>=13,(1+Assumptions!B32)^(A54-12),1) -> 22613.524 | O54: =SUM(I54:N54) -> 463577.25 | P54: =H54-O54 -> 195393.54 | Q54: =Q53+P54 -> 3336357.5 | R54: =IF(Q54>=0,"YES","No") -> YES
A55: 54 | B55: =ROUNDUP(A55/12,0) -> 5 | C55: ="Month "&A55 -> Month 54 | D55: =D54*(1+IF(B55=1,Assumptions!B14,Assumptions!B15)) -> 766.56059 | E55: =D55*Assumptions!B16 -> 459936.35 | F55: =F54*(1+Assumptions!B20) -> 677.78632 | G55: =F55*Assumptions!B21 -> 203335.9 | H55: =E55+G55 -> 663272.25 | I55: =Assumptions!B24*IF(A55>=13,(1+Assumptions!B32)^(A55-12),1) -> 170110.24 | J55: =Assumptions!B25*IF(A55>=13,(1+Assumptions!B32)^(A55-12),1) -> 45362.729 | K55: =Assumptions!B26*IF(A55>=13,(1+Assumptions!B32)^(A55-12),1) -> 34022.047 | L55: =Assumptions!B27*IF(A55>=13,(1+Assumptions!B32)^(A55-12),1) -> 22681.365 | M55: =IF(A55>=13,Assumptions!B28*IF(A55>=13,(1+Assumptions!B32)^(A55-12),1),0) -> 170110.24 | N55: =Assumptions!B29*IF(A55>=13,(1+Assumptions!B32)^(A55-12),1) -> 22681.365 | O55: =SUM(I55:N55) -> 464967.98 | P55: =H55-O55 -> 198304.27 | Q55: =Q54+P55 -> 3534661.8 | R55: =IF(Q55>=0,"YES","No") -> YES
A56: 55 | B56: =ROUNDUP(A56/12,0) -> 5 | C56: ="Month "&A56 -> Month 55 | D56: =D55*(1+IF(B56=1,Assumptions!B14,Assumptions!B15)) -> 770.39339 | E56: =D56*Assumptions!B16 -> 462236.04 | F56: =F55*(1+Assumptions!B20) -> 684.56419 | G56: =F56*Assumptions!B21 -> 205369.26 | H56: =E56+G56 -> 667605.29 | I56: =Assumptions!B24*IF(A56>=13,(1+Assumptions!B32)^(A56-12),1) -> 170620.57 | J56: =Assumptions!B25*IF(A56>=13,(1+Assumptions!B32)^(A56-12),1) -> 45498.818 | K56: =Assumptions!B26*IF(A56>=13,(1+Assumptions!B32)^(A56-12),1) -> 34124.113 | L56: =Assumptions!B27*IF(A56>=13,(1+Assumptions!B32)^(A56-12),1) -> 22749.409 | M56: =IF(A56>=13,Assumptions!B28*IF(A56>=13,(1+Assumptions!B32)^(A56-12),1),0) -> 170620.57 | N56: =Assumptions!B29*IF(A56>=13,(1+Assumptions!B32)^(A56-12),1) -> 22749.409 | O56: =SUM(I56:N56) -> 466362.88 | P56: =H56-O56 -> 201242.41 | Q56: =Q55+P56 -> 3735904.2 | R56: =IF(Q56>=0,"YES","No") -> YES
A57: 56 | B57: =ROUNDUP(A57/12,0) -> 5 | C57: ="Month "&A57 -> Month 56 | D57: =D56*(1+IF(B57=1,Assumptions!B14,Assumptions!B15)) -> 774.24536 | E57: =D57*Assumptions!B16 -> 464547.22 | F57: =F56*(1+Assumptions!B20) -> 691.40983 | G57: =F57*Assumptions!B21 -> 207422.95 | H57: =E57+G57 -> 671970.16 | I57: =Assumptions!B24*IF(A57>=13,(1+Assumptions!B32)^(A57-12),1) -> 171132.43 | J57: =Assumptions!B25*IF(A57>=13,(1+Assumptions!B32)^(A57-12),1) -> 45635.314 | K57: =Assumptions!B26*IF(A57>=13,(1+Assumptions!B32)^(A57-12),1) -> 34226.486 | L57: =Assumptions!B27*IF(A57>=13,(1+Assumptions!B32)^(A57-12),1) -> 22817.657 | M57: =IF(A57>=13,Assumptions!B28*IF(A57>=13,(1+Assumptions!B32)^(A57-12),1),0) -> 171132.43 | N57: =Assumptions!B29*IF(A57>=13,(1+Assumptions!B32)^(A57-12),1) -> 22817.657 | O57: =SUM(I57:N57) -> 467761.97 | P57: =H57-O57 -> 204208.19 | Q57: =Q56+P57 -> 3940112.4 | R57: =IF(Q57>=0,"YES","No") -> YES
A58: 57 | B58: =ROUNDUP(A58/12,0) -> 5 | C58: ="Month "&A58 -> Month 57 | D58: =D57*(1+IF(B58=1,Assumptions!B14,Assumptions!B15)) -> 778.11659 | E58: =D58*Assumptions!B16 -> 466869.95 | F58: =F57*(1+Assumptions!B20) -> 698.32393 | G58: =F58*Assumptions!B21 -> 209497.18 | H58: =E58+G58 -> 676367.13 | I58: =Assumptions!B24*IF(A58>=13,(1+Assumptions!B32)^(A58-12),1) -> 171645.83 | J58: =Assumptions!B25*IF(A58>=13,(1+Assumptions!B32)^(A58-12),1) -> 45772.22 | K58: =Assumptions!B26*IF(A58>=13,(1+Assumptions!B32)^(A58-12),1) -> 34329.165 | L58: =Assumptions!B27*IF(A58>=13,(1+Assumptions!B32)^(A58-12),1) -> 22886.11 | M58: =IF(A58>=13,Assumptions!B28*IF(A58>=13,(1+Assumptions!B32)^(A58-12),1),0) -> 171645.83 | N58: =Assumptions!B29*IF(A58>=13,(1+Assumptions!B32)^(A58-12),1) -> 22886.11 | O58: =SUM(I58:N58) -> 469165.26 | P58: =H58-O58 -> 207201.87 | Q58: =Q57+P58 -> 4147314.3 | R58: =IF(Q58>=0,"YES","No") -> YES
A59: 58 | B59: =ROUNDUP(A59/12,0) -> 5 | C59: ="Month "&A59 -> Month 58 | D59: =D58*(1+IF(B59=1,Assumptions!B14,Assumptions!B15)) -> 782.00717 | E59: =D59*Assumptions!B16 -> 469204.3 | F59: =F58*(1+Assumptions!B20) -> 705.30717 | G59: =F59*Assumptions!B21 -> 211592.15 | H59: =E59+G59 -> 680796.45 | I59: =Assumptions!B24*IF(A59>=13,(1+Assumptions!B32)^(A59-12),1) -> 172160.76 | J59: =Assumptions!B25*IF(A59>=13,(1+Assumptions!B32)^(A59-12),1) -> 45909.537 | K59: =Assumptions!B26*IF(A59>=13,(1+Assumptions!B32)^(A59-12),1) -> 34432.153 | L59: =Assumptions!B27*IF(A59>=13,(1+Assumptions!B32)^(A59-12),1) -> 22954.768 | M59: =IF(A59>=13,Assumptions!B28*IF(A59>=13,(1+Assumptions!B32)^(A59-12),1),0) -> 172160.76 | N59: =Assumptions!B29*IF(A59>=13,(1+Assumptions!B32)^(A59-12),1) -> 22954.768 | O59: =SUM(I59:N59) -> 470572.75 | P59: =H59-O59 -> 210223.7 | Q59: =Q58+P59 -> 4357538 | R59: =IF(Q59>=0,"YES","No") -> YES
A60: 59 | B60: =ROUNDUP(A60/12,0) -> 5 | C60: ="Month "&A60 -> Month 59 | D60: =D59*(1+IF(B60=1,Assumptions!B14,Assumptions!B15)) -> 785.9172 | E60: =D60*Assumptions!B16 -> 471550.32 | F60: =F59*(1+Assumptions!B20) -> 712.36024 | G60: =F60*Assumptions!B21 -> 213708.07 | H60: =E60+G60 -> 685258.39 | I60: =Assumptions!B24*IF(A60>=13,(1+Assumptions!B32)^(A60-12),1) -> 172677.24 | J60: =Assumptions!B25*IF(A60>=13,(1+Assumptions!B32)^(A60-12),1) -> 46047.265 | K60: =Assumptions!B26*IF(A60>=13,(1+Assumptions!B32)^(A60-12),1) -> 34535.449 | L60: =Assumptions!B27*IF(A60>=13,(1+Assumptions!B32)^(A60-12),1) -> 23023.633 | M60: =IF(A60>=13,Assumptions!B28*IF(A60>=13,(1+Assumptions!B32)^(A60-12),1),0) -> 172677.24 | N60: =Assumptions!B29*IF(A60>=13,(1+Assumptions!B32)^(A60-12),1) -> 23023.633 | O60: =SUM(I60:N60) -> 471984.47 | P60: =H60-O60 -> 213273.92 | Q60: =Q59+P60 -> 4570811.9 | R60: =IF(Q60>=0,"YES","No") -> YES
A61: 60 | B61: =ROUNDUP(A61/12,0) -> 5 | C61: ="Month "&A61 -> Month 60 | D61: =D60*(1+IF(B61=1,Assumptions!B14,Assumptions!B15)) -> 789.84679 | E61: =D61*Assumptions!B16 -> 473908.07 | F61: =F60*(1+Assumptions!B20) -> 719.48384 | G61: =F61*Assumptions!B21 -> 215845.15 | H61: =E61+G61 -> 689753.23 | I61: =Assumptions!B24*IF(A61>=13,(1+Assumptions!B32)^(A61-12),1) -> 173195.28 | J61: =Assumptions!B25*IF(A61>=13,(1+Assumptions!B32)^(A61-12),1) -> 46185.407 | K61: =Assumptions!B26*IF(A61>=13,(1+Assumptions!B32)^(A61-12),1) -> 34639.055 | L61: =Assumptions!B27*IF(A61>=13,(1+Assumptions!B32)^(A61-12),1) -> 23092.704 | M61: =IF(A61>=13,Assumptions!B28*IF(A61>=13,(1+Assumptions!B32)^(A61-12),1),0) -> 173195.28 | N61: =Assumptions!B29*IF(A61>=13,(1+Assumptions!B32)^(A61-12),1) -> 23092.704 | O61: =SUM(I61:N61) -> 473400.42 | P61: =H61-O61 -> 216352.8 | Q61: =Q60+P61 -> 4787164.7 | R61: =IF(Q61>=0,"YES","No") -> YES

Sheet Annual Summary
A1: Year | B1: MM Transactions (total) | C1: Commission Revenue | D1: Airtime Transactions (total) | E1: Airtime Revenue | F1: Total Revenue | G1: Total Costs | H1: Net Profit | I1: Cumulative Net Cash Position (Year-end)
A2: 1 | B2: =SUM('Monthly Model'!D2:D13) -> 6706.0449 | C2: =SUM('Monthly Model'!E2:E13) -> 4023626.9 | D2: =SUM('Monthly Model'!F2:F13) -> 5073.0012 | E2: =SUM('Monthly Model'!G2:G13) -> 1521900.4 | F2: =SUM('Monthly Model'!H2:H13) -> 5545527.3 | G2: =SUM('Monthly Model'!O2:O13) -> 3120000 | H2: =SUM('Monthly Model'!P2:P13) -> 2425527.3 | I2: ='Monthly Model'!Q13 -> -2574472.7
A3: 2 | B3: =SUM('Monthly Model'!D14:D25) -> 7707.205 | C3: =SUM('Monthly Model'!E14:E25) -> 4624323 | D3: =SUM('Monthly Model'!F14:F25) -> 5716.3847 | E3: =SUM('Monthly Model'!G14:G25) -> 1714915.4 | F3: =SUM('Monthly Model'!H14:H25) -> 6339238.4 | G3: =SUM('Monthly Model'!O14:O25) -> 5017003.3 | H3: =SUM('Monthly Model'!P14:P25) -> 1322235.1 | I3: ='Monthly Model'!Q25 -> -1252237.6
A4: 3 | B4: =SUM('Monthly Model'!D26:D37) -> 8182.5685 | C4: =SUM('Monthly Model'!E26:E37) -> 4909541.1 | D4: =SUM('Monthly Model'!F26:F37) -> 6441.3654 | E4: =SUM('Monthly Model'!G26:G37) -> 1932409.6 | F4: =SUM('Monthly Model'!H26:H37) -> 6841950.7 | G4: =SUM('Monthly Model'!O26:O37) -> 5200625.5 | H4: =SUM('Monthly Model'!P26:P37) -> 1641325.2 | I4: ='Monthly Model'!Q37 -> 389087.59
A5: 4 | B5: =SUM('Monthly Model'!D38:D49) -> 8687.2514 | C5: =SUM('Monthly Model'!E38:E49) -> 5212350.9 | D5: =SUM('Monthly Model'!F38:F49) -> 7258.2918 | E5: =SUM('Monthly Model'!G38:G49) -> 2177487.5 | F5: =SUM('Monthly Model'!H38:H49) -> 7389838.4 | G5: =SUM('Monthly Model'!O38:O49) -> 5390968.3 | H5: =SUM('Monthly Model'!P38:P49) -> 1998870.1 | I5: ='Monthly Model'!Q49 -> 2387957.7
A6: 5 | B6: =SUM('Monthly Model'!D50:D61) -> 9223.0621 | C6: =SUM('Monthly Model'!E50:E61) -> 5533837.3 | D6: =SUM('Monthly Model'!F50:F61) -> 8178.8248 | E6: =SUM('Monthly Model'!G50:G61) -> 2453647.5 | F6: =SUM('Monthly Model'!H50:H61) -> 7987484.7 | G6: =SUM('Monthly Model'!O50:O61) -> 5588277.6 | H6: =SUM('Monthly Model'!P50:P61) -> 2399207.1 | I6: ='Monthly Model'!Q61 -> 4787164.7
A7: TOTAL / 5-YR | B7: =SUM(B2:B6) -> 40506.132 | C7: =SUM(C2:C6) -> 24303679 | D7: =SUM(D2:D6) -> 32667.868 | E7: =SUM(E2:E6) -> 9800360.4 | F7: =SUM(F2:F6) -> 34104039 | G7: =SUM(G2:G6) -> 24316875 | H7: =SUM(H2:H6) -> 9787164.7 | I7: ='Monthly Model'!Q61 -> 4787164.7

Sheet Break-Even Analysis
A1: Break-Even Analysis — Mobile Money & Airtime Kiosk
A3: Total Initial Investment (Starting Capital) | B3: =Assumptions!B10 -> 5000000
A4: Average Net Profit per Month (Year 1) | B4: =AVERAGE('Monthly Model'!P2:P13) -> 202127.27
A5: Simple Break-even (months), constant Year-1 profit | B5: =B3/B4 -> 24.736889
A7: Break-even Month (from cumulative cash position, dynamic model) | B7: =IFERROR(INDEX('Monthly Model'!A2:A61,MATCH(TRUE(),INDEX('Monthly Model'!Q2:Q61>=0,0),0)),"Not reached within 60 months") -> 34
A8: Break-even Year | B8: =ROUNDUP(B7/12,0) -> 3
A10: Interpretation
A11: The break-even point is the month at which the Cumulative Net Cash Position (Monthly Model, column Q) crosses from negative to zero/positive — i.e. the accumulated profit exactly repays the starting capital in row 3. From that month onward, every shilling of net profit is 'clean' profit for the investor.
